Workbook

Sheet Intro
B7: GHG Emission Inventory and Carbon Footprint of MSC Complex
E9: GHG Atlas MSC | K9: File Name:
E10: 2.2 | K10: Version:
E11: MSC | K11: Owner:
H12: Behineh Sazan Sanat Tasisat | J12: Shayan Seif | K12: Developer:
E13: 2025 August | K13: Date:
B14: This electronic file is developed to facilitate data management and reporting for MSC Complex GHG Inventory (Section 1) and Carbon Footprint of Products (Section 2).
B18: 1. Data shall be complete and accurate to ensure the accountability of the results.
B21: 2. Units of all input data shall be checked with the required measurement system.
B24: 3. Section 1 contains all MSC areas for GHG Inventory based on ISO 14064-1:2018.
B27: 4. Section 2 contains all MSC products for Carbon Footprinting based on ISO 14067:2018.
J30: 5. Legends of cells:
D31: Cells that has to be filled by user
D32: Cells that can be modified by user
D33: Cells that reports the results of calculations
D34: Notes and guidance
J35: 6. User information:
B37: Date of completion: | E37: User Name: | H37: Title: | K37: Contact information:
B39: 7. Notes: User can add notes here.

Sheet Unit List
B7: List of Unit Processes and Cost Centers
B8: Cost Center Code | C8: Cost Center | D8: Unit Process | E8: Area | F8: Area Code
B9: 1107 | C9: Raw Material Maintenance | D9: - | E9: Iron Making | F9: 1
B10: 1110 | C10: Iron Ore and Pellet Yard | D10: Yard | E10: Iron Making | F10: 1
B11: 1120 | C11: Limestone Calcination Plant | D11: Lime Making | E11: Iron Making | F11: 1
B12: 1130 | C12: Lime Hydration Plant | D12: Lime Hydration | E12: Iron Making | F12: 1
B13: 1140 | C13: Dolomite Plant | D13: Dolomite Making | E13: Iron Making | F13: 1
B14: 1207 | C14: Pelletizing Maintenance | D14: - | E14: Iron Making | F14: 1
B15: 1210 | C15: Pelletizing Plant | D15: Pelletizing | E15: Iron Making | F15: 1
B16: 1307 | C16: Direct Reduction 1 Maintenance | D16: - | E16: Iron Making | F16: 1
B17: 1310 | C17: Direct Reduction 1 | D17: Direct Reduction | E17: Iron Making | F17: 1
B18: 1315 | C18: Direct Reduction 2 | D18: Direct Reduction | E18: Iron Making | F18: 1
B19: 1317 | C19: Direct Reduction 2 Maintenance | D19: - | E19: Iron Making | F19: 1
B20: 1320 | C20: Material Handling of Direct Reduction 1 | D20: Direct Reduction | E20: Iron Making | F20: 1
... B241: 9950 | C241: Mining Affairs | D241: - | E241: TAS | F241: 9

Sheet Settings
B7: Year
B8: 1403 | C8: 2024
B11: Parameters
B12: Parameters | D12: Value | E12: Farsi Description | G12: Source
B13: Working hours (hrs/yr) | D13: 8760 | E13: تعداد ساعت کاری در سال (hrs/yr) | G13: MSC
B14: Working days for Shift Employees | D14: 365 | E14: تعداد روزهای کاری پرسنل شیفت در سال | G14: MSC
B15: Working days for Day Employees | D15: 250 | E15: تعداد روزهای کاری پرسنل روز کار در سال | G15: MSC
B16: Methane weight percent in natural gas | D16: 0.9028 | E16: درصد وزنی متان در گاز طبیعی | G16: 1
B17: Dollar to Rial exchange rate | D17: 373005 | E17: نرخ برابری دلار به ریال (متوسط نرخ موزون) | G17: 2
G18: Source 1: Chemical composition of natural gas delivered to MSC.
G19: Source 2: https://cbi.ir/simplelist/30450.aspx
B22: GWPs
B23: CO2 | C23: CH4 (C,B) | D23: N2O | E23: SF6 | F23: CFC-12 | G23: CH4 (F,V)
B24: 1 | C24: 27 | D24: 273 | E24: 24300 | F24: 12500 | G24: 29.8
G25: Source: IPCC Sixth Assessment Report (AR6).
B28: LHV of fuels
B29: Fuel type | C29: LHV | D29: Unit | E29: Source | F29: Unit | G29: Notes
B30: Natural Gas | C30: 15 | D30: GJ/kNm3 | E30: 1 | F30: kNm3
B31: Gas oil | C31: 0.01 | D31: GJ/Lit | E31: 2 | F31: Lit
B32: Methane | C32: 5 | D32: GJ/ton | E32: 3 | F32: ton
B33: Butane | C33: 4 | D33: GJ/ton | E33: 3 | F33: ton
B34: Acetylene | C34: 5 | D34: GJ/ton | E34: 3 | F34: ton
B35: Oil | C35: 0.0357 | D35: GJ/Lit | E35: 2 | F35: Lit
B36: Others | D36: GJ/SCM
F37: Source 1: Calculation based on chemical composition of natural gas delivered to MSC.
B38: Source 2: API Compendium of Greenhouse Gas Emissions Methodologies for the Oil and Natural Gas Industry, 2009.
F40: Source 3: https://www.engineeringtoolbox.com/fuels-higher-calorific-values-d_169.html
B43: EFs: Fuel Combustion
B44: Fuel type | C44: EF- (t/GJ) | F44: Source
C45: CO2 | D45: CH4 | E45: N2O
B46: Natural Gas | C46: 0.0561 | D46: 1e-06 | E46: 1e-07 | F46: 1
B47: Gas oil | C47: 0.0741 | D47: 3e-06 | E47: 6e-07 | F47: 1
B48: Methane | C48: 7 | D48: 1e-06 | E48: 1e-07 | F48: 4
B49: Butane | C49: 6 | D49: 2.8e-06 | E49: 5.6e-07 | F49: 3
B50: Acetylene | C50: 6 | D50: 0 | E50: 0 | F50: 2
B51: Oil | C51: 7 | D51: 3e-06 | E51: 6e-07 | F51: 1
B52: Others
F53: Source 1: 2006 IPCC Guidelines for National Greenhouse Gas Inventories.
F54: Source 2: Methodology for reporting B.C. public sector greenhouse gas emissions, 2011.
F55: Source 3: Emission Factors for Greenhouse Gas Inventories, 2014.
F56: Source 4: Stoichiometry for CO2 EF and similarity to NG for CH4 and N2O.
B59: EF: Employee Commuting
B60: Cat. | C60: Vehicle type | D60: (tCO2/km) | E60: (tCH4/km) | F60: (tN2O/km)
B61: Employee Commuting | C61: Car | D61: 0.00010873996 | E61: 3.106856e-12 | F61: 1.8641136e-12
C62: Mini Bus | D62: 0.00059340949 | E62: 1.6155651e-11 | F62: 1.4291537e-11
C63: Bus | D63: 0.00077484988 | E63: 6.8350831e-12 | F63: 2.1747992e-11
B64: Source: Calculating GHG Emissions from Mobile Combustion, V2.7, GHG Protocol, 2024.
B67: EF: Business Travels
B68: Cat. | C68: Vehicle type | D68: (tCO2/km/person) | E68: (tCH4/km/person) | F68: (tN2O/km/person) | G68: Notes | I68: Notes
B69: Business Travels | C69: Car | D69: 0.00010873996 | E69: 3.106856e-12 | F69: 1.8641136e-12
C70: Bus | D70: 4 | E70: 0 | F70: 1.3048795e-09
C71: Air - Short Haul | D71: 0.00012862384 | E71: 3.9767756e-09 | F71: 4.1010499e-09 | G71: < 300 miles | I71: < 482 kms
C72: Air - Medium Haul | D72: 8.0156884e-05 | E72: 3.7282272e-10 | F72: 2.5476219e-09 | G72: >= 300 miles and < 2300 miles | I72: >= 482 kms and < 3701 kms
C73: Air - Long Haul | D73: 0.0001012835 | E73: 3.7282272e-10 | F73: 3.2311302e-09 | G73: 2300 miles < | I73: 3701 kms <
C74: Train | D74: 7.0214945e-05 | E74: 5.716615e-09 | F74: 1.6155651e-09
B75: Source: Calculating GHG Emissions from Mobile Combustion, V2.7, GHG Protocol, 2024.
B78: EF: Material Transportation
B79: Cat. | C79: Transport type | D79: (tCO2/km/ton) | E79: (tCH4/km/ton) | F79: (tN2O/km/ton)
B80: Material Transportation | C80: Road | D80: 0.00011507067 | E80: 1.0274167e-09 | F80: 3.2192391e-09
C81: Rail | D81: 1.5068779e-05 | E81: 1.1644056e-09 | F81: 3.4247225e-10
C82: Marine | D82: 5.6165448e-05 | E82: 2.232919e-08 | F82: 1.4383834e-09
C83: Air | D83: 0.00061987477 | E83: 0 | F83: 1.9109951e-08
B84: Source: Calculating GHG Emissions from Mobile Combustion, V2.7, GHG Protocol, 2024.
B87: EF: On-Site Transportation
B88: Cat. | C88: Fuel type | D88: (tCO2/L) | E88: (tCH4/L) | F88: (tN2O/L)
B89: On-Site Transportation | C89: Petrol | D89: 0.00233955 | E89: 2.7333333e-07 | F89: 2.2528302e-08
C90: Gas oil | D90: 0.00272417 | E90: 1.05e-07 | F90: 1.06e-07
C91: CNG | D91: 0.00044855 | E91: 2.2333333e-08 | F91: 7.5471698e-10
C92: 1. DEFRA-UK Government GHG Conversion Factors for Company Reporting. 2024.
B95: EF: Waste Management
B96: Waste Type | C96: Sale | D96: Landfill | E96: Reference
C97: (tCO2e/ton) | D97: (tCO2e/ton)
B98: Metal | C98: 0.00641061 | D98: 0.00888386 | E98: 1
B99: Non-Metal | C99: 0.00098485 | D99: 0.01951726 | E99: 1
B100: Plastic | C100: 0.00641061 | D100: 0.00888386 | E100: 1
B105: 1. DEFRA-UK Government GHG Conversion Factors for Company Reporting. 2024.
B108: EF: Electricity Generation (gr/kWh)
B109: Powerplant type | C109: CO2 | D109: CH4 | E109: N2O | F109: (tCO2e/kWh) | G109: Powerplant type
B110: Government Average | C110: 722.755 | D110: 0.017 | E110: 0.003 | F110: =(C110*$B$24+D110*$C$24+E110*$D$24)/1000000 -> 0.000724033 | G110: میانگین وزارت نیرو
B111: Private Average | C111: 656.593 | D111: 0.013 | E111: 0.002 | F111: =(C111*$B$24+D111*$C$24+E111*$D$24)/1000000 -> 0.00065749 | G111: میانگین بخش خصوصی
B112: Total Average | C112: 687.342 | D112: 14 | E112: 0.002 | F112: =(C112*$B$24+D112*$C$24+E112*$D$24)/1000000 -> 0.001065888 | G112: میانگین کل کشور
B113: Direct Contract | C113: 619.741 | D113: 12 | E113: 0.002 | F113: =(C113*$B$24+D113*$C$24+E113*$D$24)/1000000 -> 0.000944287 | G113: خرید برق دوجانبه 1
B114: Solar | C114: 0.0803154 | D114: 0 | E114: 0 | F114: =(C114*$B$24+D114*$C$24+E114*$D$24)/1000000 -> 8.03154e-08 | G114: نیروگاه خورشیدی 2
B115: Wind | C115: 0 | D115: 0 | E115: 0 | F115: =(C115*$B$24+D115*$C$24+E115*$D$24)/1000000 -> 0 | G115: نیروگاه بادی
B116: MSC Production | C116: 0 | D116: 0 | E116: 0 | F116: =(C116*$B$24+D116*$C$24+E116*$D$24)/1000000 -> 0 | G116: نیروگاه‏های برق مبارکه
B117: منبع: ترازنامه انرژی سال 1401، معاونت امور برق و انرژی، وزارت نیروی جمهوری اسلامی ایران.
B118: 1) EF of Combined Cycle powerplant on private sector of Iran
B119: 2) Reference: ECOINVENT
B122: EF: Energy Related (Upstream)
B123: Energy type | C123: Unit | D123: EF | E123: Reference | G123: Notes
B124: Grid Electricity | C124: tCO2e/kWh | D124: 0.0001395 | E124: 2 | H124: Including both upstream and T/D loss emissions
B125: Natural Gas | C125: tCO2e/kNm3 | D125: 0.3366 | E125: 1
B126: Gas oil | C126: tCO2e/Lit | D126: 0.00062665 | E126: 1
B127: Petrol | C127: tCO2e/Lit | D127: 0.00060664 | E127: 1
B128: Methane | C128: tCO2e/ton | D128: 0.42316368 | E128: 1 | H128: Assumed like Natural Gas (converted per ton)
B129: Butane | C129: tCO2e/ton | D129: 0.34430947 | E129: 1
B130: Acetylene | C130: tCO2e/ton | D130: 0.30295197 | E130: 1 | H130: Assume like other petroleum gas
B131: Others
B132: 1. DEFRA-UK Government GHG Conversion Factors for Company Reporting. 2024.
B133: 2. IEA Life Cycle Upstream Emission Factors 2023 (Pilot Edition).
...

Sheet Data Quality
B7: Data Quality Sheet | I7: Data Quality Assessment | N7: Uncertainty Assessment
B8: Section | C8: Sheet Name | D8: Parameters | E8: Type of Data | G8: Notes/References | H8: Documents of MSC | I8: Technology | J8: Time | K8: Geography | L8: Completeness | M8: Reliability | N8: Type of Uncertainty | O8: Uncertainty Rank
E9: Primary Data | F9: Secondary Data
B10: Section 1: Emission Inventory | C10: Combustion | D10: Annual fuel consumption | G10: Site-specific | H10: Cost Center Documents. | N10: Parameter
D11: LHV of fuels | G11: Site-specific | H11: Chemical Composition of NG. | N11: Model
D12: Emission factors | G12: Refer to Setting Sheet to access references | N12: Parameter
C13: Vent | D13: Annual production | G13: Site-specific | H13: Cost Center Documents. | N13: Parameter
D14: Emission factors | G14: Refer to Setting Sheet to access references | N14: Parameter
C15: Fugitive | D15: Annual consumption | G15: Site-specific | H15: Cost Center Documents. | N15: Parameter
D16: Equipment count | G16: Site-specific | H16: P&IDs of facilities. | N16: Parameter
D17: Emission factors | G17: Refer to Setting Sheet to access references | N17: Parameter
D18: Control efficiency | G18: Site-specific | H18: Personnel interview. | N18: Scenario
C19: Electricity | D19: Electricity consumption | G19: Site-specific | H19: Cost Center Documents. | N19: Parameter
D20: Emission factors | G20: Refer to Setting Sheet to access references | N20: Parameter
D21: Distribution loss | G21: Refer to Setting Sheet to access references | N21: Parameter
C22: On-Site Tran. | D22: Annual fuel consumption | G22: Site-specific | H22: Cost Center Documents. | N22: Parameter
D23: Emission factors | G23: Refer to Setting Sheet to access references | N23: Parameter
C24: Upstream Tran. | D24: Origin | G24: Site-specific | H24: Transportation Reports. | N24: Parameter
D25: Distance | G25: Refer to Setting Sheet to access references | N25: Parameter
D26: Weight | G26: Site-specific | H26: Transportation Reports. | N26: Parameter
D27: Emission factors | G27: Refer to Setting Sheet to access references | N27: Parameter
C28: Downstream Tran. | D28: Destination | G28: Site-specific | H28: Transportation Reports. | N28: Parameter
D29: Distance | G29: Refer to Setting Sheet to access references | N29: Parameter
D30: Weight | G30: Site-specific | H30: Transportation Reports. | N30: Parameter
D31: Emission factors | G31: Refer to Setting Sheet to access references | N31: Parameter
C32: Employee Commuting | D32: Annual distance traveled | G32: Site-specific | H32: Transportation Reports. | N32: Parameter
D33: Emission factors | G33: Refer to Setting Sheet to access references | N33: Parameter
D34: Personnel count | G34: Site-specific | H34: Transportation Reports. | N34: Parameter
C35: Business Travel | D35: Annual distance traveled | G35: Site-specific | H35: Transportation Reports. | N35: Parameter
D36: Emission factors | G36: Refer to Setting Sheet to access references | N36: Parameter
D37: Travel counts | G37: Site-specific | H37: Transportation Reports. | N37: Parameter
C38: Purchased Material | D38: Annual consumption | G38: Site-specific | H38: Cost Center Documents. | N38: Parameter
D39: Emission factors | G39: Refer to Setting Sheet to access references | N39: Parameter
C40: Ancillary Input | D40: Annual consumption | G40: Site-specific | H40: Cost Center Documents. | N40: Parameter
D41: Emission factors | G41: Refer to Setting Sheet to access references | N41: Parameter
C42: Purchased Services | D42: Annual consumption | G42: Site-specific | H42: Cost Center Documents. | N42: Parameter
D43: Emission factors | G43: Refer to Setting Sheet to access references | N43: Parameter
C44: Waste | D44: Annual production | G44: Site-specific | H44: Waste Management Reports. | N44: Parameter
D45: Management approach | G45: Site-specific | H45: Personnel interview. | N45: Scenario
D46: Emission factors | G46: Refer to Setting Sheet to access references | N46: Parameter
C47: Wastewater | D47: Annual flow | G47: Site-specific | H47: Cost Center Documents. | N47: Parameter
D48: COD | G48: Site-specific | H48: Lab Tests. | N48: Parameter
D49: Constant parameters | G49: Refer to Setting Sheet to access references | N49: Scenario
C50: Energy Related | D50: Annual consumption | G50: Site-specific | H50: Cost Center Documents. | N50: Parameter
D51: Emission factors | G51: Refer to Setting Sheet to access references | N51: Parameter
B52: Section 2: Carbon Footprint of Products | C52: Steam | D52: Annual consumption | G52: Site-specific | H52: Cost Center Documents. | N52: Parameter
D53: Emission factors | G53: Site-specific | H53: Calculations in this study. | N53: Parameter
C54: Air | D54: Annual consumption | G54: Site-specific | H54: Cost Center Documents. | N54: Parameter
D55: Emission factors | G55: Site-specific | H55: Calculations in this study. | N55: Parameter
C56: Oxygen | D56: Annual consumption | G56: Site-specific | H56: Cost Center Documents. | N56: Parameter
D57: Emission factors | G57: Site-specific | H57: Calculations in this study. | N57: Parameter
C58: Nitrogen | D58: Annual consumption | G58: Site-specific | H58: Cost Center Documents. | N58: Parameter
D59: Emission factors | G59: Site-specific | H59: Calculations in this study. | N59: Parameter
C60: Argon | D60: Annual consumption | G60: Site-specific | H60: Cost Center Documents. | N60: Parameter
D61: Emission factors | G61: Site-specific | H61: Calculations in this study. | N61: Parameter
C62: Water | D62: Annual consumption | G62: Site-specific | H62: Cost Center Documents. | N62: Parameter
D63: Emission factors | G63: Site-specific | H63: Calculations in this study. | N63: Parameter
C64: Mix Electricity | D64: Annual consumption | G64: Site-specific | H64: Cost Center Documents. | N64: Parameter
D65: Emission factors | G65: Site-specific | H65: Calculations in this study. | N65: Parameter
C66: Upstream CF | D66: Emission factors | G66: Refer to table inside sheet to access references | N66: Parameter
C67: Utility CF | D67: Annual production | G67: Site-specific | H67: Cost Center Documents. | N67: Parameter
D68: Allocation factors | G68: Based on assumptions or mass ratio | N68: Scenario
C69: Units CF | D69: Annual production | G69: Site-specific | H69: Cost Center Documents. | N69: Parameter
D70: Allocation factors | G70: Based on assumptions or mass ratio | N70: Scenario
I73: Scoring Criteria Breakdown:
I74: Technology | J74: Time | K74: Geography | L74: Completeness | M74: Reliability
I75: Very good: Data generated using the same technology. | J75: Very good: Data is less than 3 years old. | K75: Very good: Data from the same area. | L75: Very good: Data covers all relevant process sites over an adequate time period. | M75: Very good: Verified data based on measurements.
I76: Good: Data from a similar but different technology. | J76: Good: Data is less than 6 years old. | K76: Good: Data from a similar area. | L76: Good: Data covers >50% of sites for an adequate time period. | M76: Good: Verified data partly based on assumptions or non-verified data based on measurements.
I77: Fair: Data from a different technology. | J77: Fair: Data is less than 10 years old. | K77: Fair: Data from a different area. | L77: Fair: Data covers <50% of sites or is from >50% of sites but for a shorter time. | M77: Fair: Non-verified data partly based on assumptions or expert estimates.
I78: Poor: Technology is unknown. | J78: Poor: Data is more than 10 years old or age is unknown. | K78: Poor: Area is unknown. | L78: Poor: Data covers <50% of sites for a short time, or representativeness is unknown. | M78: Poor: Non-qualified estimate.

Sheet Sensitivity
B7: Sensitivity Analysis
B8: Parameters with high uncertainty | C8: Selected case in the study | D8: Scenario | E8: Description | F8: Total GHG Emissions (tCO2e) | G8: Variation of Total Emissions | H8: Carbon Footprint of "Slab" (tCO2e/t) | I8: Variation of CFP | J8: Remarks
D9: Final | E9: The present conditions of study | F9: ='Tables & Graphs'!E30 -> 20162467 | H9: ='Units CF'!E105 -> 2.3301682

Sheet Inventory
B7: GHG Emission Inventory
B8: No. | C8: Area | D8: Area Code | E8: Emission Source | F8: Category | G8: Sign | H8: Category No. | I8: Scope | J8: Emission Code | K8: CO2 (tCO2/y) | L8: CH4 (tCH4/y) | M8: N2O (tN2O/y) | N8: SF6 (tSF6/y) | O8: Emission (tCO2e/y) | P8: Emission Share (%)
B9: 1 | C9: Iron Making | D9: =VLOOKUP(C9,Settings!$B$341:C364,2,FALSE) -> 1 | E9: Fossil Fuel Combustion | F9: Combustion | G9: =VLOOKUP(F9,Settings!$B$163:D186,3,FALSE) -> C | H9: =VLOOKUP(F9,Settings!$B$163:D186,2,FALSE) -> 1 | I9: =VLOOKUP(F9,Settings!$B$163:F180,5,FALSE) -> 1 | J9: =_xlfn.TEXTJOIN("-",,D9,G9,B9) -> 1-C-1 | K9: =VLOOKUP(J9,Combustion!$J$103:$P$110,4,FALSE) -> 126420.9 | L9: =VLOOKUP(J9,Combustion!$J$103:$P$110,5,FALSE) -> 2.2524975 | M9: =VLOOKUP(J9,Combustion!$J$103:$P$110,6,FALSE) -> 0.22525242 | N9: 0 | O9: =VLOOKUP(J9,Combustion!$J$103:$P$110,7,FALSE) -> 126543.21 | P9: =O9/$O$195 -> 0.0062761768
B10: 2 | C10: Steel Making | D10: =VLOOKUP(C10,Settings!$B$341:C371,2,FALSE) -> 2 | E10: Fossil Fuel Combustion | F10: Combustion | G10: =VLOOKUP(F10,Settings!$B$163:D195,3,FALSE) -> C | H10: =VLOOKUP(F10,Settings!$B$163:D195,2,FALSE) -> 1 | I10: =VLOOKUP(F10,Settings!$B$163:F180,5,FALSE) -> 1 | J10: =_xlfn.TEXTJOIN("-",,D10,G10,B10) -> 2-C-2 | K10: =VLOOKUP(J10,Combustion!$J$103:$P$110,4,FALSE) -> 34851.215 | L10: =VLOOKUP(J10,Combustion!$J$103:$P$110,5,FALSE) -> 0.61872455 | M10: =VLOOKUP(J10,Combustion!$J$103:$P$110,6,FALSE) -> 0.061879201 | N10: 0 | O10: =VLOOKUP(J10,Combustion!$J$103:$P$110,7,FALSE) -> 34884.813 | P10: =O10/$O$195 -> 0.0017301858
B11: 3 | C11: Hot Rolling | D11: =VLOOKUP(C11,Settings!$B$341:C384,2,FALSE) -> 3 | E11: Fossil Fuel Combustion | F11: Combustion | G11: =VLOOKUP(F11,Settings!$B$163:D202,3,FALSE) -> C | H11: =VLOOKUP(F11,Settings!$B$163:D201,2,FALSE) -> 1 | I11: =VLOOKUP(F11,Settings!$B$163:F181,5,FALSE) -> 1 | J11: =_xlfn.TEXTJOIN("-",,D11,G11,B11) -> 3-C-3 | K11: =VLOOKUP(J11,Combustion!$J$103:$P$110,4,FALSE) -> 175384.09 | L11: =VLOOKUP(J11,Combustion!$J$103:$P$110,5,FALSE) -> 3.125112 | M11: =VLOOKUP(J11,Combustion!$J$103:$P$110,6,FALSE) -> 0.31251433 | N11: 0 | O11: =VLOOKUP(J11,Combustion!$J$103:$P$110,7,FALSE) -> 175553.78 | P11: =O11/$O$195 -> 0.0087069594
B12: 4 | C12: Cold Rolling | D12: =VLOOKUP(C12,Settings!$B$341:C428,2,FALSE) -> 4 | E12: Fossil Fuel Combustion | F12: Combustion | G12: =VLOOKUP(F12,Settings!$B$163:D377,3,FALSE) -> C | H12: =VLOOKUP(F12,Settings!$B$163:D376,2,FALSE) -> 1 | I12: =VLOOKUP(F12,Settings!$B$163:F213,5,FALSE) -> 1 | J12: =_xlfn.TEXTJOIN("-",,D12,G12,B12) -> 4-C-4 | K12: =VLOOKUP(J12,Combustion!$J$103:$P$110,4,FALSE) -> 27783.999 | L12: =VLOOKUP(J12,Combustion!$J$103:$P$110,5,FALSE) -> 0.4891918 | M12: =VLOOKUP(J12,Combustion!$J$103:$P$110,6,FALSE) -> 0.04893549 | N12: 0 | O12: =VLOOKUP(J12,Combustion!$J$103:$P$110,7,FALSE) -> 27810.566 | P12: =O12/$O$195 -> 0.0013793236
B13: 5 | C13: Utility | D13: =VLOOKUP(C13,Settings!$B$341:C461,2,FALSE) -> 5 | E13: Fossil Fuel Combustion | F13: Combustion | G13: =VLOOKUP(F13,Settings!$B$163:D395,3,FALSE) -> C | H13: =VLOOKUP(F13,Settings!$B$163:D395,2,FALSE) -> 1 | I13: =VLOOKUP(F13,Settings!$B$163:F214,5,FALSE) -> 1 | J13: =_xlfn.TEXTJOIN("-",,D13,G13,B13) -> 5-C-5 | K13: =VLOOKUP(J13,Combustion!$J$103:$P$110,4,FALSE) -> 827049.63 | L13: =VLOOKUP(J13,Combustion!$J$103:$P$110,5,FALSE) -> 14.948705 | M13: =VLOOKUP(J13,Combustion!$J$103:$P$110,6,FALSE) -> 1.5317712 | N13: 0 | O13: =VLOOKUP(J13,Combustion!$J$103:$P$110,7,FALSE) -> 827871.42 | P13: =O13/$O$195 -> 0.041060026
B14: 6 | C14: Transportation | D14: =VLOOKUP(C14,Settings!$B$341:C503,2,FALSE) -> 6 | E14: Fossil Fuel Combustion | F14: Combustion | G14: =VLOOKUP(F14,Settings!$B$163:D425,3,FALSE) -> C | H14: =VLOOKUP(F14,Settings!$B$163:D424,2,FALSE) -> 1 | I14: =VLOOKUP(F14,Settings!$B$163:F215,5,FALSE) -> 1 | J14: =_xlfn.TEXTJOIN("-",,D14,G14,B14) -> 6-C-6 | K14: =VLOOKUP(J14,Combustion!$J$103:$P$110,4,FALSE) -> 2.376 | L14: =VLOOKUP(J14,Combustion!$J$103:$P$110,5,FALSE) -> 1.1088e-06 | M14: =VLOOKUP(J14,Combustion!$J$103:$P$110,6,FALSE) -> 2.2176e-07 | N14: 0 | O14: =VLOOKUP(J14,Combustion!$J$103:$P$110,7,FALSE) -> 2.3760905 | P14: =O14/$O$195 -> 1.1784721e-07
B15: 7 | C15: Maintenance | D15: =VLOOKUP(C15,Settings!$B$341:C521,2,FALSE) -> 7 | E15: Fossil Fuel Combustion | F15: Combustion | G15: =VLOOKUP(F15,Settings!$B$163:D443,3,FALSE) -> C | H15: =VLOOKUP(F15,Settings!$B$163:D442,2,FALSE) -> 1 | I15: =VLOOKUP(F15,Settings!$B$163:F216,5,FALSE) -> 1 | J15: =_xlfn.TEXTJOIN("-",,D15,G15,B15) -> 7-C-7 | K15: =VLOOKUP(J15,Combustion!$J$103:$P$110,4,FALSE) -> 13894.644 | L15: =VLOOKUP(J15,Combustion!$J$103:$P$110,5,FALSE) -> 0.24738219 | M15: =VLOOKUP(J15,Combustion!$J$103:$P$110,6,FALSE) -> 0.024738994 | N15: 0 | O15: =VLOOKUP(J15,Combustion!$J$103:$P$110,7,FALSE) -> 13908.077 | P15: =O15/$O$195 -> 0.00068980036
B16: 8 | C16: TAS | D16: =VLOOKUP(C16,Settings!$B$341:C530,2,FALSE) -> 9 | E16: Fossil Fuel Combustion | F16: Combustion | G16: =VLOOKUP(F16,Settings!$B$163:D452,3,FALSE) -> C | H16: =VLOOKUP(F16,Settings!$B$163:D451,2,FALSE) -> 1 | I16: =VLOOKUP(F16,Settings!$B$163:F217,5,FALSE) -> 1 | J16: =_xlfn.TEXTJOIN("-",,D16,G16,B16) -> 9-C-8 | K16: =VLOOKUP(J16,Combustion!$J$103:$P$110,4,FALSE) -> 90085.662 | L16: =VLOOKUP(J16,Combustion!$J$103:$P$110,5,FALSE) -> 1.6038621 | M16: =VLOOKUP(J16,Combustion!$J$103:$P$110,6,FALSE) -> 0.16039131 | N16: 0 | O16: =VLOOKUP(J16,Combustion!$J$103:$P$110,7,FALSE) -> 90172.753 | P16: =O16/$O$195 -> 0.0044723076
B17: 9 | C17: Iron Making | D17: =VLOOKUP(C17,Settings!$B$341:C850,2,FALSE) -> 1 | E17: Process emission (Vent) | F17: Vent | G17: =VLOOKUP(F17,Settings!$B$163:D772,3,FALSE) -> V | H17: =VLOOKUP(F17,Settings!$B$163:D771,2,FALSE) -> 1 | I17: =VLOOKUP(F17,Settings!$B$163:F199,5,FALSE) -> 1 | J17: =_xlfn.TEXTJOIN("-",,D17,G17,B17) -> 1-V-9 | K17: =VLOOKUP(J17,Vent!$K$24:$M$31,3,FALSE) -> 3866055.4 | L17: 0 | M17: 0 | N17: 0 | O17: =K17 -> 3866055.4 | P17: =O17/$O$195 -> 0.19174516
B18: 10 | C18: Steel Making | D18: =VLOOKUP(C18,Settings!$B$341:C851,2,FALSE) -> 2 | E18: Process emission (Vent) | F18: Vent | G18: =VLOOKUP(F18,Settings!$B$163:D773,3,FALSE) -> V | H18: =VLOOKUP(F18,Settings!$B$163:D772,2,FALSE) -> 1 | I18: =VLOOKUP(F18,Settings!$B$163:F200,5,FALSE) -> 1 | J18: =_xlfn.TEXTJOIN("-",,D18,G18,B18) -> 2-V-10 | K18: =VLOOKUP(J18,Vent!$K$24:$M$31,3,FALSE) -> 427613.9 | L18: 0 | M18: 0 | N18: 0 | O18: =K18 -> 427613.9 | P18: =O18/$O$195 -> 0.021208412
B19: 11 | C19: Hot Rolling | D19: =VLOOKUP(C19,Settings!$B$341:C849,2,FALSE) -> 3 | E19: Process emission (Vent) | F19: Vent | G19: =VLOOKUP(F19,Settings!$B$163:D771,3,FALSE) -> V | H19: =VLOOKUP(F19,Settings!$B$163:D770,2,FALSE) -> 1 | I19: =VLOOKUP(F19,Settings!$B$163:F201,5,FALSE) -> 1 | J19: =_xlfn.TEXTJOIN("-",,D19,G19,B19) -> 3-V-11 | K19: =VLOOKUP(J19,Vent!$K$24:$M$31,3,FALSE) -> 0 | L19: 0 | M19: 0 | N19: 0 | O19: =K19 -> 0 | P19: =O19/$O$195 -> 0
B20: 12 | C20: Cold Rolling | D20: =VLOOKUP(C20,Settings!$B$341:C852,2,FALSE) -> 4 | E20: Process emission (Vent) | F20: Vent | G20: =VLOOKUP(F20,Settings!$B$163:D774,3,FALSE) -> V | H20: =VLOOKUP(F20,Settings!$B$163:D773,2,FALSE) -> 1 | I20: =VLOOKUP(F20,Settings!$B$163:F239,5,FALSE) -> 1 | J20: =_xlfn.TEXTJOIN("-",,D20,G20,B20) -> 4-V-12 | K20: =VLOOKUP(J20,Vent!$K$24:$M$31,3,FALSE) -> 0 | L20: 0 | M20: 0 | N20: 0 | O20: =K20 -> 0 | P20: =O20/$O$195 -> 0
B21: 13 | C21: Utility | D21: =VLOOKUP(C21,Settings!$B$341:C951,2,FALSE) -> 5 | E21: Process emission (Vent) | F21: Vent | G21: =VLOOKUP(F21,Settings!$B$163:D853,3,FALSE) -> V | H21: =VLOOKUP(F21,Settings!$B$163:D852,2,FALSE) -> 1 | I21: =VLOOKUP(F21,Settings!$B$163:F560,5,FALSE) -> 1 | J21: =_xlfn.TEXTJOIN("-",,D21,G21,B21) -> 5-V-13 | K21: =VLOOKUP(J21,Vent!$K$24:$M$31,3,FALSE) -> 0 | L21: 0 | M21: 0 | N21: 0 | O21: =K21 -> 0 | P21: =O21/$O$195 -> 0
B22: 14 | C22: Transportation | D22: =VLOOKUP(C22,Settings!$B$341:C995,2,FALSE) -> 6 | E22: Process emission (Vent) | F22: Vent | G22: =VLOOKUP(F22,Settings!$B$163:D897,3,FALSE) -> V | H22: =VLOOKUP(F22,Settings!$B$163:D896,2,FALSE) -> 1 | I22: =VLOOKUP(F22,Settings!$B$163:F604,5,FALSE) -> 1 | J22: =_xlfn.TEXTJOIN("-",,D22,G22,B22) -> 6-V-14 | K22: =VLOOKUP(J22,Vent!$K$24:$M$31,3,FALSE) -> 0 | L22: 0 | M22: 0 | N22: 0 | O22: =K22 -> 0 | P22: =O22/$O$195 -> 0
B23: 15 | C23: Maintenance | D23: =VLOOKUP(C23,Settings!$B$341:C996,2,FALSE) -> 7 | E23: Process emission (Vent) | F23: Vent | G23: =VLOOKUP(F23,Settings!$B$163:D898,3,FALSE) -> V | H23: =VLOOKUP(F23,Settings!$B$163:D897,2,FALSE) -> 1 | I23: =VLOOKUP(F23,Settings!$B$163:F605,5,FALSE) -> 1 | J23: =_xlfn.TEXTJOIN("-",,D23,G23,B23) -> 7-V-15 | K23: =VLOOKUP(J23,Vent!$K$24:$M$31,3,FALSE) -> 0 | L23: 0 | M23: 0 | N23: 0 | O23: =K23 -> 0 | P23: =O23/$O$195 -> 0
B24: 16 | C24: TAS | D24: =VLOOKUP(C24,Settings!$B$341:C997,2,FALSE) -> 9 | E24: Process emission (Vent) | F24: Vent | G24: =VLOOKUP(F24,Settings!$B$163:D899,3,FALSE) -> V | H24: =VLOOKUP(F24,Settings!$B$163:D898,2,FALSE) -> 1 | I24: =VLOOKUP(F24,Settings!$B$163:F606,5,FALSE) -> 1 | J24: =_xlfn.TEXTJOIN("-",,D24,G24,B24) -> 9-V-16 | K24: =VLOOKUP(J24,Vent!$K$24:$M$31,3,FALSE) -> 0 | L24: 0 | M24: 0 | N24: 0 | O24: =K24 -> 0 | P24: =O24/$O$195 -> 0
B25: 17 | C25: Iron Making | D25: =VLOOKUP(C25,Settings!$B$341:C858,2,FALSE) -> 1 | E25: Methane fugitive emission | F25: Fugitive | G25: =VLOOKUP(F25,Settings!$B$163:D780,3,FALSE) -> F | H25: =VLOOKUP(F25,Settings!$B$163:D779,2,FALSE) -> 1 | I25: =VLOOKUP(F25,Settings!$B$163:F196,5,FALSE) -> 1 | J25: =_xlfn.TEXTJOIN("-",,D25,G25,B25) -> 1-F-17 | K25: 0 | L25: =VLOOKUP(J25,Fugitive!$I$115:$L$122,3,FALSE) -> 11.115437 | M25: 0 | N25: 0 | O25: =VLOOKUP(J25,Fugitive!$I$115:$L$122,4,FALSE) -> 331.24004 | P25: =O25/$O$195 -> 1.6428547e-05
B26: 18 | C26: Steel Making | D26: =VLOOKUP(C26,Settings!$B$341:C872,2,FALSE) -> 2 | E26: Methane fugitive emission | F26: Fugitive | G26: =VLOOKUP(F26,Settings!$B$163:D794,3,FALSE) -> F | H26: =VLOOKUP(F26,Settings!$B$163:D793,2,FALSE) -> 1 | I26: =VLOOKUP(F26,Settings!$B$163:F196,5,FALSE) -> 1 | J26: =_xlfn.TEXTJOIN("-",,D26,G26,B26) -> 2-F-18 | K26: 0 | L26: =VLOOKUP(J26,Fugitive!$I$115:$L$122,3,FALSE) -> 7.8187593 | M26: 0 | N26: 0 | O26: =VLOOKUP(J26,Fugitive!$I$115:$L$122,4,FALSE) -> 232.99903 | P26: =O26/$O$195 -> 1.1556077e-05
B27: 19 | C27: Hot Rolling | D27: =VLOOKUP(C27,Settings!$B$341:C875,2,FALSE) -> 3 | E27: Methane fugitive emission | F27: Fugitive | G27: =VLOOKUP(F27,Settings!$B$163:D797,3,FALSE) -> F | H27: =VLOOKUP(F27,Settings!$B$163:D796,2,FALSE) -> 1 | I27: =VLOOKUP(F27,Settings!$B$163:F196,5,FALSE) -> 1 | J27: =_xlfn.TEXTJOIN("-",,D27,G27,B27) -> 3-F-19 | K27: 0 | L27: =VLOOKUP(J27,Fugitive!$I$115:$L$122,3,FALSE) -> 5.923259 | M27: 0 | N27: 0 | O27: =VLOOKUP(J27,Fugitive!$I$115:$L$122,4,FALSE) -> 176.51312 | P27: =O27/$O$195 -> 8.7545398e-06
B28: 20 | C28: Cold Rolling | D28: =VLOOKUP(C28,Settings!$B$341:C859,2,FALSE) -> 4 | E28: Methane fugitive emission | F28: Fugitive | G28: =VLOOKUP(F28,Settings!$B$163:D781,3,FALSE) -> F | H28: =VLOOKUP(F28,Settings!$B$163:D780,2,FALSE) -> 1 | I28: =VLOOKUP(F28,Settings!$B$163:F197,5,FALSE) -> 1 | J28: =_xlfn.TEXTJOIN("-",,D28,G28,B28) -> 4-F-20 | K28: 0 | L28: =VLOOKUP(J28,Fugitive!$I$115:$L$122,3,FALSE) -> 8.1441224 | M28: 0 | N28: 0 | O28: =VLOOKUP(J28,Fugitive!$I$115:$L$122,4,FALSE) -> 242.69485 | P28: =O28/$O$195 -> 1.2036962e-05
B29: 21 | C29: Utility | D29: =VLOOKUP(C29,Settings!$B$341:C860,2,FALSE) -> 5 | E29: Methane fugitive emission | F29: Fugitive | G29: =VLOOKUP(F29,Settings!$B$163:D782,3,FALSE) -> F | H29: =VLOOKUP(F29,Settings!$B$163:D781,2,FALSE) -> 1 | I29: =VLOOKUP(F29,Settings!$B$163:F198,5,FALSE) -> 1 | J29: =_xlfn.TEXTJOIN("-",,D29,G29,B29) -> 5-F-21 | K29: 0 | L29: =VLOOKUP(J29,Fugitive!$I$115:$L$122,3,FALSE) -> 24.914493 | M29: 0 | N29: 0 | O29: =VLOOKUP(J29,Fugitive!$I$115:$L$122,4,FALSE) -> 742.45189 | P29: =O29/$O$195 -> 3.6823465e-05
B30: 22 | C30: Transportation | D30: =VLOOKUP(C30,Settings!$B$341:C878,2,FALSE) -> 6 | E30: Methane fugitive emission | F30: Fugitive | G30: =VLOOKUP(F30,Settings!$B$163:D800,3,FALSE) -> F | H30: =VLOOKUP(F30,Settings!$B$163:D799,2,FALSE) -> 1 | I30: =VLOOKUP(F30,Settings!$B$163:F198,5,FALSE) -> 1 | J30: =_xlfn.TEXTJOIN("-",,D30,G30,B30) -> 6-F-22 | K30: 0 | L30: =VLOOKUP(J30,Fugitive!$I$115:$L$122,3,FALSE) -> 0 | M30: 0 | N30: 0 | O30: =VLOOKUP(J30,Fugitive!$I$115:$L$122,4,FALSE) -> 0 | P30: =O30/$O$195 -> 0
B31: 23 | C31: Maintenance | D31: =VLOOKUP(C31,Settings!$B$341:C861,2,FALSE) -> 7 | E31: Methane fugitive emission | F31: Fugitive | G31: =VLOOKUP(F31,Settings!$B$163:D783,3,FALSE) -> F | H31: =VLOOKUP(F31,Settings!$B$163:D782,2,FALSE) -> 1 | I31: =VLOOKUP(F31,Settings!$B$163:F236,5,FALSE) -> 1 | J31: =_xlfn.TEXTJOIN("-",,D31,G31,B31) -> 7-F-23 | K31: 0 | L31: =VLOOKUP(J31,Fugitive!$I$115:$L$122,3,FALSE) -> 1.575518 | M31: 0 | N31: 0 | O31: =VLOOKUP(J31,Fugitive!$I$115:$L$122,4,FALSE) -> 46.950437 | P31: =O31/$O$195 -> 2.3286058e-06
B32: 24 | C32: TAS | D32: =VLOOKUP(C32,Settings!$B$341:C862,2,FALSE) -> 9 | E32: Methane fugitive emission | F32: Fugitive | G32: =VLOOKUP(F32,Settings!$B$163:D784,3,FALSE) -> F | H32: =VLOOKUP(F32,Settings!$B$163:D783,2,FALSE) -> 1 | I32: =VLOOKUP(F32,Settings!$B$163:F238,5,FALSE) -> 1 | J32: =_xlfn.TEXTJOIN("-",,D32,G32,B32) -> 9-F-24 | K32: 0 | L32: =VLOOKUP(J32,Fugitive!$I$115:$L$122,3,FALSE) -> 2.3446234 | M32: 0 | N32: 0 | O32: =VLOOKUP(J32,Fugitive!$I$115:$L$122,4,FALSE) -> 69.869776 | P32: =O32/$O$195 -> 3.4653387e-06
B33: 25 | C33: Utility | D33: =VLOOKUP(C33,Settings!$B$341:C952,2,FALSE) -> 5 | E33: SF6 fugitive emission | F33: Fugitive | G33: =VLOOKUP(F33,Settings!$B$163:D854,3,FALSE) -> F | H33: =VLOOKUP(F33,Settings!$B$163:D853,2,FALSE) -> 1 | I33: =VLOOKUP(F33,Settings!$B$163:F561,5,FALSE) -> 1 | J33: =_xlfn.TEXTJOIN("-",,D33,G33,B33) -> 5-F-25 | K33: 0 | L33: 0 | M33: 0 | N33: =Fugitive!K49 -> 0.4 | O33: =Fugitive!L49 -> 9720 | P33: =O33/$O$195 -> 0.00048208387
B34: 26 | C34: Maintenance | D34: =VLOOKUP(C34,Settings!$B$341:C983,2,FALSE) -> 7 | E34: CO2 fire extinguishers | F34: Fugitive | G34: =VLOOKUP(F34,Settings!$B$163:D885,3,FALSE) -> F | H34: =VLOOKUP(F34,Settings!$B$163:D884,2,FALSE) -> 1 | I34: =VLOOKUP(F34,Settings!$B$163:F592,5,FALSE) -> 1 | J34: =_xlfn.TEXTJOIN("-",,D34,G34,B34) -> 7-F-26 | K34: =VLOOKUP(J34,Fugitive!$B$49:$M$67,11,FALSE) -> 46.864 | L34: 0 | M34: 0 | N34: 0 | O34: =VLOOKUP(J34,Fugitive!B49:L67,11,FALSE) -> 46.864 | P34: =O34/$O$195 -> 2.3243188e-06
B35: 27 | C35: Iron Making | D35: =VLOOKUP(C35,Settings!$B$341:C965,2,FALSE) -> 1 | E35: Non-energy product use (oil) | F35: Fugitive | G35: =VLOOKUP(F35,Settings!$B$163:D867,3,FALSE) -> F | H35: =VLOOKUP(F35,Settings!$B$163:D866,2,FALSE) -> 1 | I35: =VLOOKUP(F35,Settings!$B$163:F574,5,FALSE) -> 1 | J35: =_xlfn.TEXTJOIN("-",,D35,G35,B35) -> 1-F-27 | K35: =VLOOKUP(J35,Fugitive!$B$75:$L$90,11,FALSE) -> 90.114464 | L35: 0 | M35: 0 | N35: 0 | O35: =VLOOKUP(J35,Fugitive!$B$75:$L$90,11,FALSE) -> 90.114464 | P35: =O35/$O$195 -> 4.4694166e-06
B36: 28 | C36: Steel Making | D36: =VLOOKUP(C36,Settings!$B$341:C966,2,FALSE) -> 2 | E36: Non-energy product use (oil) | F36: Fugitive | G36: =VLOOKUP(F36,Settings!$B$163:D868,3,FALSE) -> F | H36: =VLOOKUP(F36,Settings!$B$163:D867,2,FALSE) -> 1 | I36: =VLOOKUP(F36,Settings!$B$163:F575,5,FALSE) -> 1 | J36: =_xlfn.TEXTJOIN("-",,D36,G36,B36) -> 2-F-28 | K36: =VLOOKUP(J36,Fugitive!$B$75:$L$90,11,FALSE) -> 252.45316 | L36: 0 | M36: 0 | N36: 0 | O36: =VLOOKUP(J36,Fugitive!$B$75:$L$90,11,FALSE) -> 252.45316 | P36: =O36/$O$195 -> 1.2520946e-05
B37: 29 | C37: Hot Rolling | D37: =VLOOKUP(C37,Settings!$B$341:C967,2,FALSE) -> 3 | E37: Non-energy product use (oil) | F37: Fugitive | G37: =VLOOKUP(F37,Settings!$B$163:D869,3,FALSE) -> F | H37: =VLOOKUP(F37,Settings!$B$163:D868,2,FALSE) -> 1 | I37: =VLOOKUP(F37,Settings!$B$163:F576,5,FALSE) -> 1 | J37: =_xlfn.TEXTJOIN("-",,D37,G37,B37) -> 3-F-29 | K37: =VLOOKUP(J37,Fugitive!$B$75:$L$90,11,FALSE) -> 436.21851 | L37: 0 | M37: 0 | N37: 0 | O37: =VLOOKUP(J37,Fugitive!$B$75:$L$90,11,FALSE) -> 436.21851 | P37: =O37/$O$195 -> 2.1635175e-05
B38: 30 | C38: Cold Rolling | D38: =VLOOKUP(C38,Settings!$B$341:C968,2,FALSE) -> 4 | E38: Non-energy product use (oil) | F38: Fugitive | G38: =VLOOKUP(F38,Settings!$B$163:D870,3,FALSE) -> F | H38: =VLOOKUP(F38,Settings!$B$163:D869,2,FALSE) -> 1 | I38: =VLOOKUP(F38,Settings!$B$163:F577,5,FALSE) -> 1 | J38: =_xlfn.TEXTJOIN("-",,D38,G38,B38) -> 4-F-30 | K38: =VLOOKUP(J38,Fugitive!$B$75:$L$90,11,FALSE) -> 1092.8 | L38: 0 | M38: 0 | N38: 0 | O38: =VLOOKUP(J38,Fugitive!$B$75:$L$90,11,FALSE) -> 1092.8 | P38: =O38/$O$195 -> 5.4199718e-05
B39: 31 | C39: Utility | D39: =VLOOKUP(C39,Settings!$B$341:C969,2,FALSE) -> 5 | E39: Non-energy product use (oil) | F39: Fugitive | G39: =VLOOKUP(F39,Settings!$B$163:D871,3,FALSE) -> F | H39: =VLOOKUP(F39,Settings!$B$163:D870,2,FALSE) -> 1 | I39: =VLOOKUP(F39,Settings!$B$163:F578,5,FALSE) -> 1 | J39: =_xlfn.TEXTJOIN("-",,D39,G39,B39) -> 5-F-31 | K39: =VLOOKUP(J39,Fugitive!$B$75:$L$90,11,FALSE) -> 7.7838992 | L39: 0 | M39: 0 | N39: 0 | O39: =VLOOKUP(J39,Fugitive!$B$75:$L$90,11,FALSE) -> 7.7838992 | P39: =O39/$O$195 -> 3.8605887e-07
B40: 32 | C40: Transportation | D40: =VLOOKUP(C40,Settings!$B$341:C970,2,FALSE) -> 6 | E40: Non-energy product use (oil) | F40: Fugitive | G40: =VLOOKUP(F40,Settings!$B$163:D872,3,FALSE) -> F | H40: =VLOOKUP(F40,Settings!$B$163:D871,2,FALSE) -> 1 | I40: =VLOOKUP(F40,Settings!$B$163:F579,5,FALSE) -> 1 | J40: =_xlfn.TEXTJOIN("-",,D40,G40,B40) -> 6-F-32 | K40: =VLOOKUP(J40,Fugitive!$B$75:$L$90,11,FALSE) -> 30.220538 | L40: 0 | M40: 0 | N40: 0 | O40: =VLOOKUP(J40,Fugitive!$B$75:$L$90,11,FALSE) -> 30.220538 | P40: =O40/$O$195 -> 1.4988512e-06
B41: 33 | C41: Maintenance | D41: =VLOOKUP(C41,Settings!$B$341:C971,2,FALSE) -> 7 | E41: Non-energy product use (oil) | F41: Fugitive | G41: =VLOOKUP(F41,Settings!$B$163:D873,3,FALSE) -> F | H41: =VLOOKUP(F41,Settings!$B$163:D872,2,FALSE) -> 1 | I41: =VLOOKUP(F41,Settings!$B$163:F580,5,FALSE) -> 1 | J41: =_xlfn.TEXTJOIN("-",,D41,G41,B41) -> 7-F-33 | K41: =VLOOKUP(J41,Fugitive!$B$75:$L$90,11,FALSE) -> 11.77726 | L41: 0 | M41: 0 | N41: 0 | O41: =VLOOKUP(J41,Fugitive!$B$75:$L$90,11,FALSE) -> 11.77726 | P41: =O41/$O$195 -> 5.8411801e-07
B42: 34 | C42: TAS | D42: =VLOOKUP(C42,Settings!$B$341:C972,2,FALSE) -> 9 | E42: Non-energy product use (oil) | F42: Fugitive | G42: =VLOOKUP(F42,Settings!$B$163:D874,3,FALSE) -> F | H42: =VLOOKUP(F42,Settings!$B$163:D873,2,FALSE) -> 1 | I42: =VLOOKUP(F42,Settings!$B$163:F581,5,FALSE) -> 1 | J42: =_xlfn.TEXTJOIN("-",,D42,G42,B42) -> 9-F-34 | K42: =VLOOKUP(J42,Fugitive!$B$75:$L$90,11,FALSE) -> 2.576552 | L42: 0 | M42: 0 | N42: 0 | O42: =VLOOKUP(J42,Fugitive!$B$75:$L$90,11,FALSE) -> 2.576552 | P42: =O42/$O$195 -> 1.2778952e-07
B43: 35 | C43: Iron Making | D43: =VLOOKUP(C43,Settings!$B$341:C973,2,FALSE) -> 1 | E43: Non-energy product use (grease) | F43: Fugitive | G43: =VLOOKUP(F43,Settings!$B$163:D875,3,FALSE) -> F | H43: =VLOOKUP(F43,Settings!$B$163:D874,2,FALSE) -> 1 | I43: =VLOOKUP(F43,Settings!$B$163:F582,5,FALSE) -> 1 | J43: =_xlfn.TEXTJOIN("-",,D43,G43,B43) -> 1-F-35 | K43: =VLOOKUP(J43,Fugitive!$B$75:$L$90,11,FALSE) -> 15.837393 | L43: 0 | M43: 0 | N43: 0 | O43: =VLOOKUP(J43,Fugitive!$B$75:$L$90,11,FALSE) -> 15.837393 | P43: =O43/$O$195 -> 7.8548885e-07
B44: 36 | C44: Steel Making | D44: =VLOOKUP(C44,Settings!$B$341:C974,2,FALSE) -> 2 | E44: Non-energy product use (grease) | F44: Fugitive | G44: =VLOOKUP(F44,Settings!$B$163:D876,3,FALSE) -> F | H44: =VLOOKUP(F44,Settings!$B$163:D875,2,FALSE) -> 1 | I44: =VLOOKUP(F44,Settings!$B$163:F583,5,FALSE) -> 1 | J44: =_xlfn.TEXTJOIN("-",,D44,G44,B44) -> 2-F-36 | K44: =VLOOKUP(J44,Fugitive!$B$75:$L$90,11,FALSE) -> 28.077342 | L44: 0 | M44: 0 | N44: 0 | O44: =VLOOKUP(J44,Fugitive!$B$75:$L$90,11,FALSE) -> 28.077342 | P44: =O44/$O$195 -> 1.3925549e-06
B45: 37 | C45: Hot Rolling | D45: =VLOOKUP(C45,Settings!$B$341:C975,2,FALSE) -> 3 | E45: Non-energy product use (grease) | F45: Fugitive | G45: =VLOOKUP(F45,Settings!$B$163:D877,3,FALSE) -> F | H45: =VLOOKUP(F45,Settings!$B$163:D876,2,FALSE) -> 1 | I45: =VLOOKUP(F45,Settings!$B$163:F584,5,FALSE) -> 1 | J45: =_xlfn.TEXTJOIN("-",,D45,G45,B45) -> 3-F-37 | K45: =VLOOKUP(J45,Fugitive!$B$75:$L$90,11,FALSE) -> 36.549009 | L45: 0 | M45: 0 | N45: 0 | O45: =VLOOKUP(J45,Fugitive!$B$75:$L$90,11,FALSE) -> 36.549009 | P45: =O45/$O$195 -> 1.8127251e-06
B46: 38 | C46: Cold Rolling | D46: =VLOOKUP(C46,Settings!$B$341:C976,2,FALSE) -> 4 | E46: Non-energy product use (grease) | F46: Fugitive | G46: =VLOOKUP(F46,Settings!$B$163:D878,3,FALSE) -> F | H46: =VLOOKUP(F46,Settings!$B$163:D877,2,FALSE) -> 1 | I46: =VLOOKUP(F46,Settings!$B$163:F585,5,FALSE) -> 1 | J46: =_xlfn.TEXTJOIN("-",,D46,G46,B46) -> 4-F-38 | K46: =VLOOKUP(J46,Fugitive!$B$75:$L$90,11,FALSE) -> 3.3952116 | L46: 0 | M46: 0 | N46: 0 | O46: =VLOOKUP(J46,Fugitive!$B$75:$L$90,11,FALSE) -> 3.3952116 | P46: =O46/$O$195 -> 1.6839267e-07
... B50: 42 | C50: TAS | D50: =VLOOKUP(C50,Settings!$B$341:C980,2,FALSE) -> 9 | E50: Non-energy product use (grease) | F50: Fugitive | G50: =VLOOKUP(F50,Settings!$B$163:D882,3,FALSE) -> F | H50: =VLOOKUP(F50,Settings!$B$163:D881,2,FALSE) -> 1 | I50: =VLOOKUP(F50,Settings!$B$163:F589,5,FALSE) -> 1 | J50: =_xlfn.TEXTJOIN("-",,D50,G50,B50) -> 9-F-42 | K50: =VLOOKUP(J50,Fugitive!$B$75:$L$90,11,FALSE) -> 0.002948 | L50: 0 | M50: 0 | N50: 0 | O50: =VLOOKUP(J50,Fugitive!$B$75:$L$90,11,FALSE) -> 0.002948 | P50: =O50/$O$195 -> 1.4621227e-10
B51: 43 | C51: Iron Making | D51: =VLOOKUP(C51,Settings!$B$341:C349,2,FALSE) -> 1 | E51: Electricity | F51: Electricity | G51: =VLOOKUP(F51,Settings!$B$163:D180,3,FALSE) -> E | H51: =VLOOKUP(F51,Settings!$B$163:D180,2,FALSE) -> 2 | I51: =VLOOKUP(F51,Settings!$B$163:F182,5,FALSE) -> 2 | J51: =_xlfn.TEXTJOIN("-",,D51,G51,B51) -> 1-E-43 | K51: =VLOOKUP(J51,Electricity!$H$133:$M$140,3,FALSE) -> 391357.71 | L51: =VLOOKUP(J51,Electricity!$H$133:$M$140,4,FALSE) -> 7887.0431 | M51: =VLOOKUP(J51,Electricity!$H$133:$M$140,5,FALSE) -> 1.1653535 | N51: 0 | O51: =VLOOKUP(J51,Electricity!$H$133:$M$140,6,FALSE) -> 604626.02 | P51: =O51/$O$195 -> 0.029987701
B52: 44 | C52: Steel Making | D52: =VLOOKUP(C52,Settings!$B$341:C365,2,FALSE) -> 2 | E52: Electricity | F52: Electricity | G52: =VLOOKUP(F52,Settings!$B$163:D189,3,FALSE) -> E | H52: =VLOOKUP(F52,Settings!$B$163:D189,2,FALSE) -> 2 | I52: =VLOOKUP(F52,Settings!$B$163:F183,5,FALSE) -> 2 | J52: =_xlfn.TEXTJOIN("-",,D52,G52,B52) -> 2-E-44 | K52: =VLOOKUP(J52,Electricity!$H$133:$M$140,3,FALSE) -> 2033917.6 | L52: =VLOOKUP(J52,Electricity!$H$133:$M$140,4,FALSE) -> 40989.599 | M52: =VLOOKUP(J52,Electricity!$H$133:$M$140,5,FALSE) -> 6.0564358 | N52: 0 | O52: =VLOOKUP(J52,Electricity!$H$133:$M$140,6,FALSE) -> 3142290.2 | P52: =O52/$O$195 -> 0.1558485
B53: 45 | C53: Hot Rolling | D53: =VLOOKUP(C53,Settings!$B$341:C368,2,FALSE) -> 3 | E53: Electricity | F53: Electricity | G53: =VLOOKUP(F53,Settings!$B$163:D192,3,FALSE) -> E | H53: =VLOOKUP(F53,Settings!$B$163:D192,2,FALSE) -> 2 | I53: =VLOOKUP(F53,Settings!$B$163:F184,5,FALSE) -> 2 | J53: =_xlfn.TEXTJOIN("-",,D53,G53,B53) -> 3-E-45 | K53: =VLOOKUP(J53,Electricity!$H$133:$M$140,3,FALSE) -> 135166.53 | L53: =VLOOKUP(J53,Electricity!$H$133:$M$140,4,FALSE) -> 2724.015 | M53: =VLOOKUP(J53,Electricity!$H$133:$M$140,5,FALSE) -> 0.40248801 | N53: 0 | O53: =VLOOKUP(J53,Electricity!$H$133:$M$140,6,FALSE) -> 208824.82 | P53: =O53/$O$195 -> 0.010357106
B54: 46 | C54: Cold Rolling | D54: =VLOOKUP(C54,Settings!$B$341:C372,2,FALSE) -> 4 | E54: Electricity | F54: Electricity | G54: =VLOOKUP(F54,Settings!$B$163:D195,3,FALSE) -> E | H54: =VLOOKUP(F54,Settings!$B$163:D195,2,FALSE) -> 2 | I54: =VLOOKUP(F54,Settings!$B$163:F185,5,FALSE) -> 2 | J54: =_xlfn.TEXTJOIN("-",,D54,G54,B54) -> 4-E-46 | K54: =VLOOKUP(J54,Electricity!$H$133:$M$140,3,FALSE) -> 89063.68 | L54: =VLOOKUP(J54,Electricity!$H$133:$M$140,4,FALSE) -> 1794.9029 | M54: =VLOOKUP(J54,Electricity!$H$133:$M$140,5,FALSE) -> 0.26520665 | N54: 0 | O54: =VLOOKUP(J54,Electricity!$H$133:$M$140,6,FALSE) -> 137598.46 | P54: =O54/$O$195 -> 0.0068244853
B55: 47 | C55: Utility | D55: =VLOOKUP(C55,Settings!$B$341:C385,2,FALSE) -> 5 | E55: Electricity | F55: Electricity | G55: =VLOOKUP(F55,Settings!$B$163:D203,3,FALSE) -> E | H55: =VLOOKUP(F55,Settings!$B$163:D202,2,FALSE) -> 2 | I55: =VLOOKUP(F55,Settings!$B$163:F185,5,FALSE) -> 2 | J55: =_xlfn.TEXTJOIN("-",,D55,G55,B55) -> 5-E-47 | K55: =VLOOKUP(J55,Electricity!$H$133:$M$140,3,FALSE) -> 286140.87 | L55: =VLOOKUP(J55,Electricity!$H$133:$M$140,4,FALSE) -> 5766.6051 | M55: =VLOOKUP(J55,Electricity!$H$133:$M$140,5,FALSE) -> 0.85204722 | N55: 0 | O55: =VLOOKUP(J55,Electricity!$H$133:$M$140,6,FALSE) -> 442071.82 | P55: =O55/$O$195 -> 0.021925483
B56: 48 | C56: Transportation | D56: =VLOOKUP(C56,Settings!$B$341:C394,2,FALSE) -> 6 | E56: Electricity | F56: Electricity | G56: =VLOOKUP(F56,Settings!$B$163:D213,3,FALSE) -> E | H56: =VLOOKUP(F56,Settings!$B$163:D212,2,FALSE) -> 2 | I56: =VLOOKUP(F56,Settings!$B$163:F186,5,FALSE) -> 2 | J56: =_xlfn.TEXTJOIN("-",,D56,G56,B56) -> 6-E-48 | K56: =VLOOKUP(J56,Electricity!$H$133:$M$140,3,FALSE) -> 0 | L56: =VLOOKUP(J56,Electricity!$H$133:$M$140,4,FALSE) -> 0 | M56: =VLOOKUP(J56,Electricity!$H$133:$M$140,5,FALSE) -> 0 | N56: 0 | O56: =VLOOKUP(J56,Electricity!$H$133:$M$140,6,FALSE) -> 0 | P56: =O56/$O$195 -> 0
B57: 49 | C57: Maintenance | D57: =VLOOKUP(C57,Settings!$B$341:C395,2,FALSE) -> 7 | E57: Electricity | F57: Electricity | G57: =VLOOKUP(F57,Settings!$B$163:D222,3,FALSE) -> E | H57: =VLOOKUP(F57,Settings!$B$163:D221,2,FALSE) -> 2 | I57: =VLOOKUP(F57,Settings!$B$163:F189,5,FALSE) -> 2 | J57: =_xlfn.TEXTJOIN("-",,D57,G57,B57) -> 7-E-49 | K57: =VLOOKUP(J57,Electricity!$H$133:$M$140,3,FALSE) -> 1646.6628 | L57: =VLOOKUP(J57,Electricity!$H$133:$M$140,4,FALSE) -> 33.185241 | M57: =VLOOKUP(J57,Electricity!$H$133:$M$140,5,FALSE) -> 0.0049032996 | N57: 0 | O57: =VLOOKUP(J57,Electricity!$H$133:$M$140,6,FALSE) -> 2544.0029 | P57: =O57/$O$195 -> 0.00012617518
B58: 50 | C58: TAS | D58: =VLOOKUP(C58,Settings!$B$341:C395,2,FALSE) -> 9 | E58: Electricity | F58: Electricity | G58: =VLOOKUP(F58,Settings!$B$163:D224,3,FALSE) -> E | H58: =VLOOKUP(F58,Settings!$B$163:D223,2,FALSE) -> 2 | I58: =VLOOKUP(F58,Settings!$B$163:F190,5,FALSE) -> 2 | J58: =_xlfn.TEXTJOIN("-",,D58,G58,B58) -> 9-E-50 | K58: =VLOOKUP(J58,Electricity!$H$133:$M$140,3,FALSE) -> 1025.6601 | L58: =VLOOKUP(J58,Electricity!$H$133:$M$140,4,FALSE) -> 20.670158 | M58: =VLOOKUP(J58,Electricity!$H$133:$M$140,5,FALSE) -> 0.003054128 | N58: 0 | O58: =VLOOKUP(J58,Electricity!$H$133:$M$140,6,FALSE) -> 1584.5882 | P58: =O58/$O$195 -> 7.8590986e-05
B59: 51 | C59: Iron Making | D59: =VLOOKUP(C59,Settings!$B$341:C348,2,FALSE) -> 1 | E59: On-site Transportation | F59: Mobile Combustion | G59: =VLOOKUP(F59,Settings!$B$163:D180,3,FALSE) -> M | H59: =VLOOKUP(F59,Settings!$B$163:D180,2,FALSE) -> 1 | I59: =VLOOKUP(F59,Settings!$B$163:F195,5,FALSE) -> 1 | J59: =_xlfn.TEXTJOIN("-",,D59,G59,B59) -> 1-M-51 | K59: =VLOOKUP(J59,'On-Site Tran.'!$J$45:$O$52,3,FALSE) -> 8918.3469 | L59: =VLOOKUP(J59,'On-Site Tran.'!$J$45:$O$52,4,FALSE) -> 0.34374742 | M59: =VLOOKUP(J59,'On-Site Tran.'!$J$45:$O$52,5,FALSE) -> 0.34702121 | N59: 0 | O59: =VLOOKUP(J59,'On-Site Tran.'!$J$45:$O$52,6,FALSE) -> 9022.3649 | P59: =O59/$O$195 -> 0.00044748318
B60: 52 | C60: Steel Making | D60: =VLOOKUP(C60,Settings!$B$341:C395,2,FALSE) -> 2 | E60: On-site Transportation | F60: Mobile Combustion | G60: =VLOOKUP(F60,Settings!$B$163:D236,3,FALSE) -> M | H60: =VLOOKUP(F60,Settings!$B$163:D235,2,FALSE) -> 1 | I60: =VLOOKUP(F60,Settings!$B$163:F233,5,FALSE) -> 1 | J60: =_xlfn.TEXTJOIN("-",,D60,G60,B60) -> 2-M-52 | K60: =VLOOKUP(J60,'On-Site Tran.'!$J$45:$O$52,3,FALSE) -> 196.41266 | L60: =VLOOKUP(J60,'On-Site Tran.'!$J$45:$O$52,4,FALSE) -> 0.0075705 | M60: =VLOOKUP(J60,'On-Site Tran.'!$J$45:$O$52,5,FALSE) -> 0.0076426 | N60: 0 | O60: =VLOOKUP(J60,'On-Site Tran.'!$J$45:$O$52,6,FALSE) -> 198.70349 | P60: =O60/$O$195 -> 9.855118e-06
B61: 53 | C61: Hot Rolling | D61: =VLOOKUP(C61,Settings!$B$341:C534,2,FALSE) -> 3 | E61: On-site Transportation | F61: Mobile Combustion | G61: =VLOOKUP(F61,Settings!$B$163:D456,3,FALSE) -> M | H61: =VLOOKUP(F61,Settings!$B$163:D455,2,FALSE) -> 1 | I61: =VLOOKUP(F61,Settings!$B$163:F339,5,FALSE) -> 1 | J61: =_xlfn.TEXTJOIN("-",,D61,G61,B61) -> 3-M-53 | K61: =VLOOKUP(J61,'On-Site Tran.'!$J$45:$O$52,3,FALSE) -> 0 | L61: =VLOOKUP(J61,'On-Site Tran.'!$J$45:$O$52,4,FALSE) -> 0 | M61: =VLOOKUP(J61,'On-Site Tran.'!$J$45:$O$52,5,FALSE) -> 0 | N61: 0 | O61: =VLOOKUP(J61,'On-Site Tran.'!$J$45:$O$52,6,FALSE) -> 0 | P61: =O61/$O$195 -> 0
B62: 54 | C62: Cold Rolling | D62: =VLOOKUP(C62,Settings!$B$341:C578,2,FALSE) -> 4 | E62: On-site Transportation | F62: Mobile Combustion | G62: =VLOOKUP(F62,Settings!$B$163:D500,3,FALSE) -> M | H62: =VLOOKUP(F62,Settings!$B$163:D499,2,FALSE) -> 1 | I62: =VLOOKUP(F62,Settings!$B$163:F395,5,FALSE) -> 1 | J62: =_xlfn.TEXTJOIN("-",,D62,G62,B62) -> 4-M-54 | K62: =VLOOKUP(J62,'On-Site Tran.'!$J$45:$O$52,3,FALSE) -> 57.20757 | L62: =VLOOKUP(J62,'On-Site Tran.'!$J$45:$O$52,4,FALSE) -> 0.002205 | M62: =VLOOKUP(J62,'On-Site Tran.'!$J$45:$O$52,5,FALSE) -> 0.002226 | N62: 0 | O62: =VLOOKUP(J62,'On-Site Tran.'!$J$45:$O$52,6,FALSE) -> 57.874803 | P62: =O62/$O$195 -> 2.8704227e-06
B63: 55 | C63: Utility | D63: =VLOOKUP(C63,Settings!$B$341:C685,2,FALSE) -> 5 | E63: On-site Transportation | F63: Mobile Combustion | G63: =VLOOKUP(F63,Settings!$B$163:D607,3,FALSE) -> M | H63: =VLOOKUP(F63,Settings!$B$163:D606,2,FALSE) -> 1 | I63: =VLOOKUP(F63,Settings!$B$163:F451,5,FALSE) -> 1 | J63: =_xlfn.TEXTJOIN("-",,D63,G63,B63) -> 5-M-55 | K63: =VLOOKUP(J63,'On-Site Tran.'!$J$45:$O$52,3,FALSE) -> 0 | L63: =VLOOKUP(J63,'On-Site Tran.'!$J$45:$O$52,4,FALSE) -> 0 | M63: =VLOOKUP(J63,'On-Site Tran.'!$J$45:$O$52,5,FALSE) -> 0 | N63: 0 | O63: =VLOOKUP(J63,'On-Site Tran.'!$J$45:$O$52,6,FALSE) -> 0 | P63: =O63/$O$195 -> 0
B64: 56 | C64: Transportation | D64: =VLOOKUP(C64,Settings!$B$341:C742,2,FALSE) -> 6 | E64: On-site Transportation | F64: Mobile Combustion | G64: =VLOOKUP(F64,Settings!$B$163:D664,3,FALSE) -> M | H64: =VLOOKUP(F64,Settings!$B$163:D663,2,FALSE) -> 1 | I64: =VLOOKUP(F64,Settings!$B$163:F471,5,FALSE) -> 1 | J64: =_xlfn.TEXTJOIN("-",,D64,G64,B64) -> 6-M-56 | K64: =VLOOKUP(J64,'On-Site Tran.'!$J$45:$O$52,3,FALSE) -> 5963.8211 | L64: =VLOOKUP(J64,'On-Site Tran.'!$J$45:$O$52,4,FALSE) -> 0.22986863 | M64: =VLOOKUP(J64,'On-Site Tran.'!$J$45:$O$52,5,FALSE) -> 0.23205785 | N64: 0 | O64: =VLOOKUP(J64,'On-Site Tran.'!$J$45:$O$52,6,FALSE) -> 6033.3793 | P64: =O64/$O$195 -> 0.00029923815
B65: 57 | C65: Maintenance | D65: =VLOOKUP(C65,Settings!$B$341:C755,2,FALSE) -> 7 | E65: On-site Transportation | F65: Mobile Combustion | G65: =VLOOKUP(F65,Settings!$B$163:D677,3,FALSE) -> M | H65: =VLOOKUP(F65,Settings!$B$163:D676,2,FALSE) -> 1 | I65: =VLOOKUP(F65,Settings!$B$163:F478,5,FALSE) -> 1 | J65: =_xlfn.TEXTJOIN("-",,D65,G65,B65) -> 7-M-57 | K65: =VLOOKUP(J65,'On-Site Tran.'!$J$45:$O$52,3,FALSE) -> 77.638845 | L65: =VLOOKUP(J65,'On-Site Tran.'!$J$45:$O$52,4,FALSE) -> 0.0029925 | M65: =VLOOKUP(J65,'On-Site Tran.'!$J$45:$O$52,5,FALSE) -> 0.003021 | N65: 0 | O65: =VLOOKUP(J65,'On-Site Tran.'!$J$45:$O$52,6,FALSE) -> 78.544376 | P65: =O65/$O$195 -> 3.8955737e-06
B66: 58 | C66: TAS | D66: =VLOOKUP(C66,Settings!$B$341:C794,2,FALSE) -> 9 | E66: On-site Transportation | F66: Mobile Combustion | G66: =VLOOKUP(F66,Settings!$B$163:D716,3,FALSE) -> M | H66: =VLOOKUP(F66,Settings!$B$163:D715,2,FALSE) -> 1 | I66: =VLOOKUP(F66,Settings!$B$163:F533,5,FALSE) -> 1 | J66: =_xlfn.TEXTJOIN("-",,D66,G66,B66) -> 9-M-58 | K66: =VLOOKUP(J66,'On-Site Tran.'!$J$45:$O$52,3,FALSE) -> 33334.391 | L66: =VLOOKUP(J66,'On-Site Tran.'!$J$45:$O$52,4,FALSE) -> 1.4564314 | M66: =VLOOKUP(J66,'On-Site Tran.'!$J$45:$O$52,5,FALSE) -> 1.2328911 | N66: 0 | O66: =VLOOKUP(J66,'On-Site Tran.'!$J$45:$O$52,6,FALSE) -> 33710.293 | P66: =O66/$O$195 -> 0.001671933
B67: 59 | C67: Iron Making | D67: =VLOOKUP(C67,Settings!$B$341:C897,2,FALSE) -> 1 | E67: Upstream Transportation of Raw Materials | F67: Up-Transportation | G67: =VLOOKUP(F67,Settings!$B$163:D819,3,FALSE) -> T | H67: =VLOOKUP(F67,Settings!$B$163:D818,2,FALSE) -> 3 | I67: =VLOOKUP(F67,Settings!$B$163:F194,5,FALSE) -> 3 | J67: =_xlfn.TEXTJOIN("-",,D67,G67,B67) -> 1-T-59 | K67: =VLOOKUP(J67,'Upstream Tran.'!$I$81:$N$88,3,FALSE) -> 320684.3 | L67: =VLOOKUP(J67,'Upstream Tran.'!$I$81:$N$88,4,FALSE) -> 6.4592582 | M67: =VLOOKUP(J67,'Upstream Tran.'!$I$81:$N$88,5,FALSE) -> 8.6953474 | N67: 0 | O67: =VLOOKUP(J67,'Upstream Tran.'!$I$81:$N$88,6,FALSE) -> 323232.53 | P67: =O67/$O$195 -> 0.016031398
B68: 60 | C68: Steel Making | D68: =VLOOKUP(C68,Settings!$B$341:C898,2,FALSE) -> 2 | E68: Upstream Transportation of Raw Materials | F68: Up-Transportation | G68: =VLOOKUP(F68,Settings!$B$163:D820,3,FALSE) -> T | H68: =VLOOKUP(F68,Settings!$B$163:D819,2,FALSE) -> 3 | I68: =VLOOKUP(F68,Settings!$B$163:F231,5,FALSE) -> 3 | J68: =_xlfn.TEXTJOIN("-",,D68,G68,B68) -> 2-T-60 | K68: =VLOOKUP(J68,'Upstream Tran.'!$I$81:$N$88,3,FALSE) -> 163898.79 | L68: =VLOOKUP(J68,'Upstream Tran.'!$I$81:$N$88,4,FALSE) -> 1.463382 | M68: =VLOOKUP(J68,'Upstream Tran.'!$I$81:$N$88,5,FALSE) -> 4.5852637 | N68: 0 | O68: =VLOOKUP(J68,'Upstream Tran.'!$I$81:$N$88,6,FALSE) -> 165190.08 | P68: =O68/$O$195 -> 0.0081929497
B69: 61 | C69: Hot Rolling | D69: =VLOOKUP(C69,Settings!$B$341:C899,2,FALSE) -> 3 | E69: Upstream Transportation of Raw Materials | F69: Up-Transportation | G69: =VLOOKUP(F69,Settings!$B$163:D821,3,FALSE) -> T | H69: =VLOOKUP(F69,Settings!$B$163:D820,2,FALSE) -> 3 | I69: =VLOOKUP(F69,Settings!$B$163:F281,5,FALSE) -> 3 | J69: =_xlfn.TEXTJOIN("-",,D69,G69,B69) -> 3-T-61 | K69: =VLOOKUP(J69,'Upstream Tran.'!$I$81:$N$88,3,FALSE) -> 0 | L69: =VLOOKUP(J69,'Upstream Tran.'!$I$81:$N$88,4,FALSE) -> 0 | M69: =VLOOKUP(J69,'Upstream Tran.'!$I$81:$N$88,5,FALSE) -> 0 | N69: 0 | O69: =VLOOKUP(J69,'Upstream Tran.'!$I$81:$N$88,6,FALSE) -> 0 | P69: =O69/$O$195 -> 0
B70: 62 | C70: Cold Rolling | D70: =VLOOKUP(C70,Settings!$B$341:C900,2,FALSE) -> 4 | E70: Upstream Transportation of Raw Materials | F70: Up-Transportation | G70: =VLOOKUP(F70,Settings!$B$163:D822,3,FALSE) -> T | H70: =VLOOKUP(F70,Settings!$B$163:D821,2,FALSE) -> 3 | I70: =VLOOKUP(F70,Settings!$B$163:F395,5,FALSE) -> 3 | J70: =_xlfn.TEXTJOIN("-",,D70,G70,B70) -> 4-T-62 | K70: =VLOOKUP(J70,'Upstream Tran.'!$I$81:$N$88,3,FALSE) -> 0 | L70: =VLOOKUP(J70,'Upstream Tran.'!$I$81:$N$88,4,FALSE) -> 0 | M70: =VLOOKUP(J70,'Upstream Tran.'!$I$81:$N$88,5,FALSE) -> 0 | N70: 0 | O70: =VLOOKUP(J70,'Upstream Tran.'!$I$81:$N$88,6,FALSE) -> 0 | P70: =O70/$O$195 -> 0
B71: 63 | C71: Utility | D71: =VLOOKUP(C71,Settings!$B$341:C910,2,FALSE) -> 5 | E71: Upstream Transportation of Raw Materials | F71: Up-Transportation | G71: =VLOOKUP(F71,Settings!$B$163:D862,3,FALSE) -> T | H71: =VLOOKUP(F71,Settings!$B$163:D861,2,FALSE) -> 3 | I71: =VLOOKUP(F71,Settings!$B$163:F449,5,FALSE) -> 3 | J71: =_xlfn.TEXTJOIN("-",,D71,G71,B71) -> 5-T-63 | K71: =VLOOKUP(J71,'Upstream Tran.'!$I$81:$N$88,3,FALSE) -> 0 | L71: =VLOOKUP(J71,'Upstream Tran.'!$I$81:$N$88,4,FALSE) -> 0 | M71: =VLOOKUP(J71,'Upstream Tran.'!$I$81:$N$88,5,FALSE) -> 0 | N71: 0 | O71: =VLOOKUP(J71,'Upstream Tran.'!$I$81:$N$88,6,FALSE) -> 0 | P71: =O71/$O$195 -> 0
B72: 64 | C72: Transportation | D72: =VLOOKUP(C72,Settings!$B$341:C912,2,FALSE) -> 6 | E72: Upstream Transportation of Raw Materials | F72: Up-Transportation | G72: =VLOOKUP(F72,Settings!$B$163:D864,3,FALSE) -> T | H72: =VLOOKUP(F72,Settings!$B$163:D863,2,FALSE) -> 3 | I72: =VLOOKUP(F72,Settings!$B$163:F469,5,FALSE) -> 3 | J72: =_xlfn.TEXTJOIN("-",,D72,G72,B72) -> 6-T-64 | K72: =VLOOKUP(J72,'Upstream Tran.'!$I$81:$N$88,3,FALSE) -> 0 | L72: =VLOOKUP(J72,'Upstream Tran.'!$I$81:$N$88,4,FALSE) -> 0 | M72: =VLOOKUP(J72,'Upstream Tran.'!$I$81:$N$88,5,FALSE) -> 0 | N72: 0 | O72: =VLOOKUP(J72,'Upstream Tran.'!$I$81:$N$88,6,FALSE) -> 0 | P72: =O72/$O$195 -> 0
B73: 65 | C73: Maintenance | D73: =VLOOKUP(C73,Settings!$B$341:C911,2,FALSE) -> 7 | E73: Upstream Transportation of Raw Materials | F73: Up-Transportation | G73: =VLOOKUP(F73,Settings!$B$163:D863,3,FALSE) -> T | H73: =VLOOKUP(F73,Settings!$B$163:D862,2,FALSE) -> 3 | I73: =VLOOKUP(F73,Settings!$B$163:F476,5,FALSE) -> 3 | J73: =_xlfn.TEXTJOIN("-",,D73,G73,B73) -> 7-T-65 | K73: =VLOOKUP(J73,'Upstream Tran.'!$I$81:$N$88,3,FALSE) -> 0 | L73: =VLOOKUP(J73,'Upstream Tran.'!$I$81:$N$88,4,FALSE) -> 0 | M73: =VLOOKUP(J73,'Upstream Tran.'!$I$81:$N$88,5,FALSE) -> 0 | N73: 0 | O73: =VLOOKUP(J73,'Upstream Tran.'!$I$81:$N$88,6,FALSE) -> 0 | P73: =O73/$O$195 -> 0
B74: 66 | C74: TAS | D74: =VLOOKUP(C74,Settings!$B$341:C913,2,FALSE) -> 9 | E74: Upstream Transportation of Raw Materials | F74: Up-Transportation | G74: =VLOOKUP(F74,Settings!$B$163:D865,3,FALSE) -> T | H74: =VLOOKUP(F74,Settings!$B$163:D864,2,FALSE) -> 3 | I74: =VLOOKUP(F74,Settings!$B$163:F531,5,FALSE) -> 3 | J74: =_xlfn.TEXTJOIN("-",,D74,G74,B74) -> 9-T-66 | K74: =VLOOKUP(J74,'Upstream Tran.'!$I$81:$N$88,3,FALSE) -> 0 | L74: =VLOOKUP(J74,'Upstream Tran.'!$I$81:$N$88,4,FALSE) -> 0 | M74: =VLOOKUP(J74,'Upstream Tran.'!$I$81:$N$88,5,FALSE) -> 0 | N74: 0 | O74: =VLOOKUP(J74,'Upstream Tran.'!$I$81:$N$88,6,FALSE) -> 0 | P74: =O74/$O$195 -> 0
B75: 67 | C75: Iron Making | D75: =VLOOKUP(C75,Settings!$B$341:C892,2,FALSE) -> 1 | E75: Downstream Transportation of Products | F75: Down-Transportation | G75: =VLOOKUP(F75,Settings!$B$163:D814,3,FALSE) -> D | H75: =VLOOKUP(F75,Settings!$B$163:D813,2,FALSE) -> 3 | I75: =VLOOKUP(F75,Settings!$B$163:F195,5,FALSE) -> 3 | J75: =_xlfn.TEXTJOIN("-",,D75,G75,B75) -> 1-D-67 | K75: =VLOOKUP(J75,'Downstream Tran.'!$I$57:$N$64,3,FALSE) -> 0 | L75: =VLOOKUP(J75,'Downstream Tran.'!$I$57:$N$64,4,FALSE) -> 0 | M75: =VLOOKUP(J75,'Downstream Tran.'!$I$57:$N$64,5,FALSE) -> 0 | N75: 0 | O75: =VLOOKUP(J75,'Downstream Tran.'!$I$57:$N$64,6,FALSE) -> 0 | P75: =O75/$O$195 -> 0
B76: 68 | C76: Steel Making | D76: =VLOOKUP(C76,Settings!$B$341:C893,2,FALSE) -> 2 | E76: Downstream Transportation of Products | F76: Down-Transportation | G76: =VLOOKUP(F76,Settings!$B$163:D815,3,FALSE) -> D | H76: =VLOOKUP(F76,Settings!$B$163:D814,2,FALSE) -> 3 | I76: =VLOOKUP(F76,Settings!$B$163:F232,5,FALSE) -> 3 | J76: =_xlfn.TEXTJOIN("-",,D76,G76,B76) -> 2-D-68 | K76: =VLOOKUP(J76,'Downstream Tran.'!$I$57:$N$64,3,FALSE) -> 0 | L76: =VLOOKUP(J76,'Downstream Tran.'!$I$57:$N$64,4,FALSE) -> 0 | M76: =VLOOKUP(J76,'Downstream Tran.'!$I$57:$N$64,5,FALSE) -> 0 | N76: 0 | O76: =VLOOKUP(J76,'Downstream Tran.'!$I$57:$N$64,6,FALSE) -> 0 | P76: =O76/$O$195 -> 0
B77: 69 | C77: Hot Rolling | D77: =VLOOKUP(C77,Settings!$B$341:C894,2,FALSE) -> 3 | E77: Downstream Transportation of Products | F77: Down-Transportation | G77: =VLOOKUP(F77,Settings!$B$163:D816,3,FALSE) -> D | H77: =VLOOKUP(F77,Settings!$B$163:D815,2,FALSE) -> 3 | I77: =VLOOKUP(F77,Settings!$B$163:F338,5,FALSE) -> 3 | J77: =_xlfn.TEXTJOIN("-",,D77,G77,B77) -> 3-D-69 | K77: =VLOOKUP(J77,'Downstream Tran.'!$I$57:$N$64,3,FALSE) -> 0 | L77: =VLOOKUP(J77,'Downstream Tran.'!$I$57:$N$64,4,FALSE) -> 0 | M77: =VLOOKUP(J77,'Downstream Tran.'!$I$57:$N$64,5,FALSE) -> 0 | N77: 0 | O77: =VLOOKUP(J77,'Downstream Tran.'!$I$57:$N$64,6,FALSE) -> 0 | P77: =O77/$O$195 -> 0
B78: 70 | C78: Cold Rolling | D78: =VLOOKUP(C78,Settings!$B$341:C895,2,FALSE) -> 4 | E78: Downstream Transportation of Products | F78: Down-Transportation | G78: =VLOOKUP(F78,Settings!$B$163:D817,3,FALSE) -> D | H78: =VLOOKUP(F78,Settings!$B$163:D816,2,FALSE) -> 3 | I78: =VLOOKUP(F78,Settings!$B$163:F395,5,FALSE) -> 3 | J78: =_xlfn.TEXTJOIN("-",,D78,G78,B78) -> 4-D-70 | K78: =VLOOKUP(J78,'Downstream Tran.'!$I$57:$N$64,3,FALSE) -> 0 | L78: =VLOOKUP(J78,'Downstream Tran.'!$I$57:$N$64,4,FALSE) -> 0 | M78: =VLOOKUP(J78,'Downstream Tran.'!$I$57:$N$64,5,FALSE) -> 0 | N78: 0 | O78: =VLOOKUP(J78,'Downstream Tran.'!$I$57:$N$64,6,FALSE) -> 0 | P78: =O78/$O$195 -> 0
B79: 71 | C79: Utility | D79: =VLOOKUP(C79,Settings!$B$341:C914,2,FALSE) -> 5 | E79: Downstream Transportation of Products | F79: Down-Transportation | G79: =VLOOKUP(F79,Settings!$B$163:D866,3,FALSE) -> D | H79: =VLOOKUP(F79,Settings!$B$163:D865,2,FALSE) -> 3 | I79: =VLOOKUP(F79,Settings!$B$163:F450,5,FALSE) -> 3 | J79: =_xlfn.TEXTJOIN("-",,D79,G79,B79) -> 5-D-71 | K79: =VLOOKUP(J79,'Downstream Tran.'!$I$57:$N$64,3,FALSE) -> 0 | L79: =VLOOKUP(J79,'Downstream Tran.'!$I$57:$N$64,4,FALSE) -> 0 | M79: =VLOOKUP(J79,'Downstream Tran.'!$I$57:$N$64,5,FALSE) -> 0 | N79: 0 | O79: =VLOOKUP(J79,'Downstream Tran.'!$I$57:$N$64,6,FALSE) -> 0 | P79: =O79/$O$195 -> 0
B80: 72 | C80: Transportation | D80: =VLOOKUP(C80,Settings!$B$341:C915,2,FALSE) -> 6 | E80: Downstream Transportation of Products | F80: Down-Transportation | G80: =VLOOKUP(F80,Settings!$B$163:D867,3,FALSE) -> D | H80: =VLOOKUP(F80,Settings!$B$163:D866,2,FALSE) -> 3 | I80: =VLOOKUP(F80,Settings!$B$163:F470,5,FALSE) -> 3 | J80: =_xlfn.TEXTJOIN("-",,D80,G80,B80) -> 6-D-72 | K80: =VLOOKUP(J80,'Downstream Tran.'!$I$57:$N$64,3,FALSE) -> 0 | L80: =VLOOKUP(J80,'Downstream Tran.'!$I$57:$N$64,4,FALSE) -> 0 | M80: =VLOOKUP(J80,'Downstream Tran.'!$I$57:$N$64,5,FALSE) -> 0 | N80: 0 | O80: =VLOOKUP(J80,'Downstream Tran.'!$I$57:$N$64,6,FALSE) -> 0 | P80: =O80/$O$195 -> 0
B81: 73 | C81: Maintenance | D81: =VLOOKUP(C81,Settings!$B$341:C916,2,FALSE) -> 7 | E81: Downstream Transportation of Products | F81: Down-Transportation | G81: =VLOOKUP(F81,Settings!$B$163:D868,3,FALSE) -> D | H81: =VLOOKUP(F81,Settings!$B$163:D867,2,FALSE) -> 3 | I81: =VLOOKUP(F81,Settings!$B$163:F477,5,FALSE) -> 3 | J81: =_xlfn.TEXTJOIN("-",,D81,G81,B81) -> 7-D-73 | K81: =VLOOKUP(J81,'Downstream Tran.'!$I$57:$N$64,3,FALSE) -> 0 | L81: =VLOOKUP(J81,'Downstream Tran.'!$I$57:$N$64,4,FALSE) -> 0 | M81: =VLOOKUP(J81,'Downstream Tran.'!$I$57:$N$64,5,FALSE) -> 0 | N81: 0 | O81: =VLOOKUP(J81,'Downstream Tran.'!$I$57:$N$64,6,FALSE) -> 0 | P81: =O81/$O$195 -> 0
B82: 74 | C82: TAS | D82: =VLOOKUP(C82,Settings!$B$341:C917,2,FALSE) -> 9 | E82: Downstream Transportation of Products | F82: Down-Transportation | G82: =VLOOKUP(F82,Settings!$B$163:D869,3,FALSE) -> D | H82: =VLOOKUP(F82,Settings!$B$163:D868,2,FALSE) -> 3 | I82: =VLOOKUP(F82,Settings!$B$163:F532,5,FALSE) -> 3 | J82: =_xlfn.TEXTJOIN("-",,D82,G82,B82) -> 9-D-74 | K82: =VLOOKUP(J82,'Downstream Tran.'!$I$57:$N$64,3,FALSE) -> 0 | L82: =VLOOKUP(J82,'Downstream Tran.'!$I$57:$N$64,4,FALSE) -> 0 | M82: =VLOOKUP(J82,'Downstream Tran.'!$I$57:$N$64,5,FALSE) -> 0 | N82: 0 | O82: =VLOOKUP(J82,'Downstream Tran.'!$I$57:$N$64,6,FALSE) -> 0 | P82: =O82/$O$195 -> 0
B83: 75 | C83: Iron Making | D83: =VLOOKUP(C83,Settings!$B$341:C902,2,FALSE) -> 1 | E83: Heavy and Light Transportation | F83: Commuting | G83: =VLOOKUP(F83,Settings!$B$163:D824,3,FALSE) -> P | H83: =VLOOKUP(F83,Settings!$B$163:D823,2,FALSE) -> 3 | I83: =VLOOKUP(F83,Settings!$B$163:F195,5,FALSE) -> 3 | J83: =_xlfn.TEXTJOIN("-",,D83,G83,B83) -> 1-P-75 | K83: =VLOOKUP(J83,'Employee Commuting'!$F$22:$N$29,6,FALSE) -> 1945.0586 | L83: =VLOOKUP(J83,'Employee Commuting'!$F$22:$N$29,7,FALSE) -> 2.3831108e-05 | M83: =VLOOKUP(J83,'Employee Commuting'!$F$22:$N$29,8,FALSE) -> 5.3148184e-05 | N83: 0 | O83: =VLOOKUP(J83,'Employee Commuting'!$F$22:$N$29,9,FALSE) -> 1945.0738 | P83: =O83/$O$195 -> 9.647003e-05
B84: 76 | C84: Steel Making | D84: =VLOOKUP(C84,Settings!$B$341:C903,2,FALSE) -> 2 | E84: Heavy and Light Transportation | F84: Commuting | G84: =VLOOKUP(F84,Settings!$B$163:D825,3,FALSE) -> P | H84: =VLOOKUP(F84,Settings!$B$163:D824,2,FALSE) -> 3 | I84: =VLOOKUP(F84,Settings!$B$163:F234,5,FALSE) -> 3 | J84: =_xlfn.TEXTJOIN("-",,D84,G84,B84) -> 2-P-76 | K84: =VLOOKUP(J84,'Employee Commuting'!$F$22:$N$29,6,FALSE) -> 3553.5677 | L84: =VLOOKUP(J84,'Employee Commuting'!$F$22:$N$29,7,FALSE) -> 4.3538766e-05 | M84: =VLOOKUP(J84,'Employee Commuting'!$F$22:$N$29,8,FALSE) -> 9.7100245e-05 | N84: 0 | O84: =VLOOKUP(J84,'Employee Commuting'!$F$22:$N$29,9,FALSE) -> 3553.5954 | P84: =O84/$O$195 -> 0.00017624805
B85: 77 | C85: Hot Rolling | D85: =VLOOKUP(C85,Settings!$B$341:C904,2,FALSE) -> 3 | E85: Heavy and Light Transportation | F85: Commuting | G85: =VLOOKUP(F85,Settings!$B$163:D826,3,FALSE) -> P | H85: =VLOOKUP(F85,Settings!$B$163:D825,2,FALSE) -> 3 | I85: =VLOOKUP(F85,Settings!$B$163:F340,5,FALSE) -> 3 | J85: =_xlfn.TEXTJOIN("-",,D85,G85,B85) -> 3-P-77 | K85: =VLOOKUP(J85,'Employee Commuting'!$F$22:$N$29,6,FALSE) -> 1589.9493 | L85: =VLOOKUP(J85,'Employee Commuting'!$F$22:$N$29,7,FALSE) -> 1.9480263e-05 | M85: =VLOOKUP(J85,'Employee Commuting'!$F$22:$N$29,8,FALSE) -> 4.3444922e-05 | N85: 0 | O85: =VLOOKUP(J85,'Employee Commuting'!$F$22:$N$29,9,FALSE) -> 1589.9617 | P85: =O85/$O$195 -> 7.8857499e-05
B86: 78 | C86: Cold Rolling | D86: =VLOOKUP(C86,Settings!$B$341:C905,2,FALSE) -> 4 | E86: Heavy and Light Transportation | F86: Commuting | G86: =VLOOKUP(F86,Settings!$B$163:D827,3,FALSE) -> P | H86: =VLOOKUP(F86,Settings!$B$163:D826,2,FALSE) -> 3 | I86: =VLOOKUP(F86,Settings!$B$163:F395,5,FALSE) -> 3 | J86: =_xlfn.TEXTJOIN("-",,D86,G86,B86) -> 4-P-78 | K86: =VLOOKUP(J86,'Employee Commuting'!$F$22:$N$29,6,FALSE) -> 2487.0025 | L86: =VLOOKUP(J86,'Employee Commuting'!$F$22:$N$29,7,FALSE) -> 3.0471073e-05 | M86: =VLOOKUP(J86,'Employee Commuting'!$F$22:$N$29,8,FALSE) -> 6.7956648e-05 | N86: 0 | O86: =VLOOKUP(J86,'Employee Commuting'!$F$22:$N$29,9,FALSE) -> 2487.0218 | P86: =O86/$O$195 -> 0.00012334908
B87: 79 | C87: Utility | D87: =VLOOKUP(C87,Settings!$B$341:C906,2,FALSE) -> 5 | E87: Heavy and Light Transportation | F87: Commuting | G87: =VLOOKUP(F87,Settings!$B$163:D828,3,FALSE) -> P | H87: =VLOOKUP(F87,Settings!$B$163:D827,2,FALSE) -> 3 | I87: =VLOOKUP(F87,Settings!$B$163:F452,5,FALSE) -> 3 | J87: =_xlfn.TEXTJOIN("-",,D87,G87,B87) -> 5-P-79 | K87: =VLOOKUP(J87,'Employee Commuting'!$F$22:$N$29,6,FALSE) -> 1092.5488 | L87: =VLOOKUP(J87,'Employee Commuting'!$F$22:$N$29,7,FALSE) -> 1.3386048e-05 | M87: =VLOOKUP(J87,'Employee Commuting'!$F$22:$N$29,8,FALSE) -> 2.9853592e-05 | N87: 0 | O87: =VLOOKUP(J87,'Employee Commuting'!$F$22:$N$29,9,FALSE) -> 1092.5574 | P87: =O87/$O$195 -> 5.4187682e-05
B88: 80 | C88: Transportation | D88: =VLOOKUP(C88,Settings!$B$341:C907,2,FALSE) -> 6 | E88: Heavy and Light Transportation | F88: Commuting | G88: =VLOOKUP(F88,Settings!$B$163:D829,3,FALSE) -> P | H88: =VLOOKUP(F88,Settings!$B$163:D828,2,FALSE) -> 3 | I88: =VLOOKUP(F88,Settings!$B$163:F472,5,FALSE) -> 3 | J88: =_xlfn.TEXTJOIN("-",,D88,G88,B88) -> 6-P-80 | K88: =VLOOKUP(J88,'Employee Commuting'!$F$22:$N$29,6,FALSE) -> 3173.7121 | L88: =VLOOKUP(J88,'Employee Commuting'!$F$22:$N$29,7,FALSE) -> 3.8884727e-05 | M88: =VLOOKUP(J88,'Employee Commuting'!$F$22:$N$29,8,FALSE) -> 8.6720797e-05 | N88: 0 | O88: =VLOOKUP(J88,'Employee Commuting'!$F$22:$N$29,9,FALSE) -> 3173.7368 | P88: =O88/$O$195 -> 0.00015740816
B89: 81 | C89: Maintenance | D89: =VLOOKUP(C89,Settings!$B$341:C908,2,FALSE) -> 7 | E89: Heavy and Light Transportation | F89: Commuting | G89: =VLOOKUP(F89,Settings!$B$163:D830,3,FALSE) -> P | H89: =VLOOKUP(F89,Settings!$B$163:D829,2,FALSE) -> 3 | I89: =VLOOKUP(F89,Settings!$B$163:F479,5,FALSE) -> 3 | J89: =_xlfn.TEXTJOIN("-",,D89,G89,B89) -> 7-P-81 | K89: =VLOOKUP(J89,'Employee Commuting'!$F$22:$N$29,6,FALSE) -> 3173.7121 | L89: =VLOOKUP(J89,'Employee Commuting'!$F$22:$N$29,7,FALSE) -> 3.8884727e-05 | M89: =VLOOKUP(J89,'Employee Commuting'!$F$22:$N$29,8,FALSE) -> 8.6720797e-05 | N89: 0 | O89: =VLOOKUP(J89,'Employee Commuting'!$F$22:$N$29,9,FALSE) -> 3173.7368 | P89: =O89/$O$195 -> 0.00015740816
B90: 82 | C90: TAS | D90: =VLOOKUP(C90,Settings!$B$341:C910,2,FALSE) -> 9 | E90: Heavy and Light Transportation | F90: Commuting | G90: =VLOOKUP(F90,Settings!$B$163:D832,3,FALSE) -> P | H90: =VLOOKUP(F90,Settings!$B$163:D831,2,FALSE) -> 3 | I90: =VLOOKUP(F90,Settings!$B$163:F534,5,FALSE) -> 3 | J90: =_xlfn.TEXTJOIN("-",,D90,G90,B90) -> 9-P-82 | K90: =VLOOKUP(J90,'Employee Commuting'!$F$22:$N$29,6,FALSE) -> 16890.964 | L90: =VLOOKUP(J90,'Employee Commuting'!$F$22:$N$29,7,FALSE) -> 0.00024073787 | M90: =VLOOKUP(J90,'Employee Commuting'!$F$22:$N$29,8,FALSE) -> 0.00044046025 | N90: 0 | O90: =VLOOKUP(J90,'Employee Commuting'!$F$22:$N$29,9,FALSE) -> 16891.09 | P90: =O90/$O$195 -> 0.00083774919
B91: 83 | C91: Iron Making | D91: =VLOOKUP(C91,Settings!$B$341:C911,2,FALSE) -> 1 | E91: Business Travels | F91: Business travel | G91: =VLOOKUP(F91,Settings!$B$163:D833,3,FALSE) -> B | H91: =VLOOKUP(F91,Settings!$B$163:D832,2,FALSE) -> 3 | I91: =VLOOKUP(F91,Settings!$B$163:F196,5,FALSE) -> 3 | J91: =_xlfn.TEXTJOIN("-",,D91,G91,B91) -> 1-B-83 | K91: =VLOOKUP(J91,'Business Travel'!$L$175:$Q$182,3,FALSE) -> 22680.525 | L91: =VLOOKUP(J91,'Business Travel'!$L$175:$Q$182,4,FALSE) -> 3.0326378e-05 | M91: =VLOOKUP(J91,'Business Travel'!$L$175:$Q$182,5,FALSE) -> 0.00021426697 | N91: 0 | O91: =VLOOKUP(J91,'Business Travel'!$L$175:$Q$182,6,FALSE) -> 22680.585 | P91: =O91/$O$195 -> 0.0011248914
B92: 84 | C92: Steel Making | D92: =VLOOKUP(C92,Settings!$B$341:C912,2,FALSE) -> 2 | E92: Business Travels | F92: Business travel | G92: =VLOOKUP(F92,Settings!$B$163:D834,3,FALSE) -> B | H92: =VLOOKUP(F92,Settings!$B$163:D833,2,FALSE) -> 3 | I92: =VLOOKUP(F92,Settings!$B$163:F235,5,FALSE) -> 3 | J92: =_xlfn.TEXTJOIN("-",,D92,G92,B92) -> 2-B-84 | K92: =VLOOKUP(J92,'Business Travel'!$L$175:$Q$182,3,FALSE) -> 10484.415 | L92: =VLOOKUP(J92,'Business Travel'!$L$175:$Q$182,4,FALSE) -> 8.3217926e-05 | M92: =VLOOKUP(J92,'Business Travel'!$L$175:$Q$182,5,FALSE) -> 0.00061848116 | N92: 0 | O92: =VLOOKUP(J92,'Business Travel'!$L$175:$Q$182,6,FALSE) -> 10484.586 | P92: =O92/$O$195 -> 0.0005200051
B93: 85 | C93: Hot Rolling | D93: =VLOOKUP(C93,Settings!$B$341:C913,2,FALSE) -> 3 | E93: Business Travels | F93: Business travel | G93: =VLOOKUP(F93,Settings!$B$163:D835,3,FALSE) -> B | H93: =VLOOKUP(F93,Settings!$B$163:D834,2,FALSE) -> 3 | I93: =VLOOKUP(F93,Settings!$B$163:F341,5,FALSE) -> 3 | J93: =_xlfn.TEXTJOIN("-",,D93,G93,B93) -> 3-B-85 | K93: =VLOOKUP(J93,'Business Travel'!$L$175:$Q$182,3,FALSE) -> 3511.9685 | L93: =VLOOKUP(J93,'Business Travel'!$L$175:$Q$182,4,FALSE) -> 9.6469602e-05 | M93: =VLOOKUP(J93,'Business Travel'!$L$175:$Q$182,5,FALSE) -> 0.00076484147 | N93: 0 | O93: =VLOOKUP(J93,'Business Travel'!$L$175:$Q$182,6,FALSE) -> 3512.1799 | P93: =O93/$O$195 -> 0.00017419396
B94: 86 | C94: Cold Rolling | D94: =VLOOKUP(C94,Settings!$B$341:C914,2,FALSE) -> 4 | E94: Business Travels | F94: Business travel | G94: =VLOOKUP(F94,Settings!$B$163:D836,3,FALSE) -> B | H94: =VLOOKUP(F94,Settings!$B$163:D835,2,FALSE) -> 3 | I94: =VLOOKUP(F94,Settings!$B$163:F395,5,FALSE) -> 3 | J94: =_xlfn.TEXTJOIN("-",,D94,G94,B94) -> 4-B-86 | K94: =VLOOKUP(J94,'Business Travel'!$L$175:$Q$182,3,FALSE) -> 38379.847 | L94: =VLOOKUP(J94,'Business Travel'!$L$175:$Q$182,4,FALSE) -> 4.7482685e-05 | M94: =VLOOKUP(J94,'Business Travel'!$L$175:$Q$182,5,FALSE) -> 0.00030846928 | N94: 0 | O94: =VLOOKUP(J94,'Business Travel'!$L$175:$Q$182,6,FALSE) -> 38379.932 | P94: =O94/$O$195 -> 0.0019035336
B95: 87 | C95: Utility | D95: =VLOOKUP(C95,Settings!$B$341:C915,2,FALSE) -> 5 | E95: Business Travels | F95: Business travel | G95: =VLOOKUP(F95,Settings!$B$163:D837,3,FALSE) -> B | H95: =VLOOKUP(F95,Settings!$B$163:D836,2,FALSE) -> 3 | I95: =VLOOKUP(F95,Settings!$B$163:F453,5,FALSE) -> 3 | J95: =_xlfn.TEXTJOIN("-",,D95,G95,B95) -> 5-B-87 | K95: =VLOOKUP(J95,'Business Travel'!$L$175:$Q$182,3,FALSE) -> 10470.71 | L95: =VLOOKUP(J95,'Business Travel'!$L$175:$Q$182,4,FALSE) -> 2.7431429e-05 | M95: =VLOOKUP(J95,'Business Travel'!$L$175:$Q$182,5,FALSE) -> 0.00019998219 | N95: 0 | O95: =VLOOKUP(J95,'Business Travel'!$L$175:$Q$182,6,FALSE) -> 10470.765 | P95: =O95/$O$195 -> 0.00051931966
B96: 88 | C96: Transportation | D96: =VLOOKUP(C96,Settings!$B$341:C886,2,FALSE) -> 6 | E96: Business Travels | F96: Business travel | G96: =VLOOKUP(F96,Settings!$B$163:D838,3,FALSE) -> B | H96: =VLOOKUP(F96,Settings!$B$163:D837,2,FALSE) -> 3 | I96: =VLOOKUP(F96,Settings!$B$163:F473,5,FALSE) -> 3 | J96: =_xlfn.TEXTJOIN("-",,D96,G96,B96) -> 6-B-88 | K96: =VLOOKUP(J96,'Business Travel'!$L$175:$Q$182,3,FALSE) -> 17441.821 | L96: =VLOOKUP(J96,'Business Travel'!$L$175:$Q$182,4,FALSE) -> 7.2317043e-06 | M96: =VLOOKUP(J96,'Business Travel'!$L$175:$Q$182,5,FALSE) -> 3.1485711e-05 | N96: 0 | O96: =VLOOKUP(J96,'Business Travel'!$L$175:$Q$182,6,FALSE) -> 17441.83 | P96: =O96/$O$195 -> 0.0008650643
B97: 89 | C97: Maintenance | D97: =VLOOKUP(C97,Settings!$B$341:C887,2,FALSE) -> 7 | E97: Business Travels | F97: Business travel | G97: =VLOOKUP(F97,Settings!$B$163:D839,3,FALSE) -> B | H97: =VLOOKUP(F97,Settings!$B$163:D838,2,FALSE) -> 3 | I97: =VLOOKUP(F97,Settings!$B$163:F480,5,FALSE) -> 3 | J97: =_xlfn.TEXTJOIN("-",,D97,G97,B97) -> 7-B-89 | K97: =VLOOKUP(J97,'Business Travel'!$L$175:$Q$182,3,FALSE) -> 49033.681 | L97: =VLOOKUP(J97,'Business Travel'!$L$175:$Q$182,4,FALSE) -> 0.00082910252 | M97: =VLOOKUP(J97,'Business Travel'!$L$175:$Q$182,5,FALSE) -> 0.0063059203 | N97: 0 | O97: =VLOOKUP(J97,'Business Travel'!$L$175:$Q$182,6,FALSE) -> 49035.425 | P97: =O97/$O$195 -> 0.0024320151
B98: 90 | C98: TAS | D98: =VLOOKUP(C98,Settings!$B$341:C889,2,FALSE) -> 9 | E98: Business Travels | F98: Business travel | G98: =VLOOKUP(F98,Settings!$B$163:D841,3,FALSE) -> B | H98: =VLOOKUP(F98,Settings!$B$163:D840,2,FALSE) -> 3 | I98: =VLOOKUP(F98,Settings!$B$163:F535,5,FALSE) -> 3 | J98: =_xlfn.TEXTJOIN("-",,D98,G98,B98) -> 9-B-90 | K98: =VLOOKUP(J98,'Business Travel'!$L$175:$Q$182,3,FALSE) -> 552943.65 | L98: =VLOOKUP(J98,'Business Travel'!$L$175:$Q$182,4,FALSE) -> 0.00026861913 | M98: =VLOOKUP(J98,'Business Travel'!$L$175:$Q$182,5,FALSE) -> 0.0019582876 | N98: 0 | O98: =VLOOKUP(J98,'Business Travel'!$L$175:$Q$182,6,FALSE) -> 552944.19 | P98: =O98/$O$195 -> 0.027424432
B99: 91 | C99: Iron Making | D99: =VLOOKUP(C99,Settings!$B$341:C352,2,FALSE) -> 1 | E99: Raw material CF | F99: Purchased Material | G99: =VLOOKUP(F99,Settings!$B$163:D183,3,FALSE) -> R | H99: =VLOOKUP(F99,Settings!$B$163:D183,2,FALSE) -> 4 | I99: =VLOOKUP(F99,Settings!$B$163:F202,5,FALSE) -> 3 | J99: =_xlfn.TEXTJOIN("-",,D99,G99,B99) -> 1-R-91 | K99: =VLOOKUP(J99,'Purchased Material'!$J$178:L185,3,FALSE) -> 2113407.5 | L99: 0 | M99: 0 | N99: 0 | O99: =VLOOKUP(J99,'Purchased Material'!$J$178:L185,3,FALSE) -> 2113407.5 | P99: =O99/$O$195 -> 0.1048189
B100: 92 | C100: Steel Making | D100: =VLOOKUP(C100,Settings!$B$341:C402,2,FALSE) -> 2 | E100: Raw material CF | F100: Purchased Material | G100: =VLOOKUP(F100,Settings!$B$163:D344,3,FALSE) -> R | H100: =VLOOKUP(F100,Settings!$B$163:D343,2,FALSE) -> 4 | I100: =VLOOKUP(F100,Settings!$B$163:F240,5,FALSE) -> 3 | J100: =_xlfn.TEXTJOIN("-",,D100,G100,B100) -> 2-R-92 | K100: =VLOOKUP(J100,'Purchased Material'!$J$178:L224,3,FALSE) -> 5466193.6 | L100: 0 | M100: 0 | N100: 0 | O100: =VLOOKUP(J100,'Purchased Material'!$J$178:L224,3,FALSE) -> 5466193.6 | P100: =O100/$O$195 -> 0.27110738
B101: 93 | C101: Hot Rolling | D101: =VLOOKUP(C101,Settings!$B$341:C543,2,FALSE) -> 3 | E101: Raw material CF | F101: Purchased Material | G101: =VLOOKUP(F101,Settings!$B$163:D465,3,FALSE) -> R | H101: =VLOOKUP(F101,Settings!$B$163:D464,2,FALSE) -> 4 | I101: =VLOOKUP(F101,Settings!$B$163:F344,5,FALSE) -> 3 | J101: =_xlfn.TEXTJOIN("-",,D101,G101,B101) -> 3-R-93 | K101: =VLOOKUP(J101,'Purchased Material'!$J$178:L259,3,FALSE) -> 57.124733 | L101: 0 | M101: 0 | N101: 0 | O101: =VLOOKUP(J101,'Purchased Material'!$J$178:L259,3,FALSE) -> 57.124733 | P101: =O101/$O$195 -> 2.8332214e-06
B102: 94 | C102: Cold Rolling | D102: =VLOOKUP(C102,Settings!$B$341:C577,2,FALSE) -> 4 | E102: Raw material CF | F102: Purchased Material | G102: =VLOOKUP(F102,Settings!$B$163:D499,3,FALSE) -> R | H102: =VLOOKUP(F102,Settings!$B$163:D498,2,FALSE) -> 4 | I102: =VLOOKUP(F102,Settings!$B$163:F395,5,FALSE) -> 3 | J102: =_xlfn.TEXTJOIN("-",,D102,G102,B102) -> 4-R-94 | K102: =VLOOKUP(J102,'Purchased Material'!$J$178:L324,3,FALSE) -> 24775.524 | L102: 0 | M102: 0 | N102: 0 | O102: =VLOOKUP(J102,'Purchased Material'!$J$178:L324,3,FALSE) -> 24775.524 | P102: =O102/$O$195 -> 0.0012287943
B103: 95 | C103: Utility | D103: =VLOOKUP(C103,Settings!$B$341:C918,2,FALSE) -> 5 | E103: Raw material CF | F103: Purchased Material | G103: =VLOOKUP(F103,Settings!$B$163:D870,3,FALSE) -> R | H103: =VLOOKUP(F103,Settings!$B$163:D869,2,FALSE) -> 4 | I103: =VLOOKUP(F103,Settings!$B$163:F537,5,FALSE) -> 3 | J103: =_xlfn.TEXTJOIN("-",,D103,G103,B103) -> 5-R-95 | K103: =VLOOKUP(J103,'Purchased Material'!$J$178:L397,3,FALSE) -> 0 | L103: 0 | M103: 0 | N103: 0 | O103: =VLOOKUP(J103,'Purchased Material'!$J$178:L397,3,FALSE) -> 0 | P103: =O103/$O$195 -> 0
B104: 96 | C104: Transportation | D104: =VLOOKUP(C104,Settings!$B$341:C919,2,FALSE) -> 6 | E104: Raw material CF | F104: Purchased Material | G104: =VLOOKUP(F104,Settings!$B$163:D871,3,FALSE) -> R | H104: =VLOOKUP(F104,Settings!$B$163:D870,2,FALSE) -> 4 | I104: =VLOOKUP(F104,Settings!$B$163:F538,5,FALSE) -> 3 | J104: =_xlfn.TEXTJOIN("-",,D104,G104,B104) -> 6-R-96 | K104: =VLOOKUP(J104,'Purchased Material'!$J$178:L411,3,FALSE) -> 0 | L104: 0 | M104: 0 | N104: 0 | O104: =VLOOKUP(J104,'Purchased Material'!$J$178:L411,3,FALSE) -> 0 | P104: =O104/$O$195 -> 0
B105: 97 | C105: Maintenance | D105: =VLOOKUP(C105,Settings!$B$341:C920,2,FALSE) -> 7 | E105: Raw material CF | F105: Purchased Material | G105: =VLOOKUP(F105,Settings!$B$163:D872,3,FALSE) -> R | H105: =VLOOKUP(F105,Settings!$B$163:D871,2,FALSE) -> 4 | I105: =VLOOKUP(F105,Settings!$B$163:F539,5,FALSE) -> 3 | J105: =_xlfn.TEXTJOIN("-",,D105,G105,B105) -> 7-R-97 | K105: =VLOOKUP(J105,'Purchased Material'!$J$178:L419,3,FALSE) -> 0 | L105: 0 | M105: 0 | N105: 0 | O105: =VLOOKUP(J105,'Purchased Material'!$J$178:L419,3,FALSE) -> 0 | P105: =O105/$O$195 -> 0
B106: 98 | C106: TAS | D106: =VLOOKUP(C106,Settings!$B$341:C923,2,FALSE) -> 9 | E106: Raw material CF | F106: Purchased Material | G106: =VLOOKUP(F106,Settings!$B$163:D875,3,FALSE) -> R | H106: =VLOOKUP(F106,Settings!$B$163:D874,2,FALSE) -> 4 | I106: =VLOOKUP(F106,Settings!$B$163:F542,5,FALSE) -> 3 | J106: =_xlfn.TEXTJOIN("-",,D106,G106,B106) -> 9-R-98 | K106: =VLOOKUP(J106,'Purchased Material'!$J$178:L475,3,FALSE) -> 0 | L106: 0 | M106: 0 | N106: 0 | O106: =VLOOKUP(J106,'Purchased Material'!$J$178:L475,3,FALSE) -> 0 | P106: =O106/$O$195 -> 0
B107: 99 | C107: Iron Making | D107: =VLOOKUP(C107,Settings!$B$341:C984,2,FALSE) -> 1 | E107: Ancillary Input | F107: Ancillary Input | G107: =VLOOKUP(F107,Settings!$B$163:D886,3,FALSE) -> L | H107: =VLOOKUP(F107,Settings!$B$163:D885,2,FALSE) -> 4 | I107: =VLOOKUP(F107,Settings!$B$163:F593,5,FALSE) -> 3 | J107: =_xlfn.TEXTJOIN("-",,D107,G107,B107) -> 1-L-99 | K107: =VLOOKUP(J107,'Ancillary Input'!$J$309:$L$316,3,FALSE) -> 1939.8702 | L107: 0 | M107: 0 | N107: 0 | O107: =VLOOKUP(J107,'Ancillary Input'!$J$309:$L$316,3,FALSE) -> 1939.8702 | P107: =O107/$O$195 -> 9.6211946e-05
B108: 100 | C108: Steel Making | D108: =VLOOKUP(C108,Settings!$B$341:C985,2,FALSE) -> 2 | E108: Ancillary Input | F108: Ancillary Input | G108: =VLOOKUP(F108,Settings!$B$163:D887,3,FALSE) -> L | H108: =VLOOKUP(F108,Settings!$B$163:D886,2,FALSE) -> 4 | I108: =VLOOKUP(F108,Settings!$B$163:F594,5,FALSE) -> 3 | J108: =_xlfn.TEXTJOIN("-",,D108,G108,B108) -> 2-L-100 | K108: =VLOOKUP(J108,'Ancillary Input'!$J$309:$L$316,3,FALSE) -> 769.6061 | L108: 0 | M108: 0 | N108: 0 | O108: =VLOOKUP(J108,'Ancillary Input'!$J$309:$L$316,3,FALSE) -> 769.6061 | P108: =O108/$O$195 -> 3.8170235e-05
B109: 101 | C109: Hot Rolling | D109: =VLOOKUP(C109,Settings!$B$341:C986,2,FALSE) -> 3 | E109: Ancillary Input | F109: Ancillary Input | G109: =VLOOKUP(F109,Settings!$B$163:D888,3,FALSE) -> L | H109: =VLOOKUP(F109,Settings!$B$163:D887,2,FALSE) -> 4 | I109: =VLOOKUP(F109,Settings!$B$163:F595,5,FALSE) -> 3 | J109: =_xlfn.TEXTJOIN("-",,D109,G109,B109) -> 3-L-101 | K109: =VLOOKUP(J109,'Ancillary Input'!$J$309:$L$316,3,FALSE) -> 2775.4876 | L109: 0 | M109: 0 | N109: 0 | O109: =VLOOKUP(J109,'Ancillary Input'!$J$309:$L$316,3,FALSE) -> 2775.4876 | P109: =O109/$O$195 -> 0.00013765615
...

Sheet Tables & Graphs
B7: Click to see the results of each section. | H7: Total | K7: Area Comparison
H9: Iron Making | K9: Steel Making | N9: Hot Rolling | Q9: Cold Rolling
H11: Transportation | K11: Maintenance | N11: Utility | Q11: TAS
B13: Total
B20: Emission of Areas
B21: Area | C21: Code | E21: Emission (tCO2e/yr) | F21: Share (%)
B22: Iron Making | C22: =VLOOKUP(B22,Settings!$B$341:C348,2,FALSE) -> 1 | E22: =SUMIF(Inventory!$C$9:$C$194,B22,Inventory!$O$9:$O$194) -> 7182736.2 | F22: =E22/$E$30 -> 0.35624293
B23: Steel Making | C23: =VLOOKUP(B23,Settings!$B$341:C349,2,FALSE) -> 2 | E23: =SUMIF(Inventory!$C$9:$C$194,B23,Inventory!$O$9:$O$194) -> 9305750 | F23: =E23/$E$30 -> 0.46153827
B24: Hot Rolling | C24: =VLOOKUP(B24,Settings!$B$341:C350,2,FALSE) -> 3 | E24: =SUMIF(Inventory!$C$9:$C$194,B24,Inventory!$O$9:$O$194) -> 463713.2 | F24: =E24/$E$30 -> 0.022998832
B25: Cold Rolling | C25: =VLOOKUP(B25,Settings!$B$341:C351,2,FALSE) -> 4 | E25: =SUMIF(Inventory!$C$9:$C$194,B25,Inventory!$O$9:$O$194) -> 260650.53 | F25: =E25/$E$30 -> 0.012927512
B26: Utility | C26: =VLOOKUP(B26,Settings!$B$341:C352,2,FALSE) -> 5 | E26: =SUMIF(Inventory!$C$9:$C$194,B26,Inventory!$O$9:$O$194) -> 2099578.7 | F26: =E26/$E$30 -> 0.10413303
B27: Transportation | C27: =VLOOKUP(B27,Settings!$B$341:C353,2,FALSE) -> 6 | E27: =SUMIF(Inventory!$C$9:$C$194,B27,Inventory!$O$9:$O$194) -> 35746.127 | F27: =E27/$E$30 -> 0.0017729045
B28: Maintenance | C28: =VLOOKUP(B28,Settings!$B$341:C362,2,FALSE) -> 7 | E28: =SUMIF(Inventory!$C$9:$C$194,B28,Inventory!$O$9:$O$194) -> 74832.07 | F28: =E28/$E$30 -> 0.0037114541
B29: TAS | C29: =VLOOKUP(B29,Settings!$B$341:C364,2,FALSE) -> 9 | E29: =SUMIF(Inventory!$C$9:$C$194,B29,Inventory!$O$9:$O$194) -> 739460.05 | F29: =E29/$E$30 -> 0.036675078
B30: Sum | E30: =_xlfn.AGGREGATE(9,6,E22:E29) -> 20162467 | F30: =SUM(F22:F29) -> 1
B40: Emissions by Types
B41: Emission type | C41: Sign | D41: Category | E41: Emission (tCO2e/yr) | F41: Share (%)
B42: Combustion | C42: =VLOOKUP(B42,Settings!$B$163:$D$180,3,FALSE) -> C | D42: =VLOOKUP(B42,Settings!$B$163:$C$180,2,FALSE) -> 1 | E42: =SUMIF(Inventory!$G$9:$G$194,C42,Inventory!$O$9:$O$194) -> 1296747 | F42: =E42/$E$58 -> 0.064314898
B43: Vent | C43: =VLOOKUP(B43,Settings!$B$163:$D$180,3,FALSE) -> V | D43: =VLOOKUP(B43,Settings!$B$163:$C$180,2,FALSE) -> 1 | E43: =SUMIF(Inventory!$G$9:$G$194,C43,Inventory!$O$9:$O$194) -> 4293669.3 | F43: =E43/$E$58 -> 0.21295357
B44: Fugitive | C44: =VLOOKUP(B44,Settings!$B$163:$D$180,3,FALSE) -> F | D44: =VLOOKUP(B44,Settings!$B$163:$C$180,2,FALSE) -> 1 | E44: =SUMIF(Inventory!$G$9:$G$194,C44,Inventory!$O$9:$O$194) -> 13618.733 | F44: =E44/$E$58 -> 0.00067544973
B45: Mobile Combustion | C45: =VLOOKUP(B45,Settings!$B$163:$D$180,3,FALSE) -> M | D45: =VLOOKUP(B45,Settings!$B$163:$C$180,2,FALSE) -> 1 | E45: =SUMIF(Inventory!$G$9:$G$194,C45,Inventory!$O$9:$O$194) -> 49101.16 | F45: =E45/$E$58 -> 0.0024352754
B46: Waste Onsite | C46: =VLOOKUP(B46,Settings!$B$163:$D$180,3,FALSE) -> W | D46: =VLOOKUP(B46,Settings!$B$163:$C$180,2,FALSE) -> 1 | E46: =SUMIF(Inventory!$G$9:$G$194,C46,Inventory!$O$9:$O$194) -> 90516.963 | F46: =E46/$E$58 -> 0.0044893794
B47: Wastewater | C47: =VLOOKUP(B47,Settings!$B$163:$D$180,3,FALSE) -> Y | D47: =VLOOKUP(B47,Settings!$B$163:$C$180,2,FALSE) -> 1 | E47: =SUMIF(Inventory!$G$9:$G$194,C47,Inventory!$O$9:$O$194) -> 597.43271 | F47: =E47/$E$58 -> 2.9630933e-05
B48: Electricity | C48: =VLOOKUP(B48,Settings!$B$163:$D$180,3,FALSE) -> E | D48: =VLOOKUP(B48,Settings!$B$163:$C$180,2,FALSE) -> 2 | E48: =SUMIF(Inventory!$G$9:$G$194,C48,Inventory!$O$9:$O$194) -> 4539539.9 | F48: =E48/$E$58 -> 0.22514804
B49: Up-Transportation | C49: =VLOOKUP(B49,Settings!$B$163:$D$180,3,FALSE) -> T | D49: =VLOOKUP(B49,Settings!$B$163:$C$180,2,FALSE) -> 3 | E49: =SUMIF(Inventory!$G$9:$G$194,C49,Inventory!$O$9:$O$194) -> 488422.61 | F49: =E49/$E$58 -> 0.024224348
B50: Down-Transportation | C50: =VLOOKUP(B50,Settings!$B$163:$D$180,3,FALSE) -> D | D50: =VLOOKUP(B50,Settings!$B$163:$C$180,2,FALSE) -> 3 | E50: =SUMIF(Inventory!$G$9:$G$194,C50,Inventory!$O$9:$O$194) -> 0 | F50: =E50/$E$58 -> 0
B51: Commuting | C51: =VLOOKUP(B51,Settings!$B$163:$D$180,3,FALSE) -> P | D51: =VLOOKUP(B51,Settings!$B$163:$C$180,2,FALSE) -> 3 | E51: =SUMIF(Inventory!$G$9:$G$194,C51,Inventory!$O$9:$O$194) -> 33906.774 | F51: =E51/$E$58 -> 0.0016816779
B52: Business travel | C52: =VLOOKUP(B52,Settings!$B$163:$D$180,3,FALSE) -> B | D52: =VLOOKUP(B52,Settings!$B$163:$C$180,2,FALSE) -> 3 | E52: =SUMIF(Inventory!$G$9:$G$194,C52,Inventory!$O$9:$O$194) -> 704949.5 | F52: =E52/$E$58 -> 0.034963455
B53: Purchased Material | C53: =VLOOKUP(B53,Settings!$B$163:$D$180,3,FALSE) -> R | D53: =VLOOKUP(B53,Settings!$B$163:$C$180,2,FALSE) -> 4 | E53: =SUMIF(Inventory!$G$9:$G$194,C53,Inventory!$O$9:$O$194) -> 7604433.7 | F53: =E53/$E$58 -> 0.3771579
... B57: Energy related | C57: =VLOOKUP(B57,Settings!$B$163:$D$180,3,FALSE) -> N | D57: =VLOOKUP(B57,Settings!$B$163:$C$180,2,FALSE) -> 4 | E57: =SUMIF(Inventory!$G$9:$G$194,C57,Inventory!$O$9:$O$194) -> 1001844.7 | F57: =E57/$E$58 -> 0.049688597
B58: Sum | E58: =_xlfn.AGGREGATE(9,6,E42:E57) -> 20162467 | F58: =SUM(F42:F57) -> 1
B66: Emissions by Categories
B67: Category | E67: Emission (tCO2e/yr) | F67: Share (%)
B68: 1 | E68: =SUMIF(Inventory!$H$9:$H$194,B68,Inventory!$O$9:$O$194) -> 5744250.6 | F68: =E68/$E$74 -> 0.2848982
B69: 2 | E69: =SUMIF(Inventory!$H$9:$H$194,B69,Inventory!$O$9:$O$194) -> 4539539.9 | F69: =E69/$E$74 -> 0.22514804
B70: 3 | E70: =SUMIF(Inventory!$H$9:$H$194,B70,Inventory!$O$9:$O$194) -> 1227278.9 | F70: =E70/$E$74 -> 0.06086948
B71: 4 | E71: =SUMIF(Inventory!$H$9:$H$194,B71,Inventory!$O$9:$O$194) -> 8651397.6 | F71: =E71/$E$74 -> 0.42908428
B72: 5 | E72: =SUMIF(Inventory!$H$9:$H$194,B72,Inventory!$O$9:$O$194) -> 0 | F72: =E72/$E$74 -> 0
B73: 6 | E73: =SUMIF(Inventory!$H$9:$H$194,B73,Inventory!$O$9:$O$194) -> 0 | F73: =E73/$E$74 -> 0
B74: Sum | E74: =_xlfn.AGGREGATE(9,6,E68:E73) -> 20162467 | F74: =SUM(F68:F73) -> 1
B86: Emissions by GHGs
B87: GHG | C87: Formula | E87: Emission (t/yr) | F87: Share (%)
B88: Carbon Dioxide | C88: CO2 | E88: =Inventory!K195 -> 18543415 | F88: =E88/$E$92 -> 0.99680909
B89: Methane | C89: CH4 | E89: =Inventory!L195 -> 59333.236 | F89: =E89/$E$92 -> 0.0031894831
B90: Nitrous Oxide | C90: N2O | E90: =Inventory!M195 -> 26.23175 | F90: =E90/$E$92 -> 1.4100987e-06
B91: Sulfur Hexafluoride | C91: SF6 | E91: =Inventory!N195 -> 0.4 | F91: =E91/$E$92 -> 2.1502168e-08
B92: Sum | E92: =SUM(E88:E91) -> 18602775 | F92: =SUM(F88:F90) -> 0.99999998
B105: Emissions by Scope
B106: Scope | E106: Emission (t/yr) | F106: Share (%)
B107: Scope 1 | E107: =E68 -> 5744250.6 | F107: =E107/$E$110 -> 0.2848982
B108: Scope 2 | E108: =E69 -> 4539539.9 | F108: =E108/$E$110 -> 0.22514804
B109: Scope 3 | E109: =SUM(E70:E73) -> 9878676.5 | F109: =E109/$E$110 -> 0.48995376
B110: Sum | E110: =SUM(E107:E109) -> 20162467 | F110: =SUM(F107:F109) -> 1
B117: Emissions | C117: Scope | E117: Emission Type | F117: tCO2e | G117: tCO2e | J117: Direct Emissions
B118: Direct Emissions | C118: 1 | E118: C | F118: =SUM(E42:E47) -> 5744250.6 | G118: =F118+F124 -> 20162467 | J118: GHG | L118: CO2 | N118: CH4 (V,F) | P118: CH4 (C,B) | R118: N2O | T118: SF6
E119: V | J119: GWP | L119: =Settings!B24 -> 1 | N119: =Settings!G24 -> 29.8 | P119: =Settings!C24 -> 27 | R119: =Settings!D24 -> 273 | T119: =Settings!E24 -> 24300
E120: F | J120: tonnes | L120: =SUMIF(Inventory!I9:I194,C118,Inventory!K9:K194) -> 5730262.6 | N120: =SUMIF(Inventory!G9:G194,E119,Inventory!L9:L194)+SUMIF(Inventory!G9:G194,E120,Inventory!L9:L194) -> 61.836212 | P120: =SUMIF(Inventory!G9:G194,E118,Inventory!L9:L194)+SUMIF(Inventory!G9:G194,E123,Inventory!L9:L194) -> 45.412614 | R120: =SUMIF(Inventory!I9:I194,C118,Inventory!M9:M194) -> 4.1903429 | T120: =SUMIF(Inventory!I9:I194,C118,Inventory!N9:N194) -> 0.4
E121: M | J121: tCO2e | L121: =L120*L119 -> 5730262.6 | N121: =N120*N119 -> 1842.7191 | P121: =P120*P119 -> 1226.1406 | R121: =R120*R119 -> 1143.9636 | T121: =T120*T119 -> 9720
E122: W | J122: tCO2e | L122: =L121 -> 5730262.6 | N122: =N121+P121 -> 3068.8597 | R122: =R121 -> 1143.9636 | T122: =T121 -> 9720
E123: Y | J123: Sum | L123: =SUM(L122:U122) -> 5744195.4
B124: Indirect Emissions | C124: 2,3 | E124: E, T, D, P, B, R, L, X, N | F124: =SUM(E48:E57) -> 14418216
B125: Non-Kyoto GHGs Emissions | C125: 1 | E125: - | F125: =Fugitive!L108 -> 85633.728 | G125: =F125 -> 85633.728
A129: 1 | B129: Iron Making
B132: Emission Type | C132: Sign | D132: Category | E132: Emission (tCO2e/yr) | F132: Share (%) | G132: Categories Emission (tCO2e) | H132: Categories Emission (%)
B133: Combustion | C133: =VLOOKUP(B133,Settings!$B$163:D242,3,FALSE) -> C | D133: Cat1 | E133: =SUMIFS(Inventory!$O$9:$O$194,Inventory!$D$9:$D$194,1,Inventory!$G$9:$G$194,C133) -> 126543.21 | F133: =E133/$E$149 -> 0.017617688 | G133: =SUM(E133:E138) -> 4060422 | H133: =G133/G149 -> 0.56530296
B134: Vent | C134: =VLOOKUP(B134,Settings!$B$163:D242,3,FALSE) -> V | E134: =SUMIFS(Inventory!$O$9:$O$194,Inventory!$D$9:$D$194,1,Inventory!$G$9:$G$194,C134) -> 3866055.4 | F134: =E134/$E$149 -> 0.5382427
B135: Fugitive | C135: =VLOOKUP(B135,Settings!$B$163:D242,3,FALSE) -> F | E135: =SUMIFS(Inventory!$O$9:$O$194,Inventory!$D$9:$D$194,1,Inventory!$G$9:$G$194,C135) -> 437.19189 | F135: =E135/$E$149 -> 6.086704e-05
B136: Mobile Combustion | C136: =VLOOKUP(B136,Settings!$B$163:D242,3,FALSE) -> M | E136: =SUMIFS(Inventory!$O$9:$O$194,Inventory!$D$9:$D$194,1,Inventory!$G$9:$G$194,C136) -> 9022.3649 | F136: =E136/$E$149 -> 0.0012561181
B137: Waste Onsite | C137: =VLOOKUP(B137,Settings!$B$163:D243,3,FALSE) -> W | E137: =SUMIFS(Inventory!$O$9:$O$194,Inventory!$D$9:$D$194,1,Inventory!$G$9:$G$194,C137) -> 58165.408 | F137: =E137/$E$149 -> 0.0080979457
B138: Wastewater | C138: =VLOOKUP(B138,Settings!$B$163:D244,3,FALSE) -> Y | E138: =SUMIFS(Inventory!$O$9:$O$194,Inventory!$D$9:$D$194,1,Inventory!$G$9:$G$194,C138) -> 198.48987 | F138: =E138/$E$149 -> 2.7634298e-05
B139: Electricity | C139: =VLOOKUP(B139,Settings!$B$163:D243,3,FALSE) -> E | D139: Cat2 | E139: =SUMIFS(Inventory!$O$9:$O$194,Inventory!$D$9:$D$194,1,Inventory!$G$9:$G$194,C139) -> 604626.02 | F139: =E139/$E$149 -> 0.084177673 | G139: =E139 -> 604626.02 | H139: =G139/G149 -> 0.084177673
B140: Up-Transportation | C140: =VLOOKUP(B140,Settings!$B$163:D246,3,FALSE) -> T | D140: Cat3 | E140: =SUMIFS(Inventory!$O$9:$O$194,Inventory!$D$9:$D$194,1,Inventory!$G$9:$G$194,C140) -> 323232.53 | F140: =E140/$E$149 -> 0.045001309 | G140: =SUM(E140:E143) -> 347858.19 | H140: =G140/G149 -> 0.04842976
B141: Down-Transportation | C141: =VLOOKUP(B141,Settings!$B$163:D247,3,FALSE) -> D | E141: =SUMIFS(Inventory!$O$9:$O$194,Inventory!$D$9:$D$194,1,Inventory!$G$9:$G$194,C141) -> 0 | F141: =E141/$E$149 -> 0
B142: Commuting | C142: =VLOOKUP(B142,Settings!$B$163:D248,3,FALSE) -> P | E142: =SUMIFS(Inventory!$O$9:$O$194,Inventory!$D$9:$D$194,1,Inventory!$G$9:$G$194,C142) -> 1945.0738 | F142: =E142/$E$149 -> 0.00027079844
B143: Business travel | C143: =VLOOKUP(B143,Settings!$B$163:D249,3,FALSE) -> B | E143: =SUMIFS(Inventory!$O$9:$O$194,Inventory!$D$9:$D$194,1,Inventory!$G$9:$G$194,C143) -> 22680.585 | F143: =E143/$E$149 -> 0.0031576525
B144: Purchased Material | C144: =VLOOKUP(B144,Settings!$B$163:D250,3,FALSE) -> R | D144: Cat4 | E144: =SUMIFS(Inventory!$O$9:$O$194,Inventory!$D$9:$D$194,1,Inventory!$G$9:$G$194,C144) -> 2113407.5 | F144: =E144/$E$149 -> 0.29423432 | G144: =SUM(E144:E148) -> 2169830 | H144: =G144/G149 -> 0.30208961
B145: Ancillary Input | C145: =VLOOKUP(B145,Settings!$B$163:D251,3,FALSE) -> L | E145: =SUMIFS(Inventory!$O$9:$O$194,Inventory!$D$9:$D$194,1,Inventory!$G$9:$G$194,C145) -> 1939.8702 | F145: =E145/$E$149 -> 0.00027007398
B146: Purchased Services | C146: =VLOOKUP(B146,Settings!$B$163:D252,3,FALSE) -> X | E146: =SUMIFS(Inventory!$O$9:$O$194,Inventory!$D$9:$D$194,1,Inventory!$G$9:$G$194,C146) -> 1884.7867 | F146: =E146/$E$149 -> 0.00026240511
B147: Waste Offsite | C147: =VLOOKUP(B147,Settings!$B$163:D253,3,FALSE) -> Z | E147: =SUMIFS(Inventory!$O$9:$O$194,Inventory!$D$9:$D$194,1,Inventory!$G$9:$G$194,C147) -> 0 | F147: =E147/$E$149 -> 0
B148: Energy related | C148: =VLOOKUP(B148,Settings!$B$163:D252,3,FALSE) -> N | E148: =SUMIFS(Inventory!$O$9:$O$194,Inventory!$D$9:$D$194,1,Inventory!$G$9:$G$194,C148) -> 52597.782 | F148: =E148/$E$149 -> 0.0073228058
B149: Sum | E149: =_xlfn.AGGREGATE(9,6,E133:E148) -> 7182736.2 | F149: =SUM(F133:F148) -> 1 | G149: =SUM(G133:G148) -> 7182736.2 | H149: =SUM(H133:H148) -> 1
A154: 2 | B154: Steel Making
B157: Emission Type | C157: Sign | D157: Category | E157: Emission (tCO2e/yr) | F157: Share (%) | G157: Categories Emission (tCO2e) | H157: Categories Emission (%)
B158: Combustion | C158: =VLOOKUP(B158,Settings!$B$163:D340,3,FALSE) -> C | D158: Cat1 | E158: =SUMIFS(Inventory!$O$9:$O$194,Inventory!$D$9:$D$194,2,Inventory!$G$9:$G$194,C158) -> 34884.813 | F158: =E158/$E$174 -> 0.0037487374 | G158: =SUM(E158:E163) -> 495709.88 | H158: =G158/G174 -> 0.053269203
B159: Vent | C159: =VLOOKUP(B159,Settings!$B$163:D340,3,FALSE) -> V | E159: =SUMIFS(Inventory!$O$9:$O$194,Inventory!$D$9:$D$194,2,Inventory!$G$9:$G$194,C159) -> 427613.9 | F159: =E159/$E$174 -> 0.045951578
B160: Fugitive | C160: =VLOOKUP(B160,Settings!$B$163:D341,3,FALSE) -> F | E160: =SUMIFS(Inventory!$O$9:$O$194,Inventory!$D$9:$D$194,2,Inventory!$G$9:$G$194,C160) -> 513.52953 | F160: =E160/$E$174 -> 5.5184109e-05
B161: Mobile Combustion | C161: =VLOOKUP(B161,Settings!$B$163:D342,3,FALSE) -> M | E161: =SUMIFS(Inventory!$O$9:$O$194,Inventory!$D$9:$D$194,2,Inventory!$G$9:$G$194,C161) -> 198.70349 | F161: =E161/$E$174 -> 2.1352765e-05
B162: Waste Onsite | C162: =VLOOKUP(B162,Settings!$B$163:D343,3,FALSE) -> W | E162: =SUMIFS(Inventory!$O$9:$O$194,Inventory!$D$9:$D$194,2,Inventory!$G$9:$G$194,C162) -> 32351.556 | F162: =E162/$E$174 -> 0.0034765125
B163: Wastewater | C163: =VLOOKUP(B163,Settings!$B$163:D344,3,FALSE) -> Y | E163: =SUMIFS(Inventory!$O$9:$O$194,Inventory!$D$9:$D$194,2,Inventory!$G$9:$G$194,C163) -> 147.38568 | F163: =E163/$E$174 -> 1.5838131e-05
B164: Electricity | C164: =VLOOKUP(B164,Settings!$B$163:D343,3,FALSE) -> E | D164: Cat2 | E164: =SUMIFS(Inventory!$O$9:$O$194,Inventory!$D$9:$D$194,2,Inventory!$G$9:$G$194,C164) -> 3142290.2 | F164: =E164/$E$174 -> 0.33767189 | G164: =E164 -> 3142290.2 | H164: =G164/G174 -> 0.33767189
B165: Up-Transportation | C165: =VLOOKUP(B165,Settings!$B$163:D346,3,FALSE) -> T | D165: Cat3 | E165: =SUMIFS(Inventory!$O$9:$O$194,Inventory!$D$9:$D$194,2,Inventory!$G$9:$G$194,C165) -> 165190.08 | F165: =E165/$E$174 -> 0.017751398 | G165: =SUM(E165:E168) -> 179228.26 | H165: =G165/G174 -> 0.019259948
B166: Down-Transportation | C166: =VLOOKUP(B166,Settings!$B$163:D347,3,FALSE) -> D | E166: =SUMIFS(Inventory!$O$9:$O$194,Inventory!$D$9:$D$194,2,Inventory!$G$9:$G$194,C166) -> 0 | F166: =E166/$E$174 -> 0
B167: Commuting | C167: =VLOOKUP(B167,Settings!$B$163:D347,3,FALSE) -> P | E167: =SUMIFS(Inventory!$O$9:$O$194,Inventory!$D$9:$D$194,2,Inventory!$G$9:$G$194,C167) -> 3553.5954 | F167: =E167/$E$174 -> 0.00038187093
B168: Business travel | C168: =VLOOKUP(B168,Settings!$B$163:D348,3,FALSE) -> B | E168: =SUMIFS(Inventory!$O$9:$O$194,Inventory!$D$9:$D$194,2,Inventory!$G$9:$G$194,C168) -> 10484.586 | F168: =E168/$E$174 -> 0.0011266782
B169: Purchased Material | C169: =VLOOKUP(B169,Settings!$B$163:D349,3,FALSE) -> R | D169: Cat4 | E169: =SUMIFS(Inventory!$O$9:$O$194,Inventory!$D$9:$D$194,2,Inventory!$G$9:$G$194,C169) -> 5466193.6 | F169: =E169/$E$174 -> 0.58739957 | G169: =SUM(E169:E173) -> 5488521.7 | H169: =G169/G174 -> 0.58979896
B170: Ancillary Input | C170: =VLOOKUP(B170,Settings!$B$163:D350,3,FALSE) -> L | E170: =SUMIFS(Inventory!$O$9:$O$194,Inventory!$D$9:$D$194,2,Inventory!$G$9:$G$194,C170) -> 769.6061 | F170: =E170/$E$174 -> 8.2702211e-05
B171: Purchased Services | C171: =VLOOKUP(B171,Settings!$B$163:D351,3,FALSE) -> X | E171: =SUMIFS(Inventory!$O$9:$O$194,Inventory!$D$9:$D$194,2,Inventory!$G$9:$G$194,C171) -> 3881.4482 | F171: =E171/$E$174 -> 0.00041710213
B172: Waste Offsite | C172: =VLOOKUP(B172,Settings!$B$163:D352,3,FALSE) -> Z | E172: =SUMIFS(Inventory!$O$9:$O$194,Inventory!$D$9:$D$194,2,Inventory!$G$9:$G$194,C172) -> 3747.1916 | F172: =E172/$E$174 -> 0.00040267486
B173: Energy related | C173: =VLOOKUP(B173,Settings!$B$163:D351,3,FALSE) -> N | E173: =SUMIFS(Inventory!$O$9:$O$194,Inventory!$D$9:$D$194,2,Inventory!$G$9:$G$194,C173) -> 13929.92 | F173: =E173/$E$174 -> 0.0014969154
B174: Sum | E174: =_xlfn.AGGREGATE(9,6,E158:E173) -> 9305750 | F174: =SUM(F158:F173) -> 1 | G174: =SUM(G158:G173) -> 9305750 | H174: =SUM(H158:H173) -> 1
...

Sheet Life Cycle
Y8: Electrode | Z8: Upstream Tran. | AA8: Electrode | AB8: Production | AC8: Raw material | AD8: Extraction
Y10: Briquett | Z10: Upstream Tran. | AA10: Briquett | AB10: Production | AC10: Raw material | AD10: Extraction
B12: Legend | D12: Outside of the boundary | Y12: Sponge iron | Z12: Upstream Tran. | AA12: Sponge iron | AB12: Production | AC12: Iron ore | AD12: Extraction
D14: Inside the boundary | Y14: Electrode | Z14: Upstream Tran. | AA14: Electrode | AB14: Production | AC14: Raw material | AD14: Extraction
Y16: Lime | Z16: Upstream Tran. | AA16: Lime | AB16: Production | AC16: Lime stone | AD16: Extraction
Y18: Coke | Z18: Upstream Tran. | AA18: Coke | AB18: Production | AC18: Raw material | AD18: Extraction
Y20: Graphite | Z20: Upstream Tran. | AA20: Graphite | AB20: Production | AC20: Raw material | AD20: Extraction
Y22: Scrap | Z22: Upstream Tran. | AA22: Scrap | AB22: Gathering
Y24: Gasoil | Z24: Upstream Tran. | AA24: Gasoil | AB24: Production | AC24: Oil | AD24: Extraction
Y26: Natural gas | Z26: Upstream Tran. | AA26: Natural gas | AB26: Production | AC26: Natural gas | AD26: Extraction
B29: Sale | J29: Molten slab 1 | K29: Ladle Furnaces | Y29: Dolomite | Z29: Upstream Tran. | AA29: Dolomite | AB29: Production | AC29: Dolomite stone | AD29: Extraction
B31: Store | D31: Slab | E31: Slab Cooling | G31: Slab (Unfinished) | H31: Casting | M31: Molten steel | N31: EAFs | P31: Dolomite | Q31: Dolomite Making | Y31: Dolomite stone | Z31: Upstream Tran. | AC31: Dolomite stone | AD31: Extraction
J33: Molten slab 2 | K33: De-gassing | T33: Lime | U33: Lime Making | Y33: Lime stone | Z33: Upstream Tran. | AC33: Lime stone | AD33: Extraction
Y35: Binder | Z35: Upstream Tran. | AA35: Binder | AB35: Production | AC35: Raw material | AD35: Extraction
P37: Briquett | Q37: Briquetting | R37: Hydrated lime | S37: Lime Dehydration | T37: Lime powder
L38: Sale | M38: Slag
R39: Powder
H42: Sale
P44: Sponge iron | Q44: DRI | Y44: Natural gas | Z44: Upstream Tran. | AA44: Natural gas | AB44: Production | AC44: Natural gas | AD44: Extraction
I45: Hot Coil (Temper) | K45: Sale
E48: Hot Rolling Mill | F48: Hot Rolled Coil | H48: Light Shearing 1 | I48: Hot Sheet (Light 1) | K48: Sale | Y48: Bentonite | Z48: Upstream Tran. | AA48: Bentonite | AB48: Production | AC48: Raw material | AD48: Extraction
R49: Pellet | S49: Pelletizing
U50: Concentrate | Y50: Concentrate | Z50: Upstream Tran. | AA50: Concentrate | AB50: Production | AC50: Iron ore | AD50: Extraction
H51: Light Shearing 2 | I51: Hot Sheet (Light 2) | K51: Sale
U53: Pellet | V53: Yard | Y53: Pellet | Z53: Upstream Tran. | AA53: Pellet | AB53: Production | AC53: Iron ore | AD53: Extraction
H54: Heavy Shearing | I54: Hot Sheet (Heavy) | K54: Sale
H57: Skin Pass Mill | I57: Hot Coil (Skin) | K57: Sale
K68: Sale | N68: Sale | Q68: Sale | S68: Sale | U68: Sale
R74: Full Hard Rolled Coil 1 | V74: Pickled Oxide Powder
L76: Color Coated Coil | M76: Coating Line | O76: Galvanized Coil | P76: Galvanizing Line | R76: Full Hard Coil 1 | S76: Tandem Mill | V76: Pickled Coil | W76: Pickling Line 1,2 | Y76: HCl | Z76: Upstream Tran. | AA76: HCl | AB76: Production | AC76: Raw material | AD76: Extraction
Y78: Zinc | Z78: Upstream Tran. | AA78: Zinc | AB78: Production | AC78: Raw material | AD78: Extraction
Y80: Paint | Z80: Upstream Tran. | AA80: Paint | AB80: Production | AC80: Raw material | AD80: Extraction
B81: Sale | F81: Cold Rolled Coil | G81: Corrective Line 1-4 | O81: Annealed Coil 1 | P81: Box Annealing 1
J82: Cold Rolled Oiled Coil
B85: Sale | F85: Cold Rolled Sheet (Light) | G85: Light Shearing | J85: Cold Non-Oiled Coil | K85: Skin Pass 1,2 | O85: Annealed Coil 2 | P85: Box Annealing 2
B89: Sale | F89: Cold Rolled Sheet (Heavy) | G89: Heavy Shearing | L89: Annealed Coil 3 | M89: Box Annealing 3 | O89: Cleaned Coil | P89: Electrolytic Cleaning
B93: Sale | I93: Black Plate Coil | J93: Temper Mill | L93: Annealed Coil | R93: Full Hard Coil 2 | S93: Two Stand Mill
B97: Sale | R97: Full Hard Rolled Coil 2
B101: Sale | F101: Tin Plated Coil | G101: Tinning Line | I101: Cold Coil Temper Mill
Y104: Tin | Z104: Upstream Tran. | AA104: Tin | AB104: Production | AC104: Raw material | AD104: Extraction
B105: Sale | D105: Tin Plated Sheet | E105: Shearing Line of Tinning 1,2
Y120: Natural gas | Z120: Upstream Tran. | AA120: Natural gas | AB120: Production | AC120: Natural gas | AD120: Extraction
V125: Solar Electricity | W125: Solar Plant
V130: Grid Electrivity | Y130: Electricity | Z130: Grid | AA130: Electricity | AB130: Production | AC130: Oil/gas | AD130: Extraction
K131: All Unit Processes | N131: Mix Electricity | O131: Electricity Distribution
V135: Direct Electricity | Y135: Electricity | Z135: Grid | AA135: Electricity | AB135: Production | AC135: Natural Gas | AD135: Extraction
K138: Cold Rolling Area | N138: HNX | O138: Oxygen & Hydrogen
K140: Steel Making Area | N140: Argon
V141: Electricity 3 | W141: PowerPlant 3 | Y141: Natural gas | Z141: Upstream Tran. | AA141: Natural gas | AB141: Production | AC141: Natural gas | AD141: Extraction
K142: All Unit Processes | N142: Oxygen
K144: All Unit Processes | N144: Nitrogen
V146: Electricity 2 | W146: PowerPlant 2 | Y146: Natural gas | Z146: Upstream Tran. | AA146: Natural gas | AB146: Production | AC146: Natural gas | AD146: Extraction
K151: All Unit Processes | N151: Compressed Air | O151: Compressed Air Production | V151: Electricity 1 | W151: PowerPlant 1
K168: Steel Making | U168: Hot Steam | V168: Steam Production | Y168: Natural gas | Z168: Upstream Tran. | AA168: Natural gas | AB168: Production | AC168: Natural gas | AD168: Extraction
Y171: Gasoil | Z171: Upstream Tran. | AA171: Gasoil | AB171: Production | AC171: Oil | AD171: Extraction
U175: DM Water | V175: DM Water Production
U180: Saturated Steam 3 | V180: Steam Production (Pu:55) | Y180: Natural gas | Z180: Upstream Tran. | AA180: Natural gas | AB180: Production | AC180: Natural gas | AD180: Extraction
K182: Cold Rolling Area | N182: Saturated Steam | O182: Steam Distribution
U185: Saturated Steam 1 | V185: RO 1 | Y185: Natural gas | Z185: Upstream Tran. | AA185: Natural gas | AB185: Production | AC185: Natural gas | AD185: Extraction
U187: Light Water 1
U190: Saturated Steam 2 | V190: RO 2 | Y190: Natural gas | Z190: Upstream Tran. | AA190: Natural gas | AB190: Production | AC190: Natural gas | AD190: Extraction
K192: All Unit Processes | N192: Light Water | O192: Light Water Distribution | U192: Light Water 2
U195: Light Water 3 | V195: RO 3
U202: Industrial Water 1 | V202: Industrial Water Production | Y202: Urban Wastewater | Z202: Upstream Tran. | AA202: Urban Wastewater | AB202: Cities | AC202: Water | AD202: Extraction
S204: Green Area | U204: Urban Wastewater
Y205: River Water | Z205: Upstream Tran. | AC205: Water | AD205: River
K206: All Unit Processes | N206: Industrial Water | O206: Industrial Water Distribution
U209: Industrial Water 2 | V209: Sewage Treatment | Y209: Industrial Wastewater | Z209: Areas
Y212: Sanitary Wastewater | Z212: Areas

Sheet Carbon Footprints
B7: Click to see the results of each product. | I7: Slab | L7: Hot Coil (Skin) | O7: Black Plate Coil | R7: Tin Plated Sheet
I9: Hot Rolled Coil | L9: Pickled Coil | O9: Cold Rolled Coil | R9: Galvanized Coil
I11: Hot Coil (Temper) | L11: Full Hard Rolled Coil | O11: Cold Rolled Sheet | R11: Color Coated Coil
I13: Hot Rolled Sheet | L13: Cold Rolled Oiled Coil | O13: Tin Plated Coil | R13: Comparison
B16: Comparison | D16: مقایسه محصولات
B20: Company | C20: No. | D20: Product | E20: Product | F20: CFP (tCO2e/ton)
B21: MSC | C21: 1 | D21: تختال | E21: Slab | F21: =VLOOKUP(E21,'Units CF'!$C$90:$E$136,3,FALSE) -> 2.3301682
C22: 2 | D22: کلاف گرم | E22: Hot Rolled Coil | F22: =VLOOKUP(E22,'Units CF'!$C$90:$E$136,3,FALSE) -> 2.4846049
C23: 3 | D23: کلاف گرم (تمپر) | E23: Hot Coil (Temper) | F23: =VLOOKUP(E23,'Units CF'!$C$90:$E$136,3,FALSE) -> 2.8950544
C24: 4 | D24: ورق گرم | E24: Hot Rolled Sheet | F24: =VLOOKUP(E24,'Units CF'!$C$90:$E$136,3,FALSE) -> 2.7318012
C25: 5 | D25: کلاف گرم (اسکین) | E25: Hot Coil (Skin) | F25: =VLOOKUP(E25,'Units CF'!$C$90:$E$136,3,FALSE) -> 2.5594019
C26: 6 | D26: کلاف اسیدشویی | E26: Pickled Coil | F26: =VLOOKUP(E26,'Units CF'!$C$90:$E$136,3,FALSE) -> 2.6163427
C27: 7 | D27: کلاف خام | E27: Full Hard Rolled Coil | F27: =VLOOKUP(E27,'Units CF'!$C$90:$E$136,3,FALSE) -> 2.7418557
C28: 8 | D28: کلاف سرد روغنی | E28: Cold Rolled Oiled Coil | F28: =VLOOKUP(E28,'Units CF'!$C$90:$E$136,3,FALSE) -> 2.8652756
C29: 9 | D29: کلاف سیاه | E29: Black Plate Coil | F29: =VLOOKUP(E29,'Units CF'!$C$90:$E$136,3,FALSE) -> 3.2725871
C30: 10 | D30: کلاف سرد | E30: Cold Rolled Coil | F30: =VLOOKUP(E30,'Units CF'!$C$90:$E$136,3,FALSE) -> 2.9579956
C31: 11 | D31: ورق سرد | E31: Cold Rolled Sheet | F31: =VLOOKUP(E31,'Units CF'!$C$90:$E$136,3,FALSE) -> 2.970992
C32: 12 | D32: کلاف قلع اندود | E32: Tin Plated Coil | F32: =VLOOKUP(E32,'Units CF'!$C$90:$E$136,3,FALSE) -> 3.5098788
C33: 13 | D33: ورق قلع اندود | E33: Tin Plated Sheet | F33: =VLOOKUP(E33,'Units CF'!$C$90:$E$136,3,FALSE) -> 3.5975776
... C35: 15 | D35: کلاف رنگی | E35: Color Coated Coil | F35: =VLOOKUP(E35,'Units CF'!$C$90:$E$136,3,FALSE) -> 3.1282025
B38: توجه 1: ردپای کربن ورق گرم، متوسط وزنی ردپای کربن ورق‏های گرم خروجی از خطوط برش سبک 1 و 2 و سنگین است.
B39: توجه 2: ردپای کربن کلاف خام، متوسط وزنی ردپای کربن کلاف‏های خام خروجی از خطوط تاندم میل و نورد دو قفسه‏ای است.
B40: توجه 3: ردپای کربن ورق سرد، متوسط وزنی ردپای کربن ورق‏های سرد خروجی از خطوط برش سبک و سنگین است.
B44: Slab | D44: تختال
B48: Product | C48: Production | D48: Unit Process | E48: Unit Process | F48: Upstream Emission | G48: Direct Emission | H48: Utility Emission | I48: Total Emission | J48: Upstream CF | K48: Direct CF | L48: Utility CF | M48: Total CFP | N48: Share
C49: (ton) | F49: tCO2e | G49: tCO2e | H49: tCO2e | I49: tCO2e | J49: tCO2e/ton | K49: tCO2e/ton | L49: tCO2e/ton | M49: tCO2e/ton | N49: %
B50: Slab | C50: =SUM('Units CF'!F32:F34) -> 7299999.9 | D50: انباشت و برداشت | E50: Yard | F50: =SUM('Units CF'!O13:U14)*(1-'Units CF'!I28) -> 310622.44 | G50: =SUM('Units CF'!V13:AA14)*(1-'Units CF'!I28) -> 6405.1041 | H50: =SUM('Units CF'!AB13:AH14)*(1-'Units CF'!I28) -> 44047.5 | I50: =SUM(F50:H50) -> 361075.04 | J50: =F50/$C$50 -> 0.04255102 | K50: =G50/$C$50 -> 0.00087741153 | L50: =H50/$C$50 -> 0.0060339042 | M50: =SUM(J50:L50) -> 0.049462335 | N50: =M50/$M$62 -> 0.021226938
D51: آهک‏سازی | E51: Lime Plant | F51: =SUM('Units CF'!O15:U16)*('Units CF'!I15+'Units CF'!I16*('Units CF'!I17))*(1-'Units CF'!I28) -> 270063.69 | G51: =SUM('Units CF'!V15:AA16)*('Units CF'!I15+'Units CF'!I16*('Units CF'!I17))*(1-'Units CF'!I28) -> 216678 | H51: =SUM('Units CF'!AB15:AH16)*('Units CF'!I15+'Units CF'!I16*('Units CF'!I17))*(1-'Units CF'!I28) -> 12138.086 | I51: =SUM(F51:H51) -> 498879.78 | J51: =F51/$C$50 -> 0.036995027 | K51: =G51/$C$50 -> 0.029681918 | L51: =H51/$C$50 -> 0.0016627516 | M51: =SUM(J51:L51) -> 0.068339697 | N51: =M51/$M$62 -> 0.029328225
D52: تولید آهک هیدراته | E52: Lime Dehydration | F52: =SUM('Units CF'!O17:U20)*('Units CF'!I17)*(1-'Units CF'!I28) -> 1.363213 | G52: =SUM('Units CF'!V17:AA20)*('Units CF'!I17)*(1-'Units CF'!I28) -> 90.924524 | H52: =SUM('Units CF'!AB17:AH20)*('Units CF'!I17)*(1-'Units CF'!I28) -> 852.19467 | I52: =SUM(F52:H52) -> 944.48241 | J52: =F52/$C$50 -> 1.8674151e-07 | K52: =G52/$C$50 -> 1.2455414e-05 | L52: =H52/$C$50 -> 0.000116739 | M52: =SUM(J52:L52) -> 0.00012938115 | N52: =M52/$M$62 -> 5.5524385e-05
D53: دولومیت‏سازی | E53: Dolomite Plant | F53: =SUM('Units CF'!O21:U21)*(1-'Units CF'!I28) -> 12240.6 | G53: =SUM('Units CF'!V21:AA21)*(1-'Units CF'!I28) -> 118434.93 | H53: =SUM('Units CF'!AB21:AH21)*(1-'Units CF'!I28) -> 6272.2993 | I53: =SUM(F53:H53) -> 136947.83 | J53: =F53/$C$50 -> 0.0016767945 | K53: =G53/$C$50 -> 0.016223963 | L53: =H53/$C$50 -> 0.0008592191 | M53: =SUM(J53:L53) -> 0.018759976 | N53: =M53/$M$62 -> 0.008050911
D54: گندله‏سازی | E54: Pelletizing | F54: =SUM('Units CF'!O22:U22)*(1-'Units CF'!I28) -> 375799.34 | G54: =SUM('Units CF'!V22:AA22)*(1-'Units CF'!I28) -> 91439.218 | H54: =SUM('Units CF'!AB22:AH22)*(1-'Units CF'!I28) -> 136627.88 | I54: =SUM(F54:H54) -> 603866.44 | J54: =F54/$C$50 -> 0.051479363 | K54: =G54/$C$50 -> 0.01252592 | L54: =H54/$C$50 -> 0.018716148 | M54: =SUM(J54:L54) -> 0.082721431 | N54: =M54/$M$62 -> 0.035500198
D55: احیای مستقیم | E55: Direct Reduction | F55: =SUM('Units CF'!O23:U24)*(1-'Units CF'!I28) -> 766883.58 | G55: =SUM('Units CF'!V23:AA24)*(1-'Units CF'!I28) -> 3441657.1 | H55: =SUM('Units CF'!AB23:AH24)*(1-'Units CF'!I28) -> 651988.71 | I55: =SUM(F55:H55) -> 4860529.4 | J55: =F55/$C$50 -> 0.10505255 | K55: =G55/$C$50 -> 0.47145989 | L55: =H55/$C$50 -> 0.089313523 | M55: =SUM(J55:L55) -> 0.66582595 | N55: =M55/$M$62 -> 0.28574159
D56: بریکت‏سازی | E56: Briquetting | F56: =SUM('Units CF'!O25:U25)*(1-'Units CF'!I28) -> 628859.53 | G56: =SUM('Units CF'!V25:AA25)*(1-'Units CF'!I28) -> 28.920231 | H56: =SUM('Units CF'!AB25:AH25)*(1-'Units CF'!I28) -> 7399.2998 | I56: =SUM(F56:H56) -> 636287.75 | J56: =F56/$C$50 -> 0.086145143 | K56: =G56/$C$50 -> 3.9616755e-06 | L56: =H56/$C$50 -> 0.0010136027 | M56: =SUM(J56:L56) -> 0.087162708 | N56: =M56/$M$62 -> 0.037406188
D57: کوره‏های قوس | E57: EAF | F57: =SUM('Units CF'!O26:U28)*(1-'Units CF'!I28) -> 5206838.4 | G57: =SUM('Units CF'!V26:AA28)*(1-'Units CF'!I28) -> 440642.71 | H57: =SUM('Units CF'!AB26:AH28)*(1-'Units CF'!I28) -> 3717721.1 | I57: =SUM(F57:H57) -> 9365202.3 | J57: =F57/$C$50 -> 0.71326555 | K57: =G57/$C$50 -> 0.060362017 | L57: =H57/$C$50 -> 0.50927688 | M57: =SUM(J57:L57) -> 1.2829044 | N57: =M57/$M$62 -> 0.55056303
D58: گاززدایی | E58: Degassing | F58: =SUM('Units CF'!O29:U29) -> 11812.106 | G58: =SUM('Units CF'!V29:AA29) -> 2453.3686 | H58: =SUM('Units CF'!AB29:AH29) -> 24466.651 | I58: =SUM(F58:H58) -> 38732.126 | J58: =F58/$C$50 -> 0.0016180968 | K58: =G58/$C$50 -> 0.0003360779 | L58: =H58/$C$50 -> 0.0033515961 | M58: =SUM(J58:L58) -> 0.0053057708 | N58: =M58/$M$62 -> 0.0022769905
D59: کوره‏های پاتیلی | E59: Ladle Furnaces | F59: =SUM('Units CF'!O30:U30) -> 186580.02 | G59: =SUM('Units CF'!V30:AA30) -> 13086.121 | H59: =SUM('Units CF'!AB30:AH30) -> 154343.2 | I59: =SUM(F59:H59) -> 354009.34 | J59: =F59/$C$50 -> 0.025558907 | K59: =G59/$C$50 -> 0.0017926194 | L59: =H59/$C$50 -> 0.021142904 | M59: =SUM(J59:L59) -> 0.048494431 | N59: =M59/$M$62 -> 0.020811558
D60: ریخته‏گری مداوم | E60: Continuous Casting | F60: =SUM('Units CF'!O31:U31) -> 6449.8678 | G60: =SUM('Units CF'!V31:AA31) -> 16327.933 | H60: =SUM('Units CF'!AB31:AH31) -> 90348.613 | I60: =SUM(F60:H60) -> 113126.41 | J60: =F60/$C$50 -> 0.00088354355 | K60: =G60/$C$50 -> 0.0022367032 | L60: =H60/$C$50 -> 0.012376523 | M60: =SUM(J60:L60) -> 0.015496769 | N60: =M60/$M$62 -> 0.0066504939
D61: آماده‏سازی و خنک‏کننده شمش | E61: Slab Conditioning | F61: =SUM('Units CF'!O32:U34) -> 2058.4996 | G61: =SUM('Units CF'!V32:AA34) -> 2936.0987 | H61: =SUM('Units CF'!AB32:AH34) -> 35631.892 | I61: =SUM(F61:H61) -> 40626.49 | J61: =F61/$C$50 -> 0.00028198625 | K61: =G61/$C$50 -> 0.00040220532 | L61: =H61/$C$50 -> 0.0048810811 | M61: =SUM(J61:L61) -> 0.0055652727 | N61: =M61/$M$62 -> 0.0023883567
E62: Sum | F62: =SUM(F50:F61) -> 7778209.5 | G62: =SUM(G50:G61) -> 4350180.4 | H62: =SUM(H50:H61) -> 4881837.4 | I62: =SUM(I50:I61) -> 17010227 | J62: =SUM(J50:J61) -> 1.0655082 | K62: =SUM(K50:K61) -> 0.59591514 | L62: =SUM(L50:L61) -> 0.66874487 | M62: =SUM(M50:M61) -> 2.3301682 | N62: =SUM(N50:N61) -> 1
E63: % | J63: =J62/M62 -> 0.45726664 | K63: =K62/M62 -> 0.25573911 | L63: =L62/M62 -> 0.28699425
B98: Hot Rolled Coil | D98: کلاف گرم
B101: Product | C101: Production | D101: Unit Process | E101: Unit Process | F101: Upstream Emission | G101: Direct Emission | H101: Utility Emission | I101: Total Emission | J101: Upstream CF | K101: Direct CF | L101: Utility CF | M101: Total CFP | N101: Share
C102: (ton) | F102: tCO2e | G102: tCO2e | H102: tCO2e | I102: tCO2e | J102: tCO2e/ton | K102: tCO2e/ton | L102: tCO2e/ton | M102: tCO2e/ton | N102: %
B103: Hot Rolled Coil | C103: ='Units CF'!F40 -> 2750925.5 | D103: انباشت و برداشت | E103: Yard | F103: =F50*'Units CF'!$I$32*'Units CF'!$I$40 -> 120318.9 | G103: =G50*'Units CF'!$I$32*'Units CF'!$I$40 -> 2481.0026 | H103: =H50*'Units CF'!$I$32*'Units CF'!$I$40 -> 17061.699 | I103: =SUM(F103:H103) -> 139861.6 | J103: =F103/$C$103 -> 0.043737608 | K103: =G103/$C$103 -> 0.00090187925 | L103: =H103/$C$103 -> 0.0062021671 | M103: =SUM(J103:L103) -> 0.050841655 | N103: =M103/$M$116 -> 0.020462671
D104: آهک‏سازی | E104: Lime Plant | F104: =F51*'Units CF'!$I$32*'Units CF'!$I$40 -> 104608.56 | G104: =G51*'Units CF'!$I$32*'Units CF'!$I$40 -> 83929.734 | H104: =H51*'Units CF'!$I$32*'Units CF'!$I$40 -> 4701.6603 | I104: =SUM(F104:H104) -> 193239.96 | J104: =F104/$C$103 -> 0.038026679 | K104: =G104/$C$103 -> 0.030509636 | L104: =H104/$C$103 -> 0.0017091195 | M104: =SUM(J104:L104) -> 0.070245435 | N104: =M104/$M$116 -> 0.028272275
D105: تولید آهک هیدراته | E105: Lime Dehydration | F105: =F52*'Units CF'!$I$32*'Units CF'!$I$40 -> 0.52803748 | G105: =G52*'Units CF'!$I$32*'Units CF'!$I$40 -> 35.219409 | H105: =H52*'Units CF'!$I$32*'Units CF'!$I$40 -> 330.09568 | I105: =SUM(F105:H105) -> 365.84313 | J105: =F105/$C$103 -> 1.9194903e-07 | K105: =G105/$C$103 -> 1.2802749e-05 | L105: =H105/$C$103 -> 0.00011999441 | M105: =SUM(J105:L105) -> 0.00013298911 | N105: =M105/$M$116 -> 5.3525254e-05
D106: دولومیت‏سازی | E106: Dolomite Plant | F106: =F53*'Units CF'!$I$32*'Units CF'!$I$40 -> 4741.3686 | G106: =G53*'Units CF'!$I$32*'Units CF'!$I$40 -> 45875.502 | H106: =H53*'Units CF'!$I$32*'Units CF'!$I$40 -> 2429.561 | I106: =SUM(F106:H106) -> 53046.431 | J106: =F106/$C$103 -> 0.001723554 | K106: =G106/$C$103 -> 0.016676388 | L106: =H106/$C$103 -> 0.00088317949 | M106: =SUM(J106:L106) -> 0.019283122 | N106: =M106/$M$116 -> 0.0077610414
D107: گندله‏سازی | E107: Pelletizing | F107: =F54*'Units CF'!$I$32*'Units CF'!$I$40 -> 145565.03 | G107: =G54*'Units CF'!$I$32*'Units CF'!$I$40 -> 35418.774 | H107: =H54*'Units CF'!$I$32*'Units CF'!$I$40 -> 52922.5 | I107: =SUM(F107:H107) -> 233906.3 | J107: =F107/$C$103 -> 0.052914929 | K107: =G107/$C$103 -> 0.012875221 | L107: =H107/$C$103 -> 0.019238071 | M107: =SUM(J107:L107) -> 0.085028222 | N107: =M107/$M$116 -> 0.034222029
D108: احیای مستقیم | E108: Direct Reduction | F108: =F55*'Units CF'!$I$32*'Units CF'!$I$40 -> 297050.62 | G108: =G55*'Units CF'!$I$32*'Units CF'!$I$40 -> 1333118.1 | H108: =H55*'Units CF'!$I$32*'Units CF'!$I$40 -> 252546.35 | I108: =SUM(F108:H108) -> 1882715.1 | J108: =F108/$C$103 -> 0.10798207 | K108: =G108/$C$103 -> 0.48460713 | L108: =H108/$C$103 -> 0.091804142 | M108: =SUM(J108:L108) -> 0.68439334 | N108: =M108/$M$116 -> 0.27545359
D109: بریکت‏سازی | E109: Briquetting | F109: =F56*'Units CF'!$I$32*'Units CF'!$I$40 -> 243587.32 | G109: =G56*'Units CF'!$I$32*'Units CF'!$I$40 -> 11.202186 | H109: =H56*'Units CF'!$I$32*'Units CF'!$I$40 -> 2866.1021 | I109: =SUM(F109:H109) -> 246464.62 | J109: =F109/$C$103 -> 0.088547408 | K109: =G109/$C$103 -> 4.0721518e-06 | L109: =H109/$C$103 -> 0.0010418683 | M109: =SUM(J109:L109) -> 0.089593349 | N109: =M109/$M$116 -> 0.036059394
D110: کوره‏های قوس | E110: EAF | F110: =F57*'Units CF'!$I$32*'Units CF'!$I$40 -> 2016857.1 | G110: =G57*'Units CF'!$I$32*'Units CF'!$I$40 -> 170681.96 | H110: =H57*'Units CF'!$I$32*'Units CF'!$I$40 -> 1440050.9 | I110: =SUM(F110:H110) -> 3627589.9 | J110: =F110/$C$103 -> 0.73315586 | K110: =G110/$C$103 -> 0.062045287 | L110: =H110/$C$103 -> 0.5234787 | M110: =SUM(J110:L110) -> 1.3186798 | N110: =M110/$M$116 -> 0.53074025
D111: گاززدایی | E111: Degassing | F111: =F58*'Units CF'!$I$32*'Units CF'!$I$40 -> 4575.3926 | G111: =G58*'Units CF'!$I$32*'Units CF'!$I$40 -> 950.3068 | H111: =H58*'Units CF'!$I$32*'Units CF'!$I$40 -> 9477.102 | I111: =SUM(F111:H111) -> 15002.801 | J111: =F111/$C$103 -> 0.0016632194 | K111: =G111/$C$103 -> 0.00034544985 | L111: =H111/$C$103 -> 0.0034450596 | M111: =SUM(J111:L111) -> 0.0054537288 | N111: =M111/$M$116 -> 0.0021950084
D112: کوره‏های پاتیلی | E112: Ladle Furnaces | F112: =F59*'Units CF'!$I$32*'Units CF'!$I$40 -> 72271.349 | G112: =G59*'Units CF'!$I$32*'Units CF'!$I$40 -> 5068.8794 | H112: =H59*'Units CF'!$I$32*'Units CF'!$I$40 -> 59784.49 | I112: =SUM(F112:H112) -> 137124.72 | J112: =F112/$C$103 -> 0.026271649 | K112: =G112/$C$103 -> 0.0018426088 | L112: =H112/$C$103 -> 0.021732501 | M112: =SUM(J112:L112) -> 0.049846759 | N112: =M112/$M$116 -> 0.020062247
D113: ریخته‏گری مداوم | E113: Continuous Casting | F113: =F60*'Units CF'!$I$32*'Units CF'!$I$40 -> 2498.3417 | G113: =G60*'Units CF'!$I$32*'Units CF'!$I$40 -> 6324.5881 | H113: =H60*'Units CF'!$I$32*'Units CF'!$I$40 -> 34996.331 | I113: =SUM(F113:H113) -> 43819.261 | J113: =F113/$C$103 -> 0.00090818227 | K113: =G113/$C$103 -> 0.0022990765 | L113: =H113/$C$103 -> 0.012721657 | M113: =SUM(J113:L113) -> 0.015928916 | N113: =M113/$M$116 -> 0.0064110458
D114: آماده‏سازی و خنک‏کننده شمش | E114: Slab Conditioning | F114: =F61*'Units CF'!$I$32*'Units CF'!$I$40 -> 797.35516 | G114: =G61*'Units CF'!$I$32*'Units CF'!$I$40 -> 1137.2912 | H114: =H61*'Units CF'!$I$32*'Units CF'!$I$40 -> 13801.933 | I114: =SUM(F114:H114) -> 15736.579 | J114: =F114/$C$103 -> 0.00028984979 | K114: =G114/$C$103 -> 0.00041342131 | L114: =H114/$C$103 -> 0.0050171962 | M114: =SUM(J114:L114) -> 0.0057204673 | N114: =M114/$M$116 -> 0.0023023649
D115: خط نورد گرم | E115: Hot Rolling Mill | F115: ='Units CF'!L35*'Units CF'!I40 -> 31447.693 | G115: ='Units CF'!M35*'Units CF'!I40 -> 89091.072 | H115: ='Units CF'!N35*'Units CF'!I40 -> 125551.1 | I115: =SUM(F115:H115) -> 246089.86 | J115: =F115/$C$103 -> 0.011431678 | K115: =G115/$C$103 -> 0.032385854 | L115: =H115/$C$103 -> 0.045639585 | M115: =SUM(J115:L115) -> 0.089457118 | N115: =M115/$M$116 -> 0.036004564
E116: Sum | F116: =SUM(F103:F115) -> 3044319.6 | G116: =SUM(G103:G115) -> 1774123.6 | H116: =SUM(H103:H115) -> 2016519.8 | I116: =SUM(I103:I115) -> 6834963 | J116: =SUM(J103:J115) -> 1.1066529 | K116: =SUM(K103:K115) -> 0.64491883 | L116: =SUM(L103:L115) -> 0.73303324 | M116: =SUM(M103:M115) -> 2.4846049 | N116: =SUM(N103:N115) -> 1
E117: % | J117: =J116/M116 -> 0.44540396 | K117: =K116/M116 -> 0.25956595 | L117: =L116/M116 -> 0.2950301
B152: Hot Coil (Temper) | D152: کلاف گرم (تمپر)
B155: Product | C155: Production | D155: Unit Process | E155: Unit Process | F155: Upstream Emission | G155: Direct Emission | H155: Utility Emission | I155: Total Emission | J155: Upstream CF | K155: Direct CF | L155: Utility CF | M155: Total CFP | N155: Share
C156: (ton) | F156: tCO2e | G156: tCO2e | H156: tCO2e | I156: tCO2e | J156: tCO2e/ton | K156: tCO2e/ton | L156: tCO2e/ton | M156: tCO2e/ton | N156: %
B157: Hot Coil (Temper) | C157: ='Units CF'!F42 -> 13211 | D157: انباشت و برداشت | E157: Yard | F157: =F50*'Units CF'!$I$32*'Units CF'!$I$35*'Units CF'!$I$42 -> 636.19587 | G157: =G50*'Units CF'!$I$32*'Units CF'!$I$35*'Units CF'!$I$42 -> 13.118501 | H157: =H50*'Units CF'!$I$32*'Units CF'!$I$35*'Units CF'!$I$42 -> 90.21511 | I157: =SUM(F157:H157) -> 739.52948 | J157: =F157/$C$157 -> 0.048156527 | K157: =G157/$C$157 -> 0.00099299834 | L157: =H157/$C$157 -> 0.0068287874 | M157: =SUM(J157:L157) -> 0.055978312 | N157: =M157/$M$171 -> 0.019335841
D158: آهک‏سازی | E158: Lime Plant | F158: =F51*'Units CF'!$I$32*'Units CF'!$I$35*'Units CF'!$I$42 -> 553.12619 | G158: =G51*'Units CF'!$I$32*'Units CF'!$I$35*'Units CF'!$I$42 -> 443.78523 | H158: =H51*'Units CF'!$I$32*'Units CF'!$I$35*'Units CF'!$I$42 -> 24.860408 | I158: =SUM(F158:H158) -> 1021.7718 | J158: =F158/$C$157 -> 0.041868609 | K158: =G158/$C$157 -> 0.0335921 | L158: =H158/$C$157 -> 0.0018817961 | M158: =SUM(J158:L158) -> 0.077342504 | N158: =M158/$M$171 -> 0.026715389
D159: تولید آهک هیدراته | E159: Lime Dehydration | F159: =F52*'Units CF'!$I$32*'Units CF'!$I$35*'Units CF'!$I$42 -> 0.0027920407 | G159: =G52*'Units CF'!$I$32*'Units CF'!$I$35*'Units CF'!$I$42 -> 0.18622546 | H159: =H52*'Units CF'!$I$32*'Units CF'!$I$35*'Units CF'!$I$42 -> 1.7454075 | I159: =SUM(F159:H159) -> 1.934425 | J159: =F159/$C$157 -> 2.1134211e-07 | K159: =G159/$C$157 -> 1.4096243e-05 | L159: =H159/$C$157 -> 0.00013211774 | M159: =SUM(J159:L159) -> 0.00014642533 | N159: =M159/$M$171 -> 5.0577747e-05
D160: دولومیت‏سازی | E160: Dolomite Plant | F160: =F53*'Units CF'!$I$32*'Units CF'!$I$35*'Units CF'!$I$42 -> 25.070368 | G160: =G53*'Units CF'!$I$32*'Units CF'!$I$35*'Units CF'!$I$42 -> 242.57041 | H160: =H53*'Units CF'!$I$32*'Units CF'!$I$35*'Units CF'!$I$42 -> 12.846499 | I160: =SUM(F160:H160) -> 280.48728 | J160: =F160/$C$157 -> 0.0018976889 | K160: =G160/$C$157 -> 0.018361245 | L160: =H160/$C$157 -> 0.0009724093 | M160: =SUM(J160:L160) -> 0.021231343 | N160: =M160/$M$171 -> 0.0073336596
D161: گندله‏سازی | E161: Pelletizing | F161: =F54*'Units CF'!$I$32*'Units CF'!$I$35*'Units CF'!$I$42 -> 769.6868 | G161: =G54*'Units CF'!$I$32*'Units CF'!$I$35*'Units CF'!$I$42 -> 187.27962 | H161: =H54*'Units CF'!$I$32*'Units CF'!$I$35*'Units CF'!$I$42 -> 279.83198 | I161: =SUM(F161:H161) -> 1236.7984 | J161: =F161/$C$157 -> 0.058261055 | K161: =G161/$C$157 -> 0.014176037 | L161: =H161/$C$157 -> 0.021181741 | M161: =SUM(J161:L161) -> 0.093618833 | N161: =M161/$M$171 -> 0.032337504
D162: احیای مستقیم | E162: Direct Reduction | F162: =F55*'Units CF'!$I$32*'Units CF'!$I$35*'Units CF'!$I$42 -> 1570.6791 | G162: =G55*'Units CF'!$I$32*'Units CF'!$I$35*'Units CF'!$I$42 -> 7048.9693 | H162: =H55*'Units CF'!$I$32*'Units CF'!$I$35*'Units CF'!$I$42 -> 1335.3592 | I162: =SUM(F162:H162) -> 9955.0076 | J162: =F162/$C$157 -> 0.11889176 | K162: =G162/$C$157 -> 0.53356819 | L162: =H162/$C$157 -> 0.10107934 | M162: =SUM(J162:L162) -> 0.75353929 | N162: =M162/$M$171 -> 0.26028502
D163: بریکت‏سازی | E163: Briquetting | F163: =F56*'Units CF'!$I$32*'Units CF'!$I$35*'Units CF'!$I$42 -> 1287.9876 | G163: =G56*'Units CF'!$I$32*'Units CF'!$I$35*'Units CF'!$I$42 -> 0.059232461 | H163: =H56*'Units CF'!$I$32*'Units CF'!$I$35*'Units CF'!$I$42 -> 15.154746 | I163: =SUM(F163:H163) -> 1303.2016 | J163: =F163/$C$157 -> 0.097493571 | K163: =G163/$C$157 -> 4.4835714e-06 | L163: =H163/$C$157 -> 0.0011471308 | M163: =SUM(J163:L163) -> 0.098645186 | N163: =M163/$M$171 -> 0.03407369
D164: کوره‏های قوس | E164: EAF | F164: =F57*'Units CF'!$I$32*'Units CF'!$I$35*'Units CF'!$I$42 -> 10664.294 | G164: =G57*'Units CF'!$I$32*'Units CF'!$I$35*'Units CF'!$I$42 -> 902.49461 | H164: =H57*'Units CF'!$I$32*'Units CF'!$I$35*'Units CF'!$I$42 -> 7614.385 | I164: =SUM(F164:H164) -> 19181.174 | J164: =F164/$C$157 -> 0.8072284 | K164: =G164/$C$157 -> 0.068313875 | L164: =H164/$C$157 -> 0.57636704 | M164: =SUM(J164:L164) -> 1.4519093 | N164: =M164/$M$171 -> 0.50151366
D165: گاززدایی | E165: Degassing | F165: =F58*'Units CF'!$I$32*'Units CF'!$I$35*'Units CF'!$I$42 -> 24.192757 | G165: =G58*'Units CF'!$I$32*'Units CF'!$I$35*'Units CF'!$I$42 -> 5.0248237 | H165: =H58*'Units CF'!$I$32*'Units CF'!$I$35*'Units CF'!$I$42 -> 50.11094 | I165: =SUM(F165:H165) -> 79.328521 | J165: =F165/$C$157 -> 0.0018312586 | K165: =G165/$C$157 -> 0.0003803515 | L165: =H165/$C$157 -> 0.0037931224 | M165: =SUM(J165:L165) -> 0.0060047325 | N165: =M165/$M$171 -> 0.0020741346
D166: کوره‏های پاتیلی | E166: Ladle Furnaces | F166: =F59*'Units CF'!$I$32*'Units CF'!$I$35*'Units CF'!$I$42 -> 382.14058 | G166: =G59*'Units CF'!$I$32*'Units CF'!$I$35*'Units CF'!$I$42 -> 26.802108 | H166: =H59*'Units CF'!$I$32*'Units CF'!$I$35*'Units CF'!$I$42 -> 316.1153 | I166: =SUM(F166:H166) -> 725.05799 | J166: =F166/$C$157 -> 0.028925939 | K166: =G166/$C$157 -> 0.0020287721 | L166: =H166/$C$157 -> 0.023928189 | M166: =SUM(J166:L166) -> 0.0548829 | N166: =M166/$M$171 -> 0.018957468
D167: ریخته‏گری مداوم | E167: Continuous Casting | F167: =F60*'Units CF'!$I$32*'Units CF'!$I$35*'Units CF'!$I$42 -> 13.210183 | G167: =G60*'Units CF'!$I$32*'Units CF'!$I$35*'Units CF'!$I$42 -> 33.441769 | H167: =H60*'Units CF'!$I$32*'Units CF'!$I$35*'Units CF'!$I$42 -> 185.04592 | I167: =SUM(F167:H167) -> 231.69787 | J167: =F167/$C$157 -> 0.00099993817 | K167: =G167/$C$157 -> 0.0025313579 | L167: =H167/$C$157 -> 0.014006958 | M167: =SUM(J167:L167) -> 0.017538254 | N167: =M167/$M$171 -> 0.006058005
D168: آماده‏سازی و خنک‏کننده شمش | E168: Slab Conditioning | F168: =F61*'Units CF'!$I$32*'Units CF'!$I$35*'Units CF'!$I$42 -> 4.2160796 | G168: =G61*'Units CF'!$I$32*'Units CF'!$I$35*'Units CF'!$I$42 -> 6.0135189 | H168: =H61*'Units CF'!$I$32*'Units CF'!$I$35*'Units CF'!$I$42 -> 72.978831 | I168: =SUM(F168:H168) -> 83.208429 | J168: =F168/$C$157 -> 0.00031913403 | K168: =G168/$C$157 -> 0.00045519029 | L168: =H168/$C$157 -> 0.0055240959 | M168: =SUM(J168:L168) -> 0.0062984202 | N168: =M168/$M$171 -> 0.0021755792
D169: خط نورد گرم | E169: Hot Rolling Mill | F169: ='Units CF'!L35*'Units CF'!I35*'Units CF'!I42 -> 166.28221 | G169: ='Units CF'!M35*'Units CF'!I35*'Units CF'!I42 -> 471.07622 | H169: ='Units CF'!N35*'Units CF'!I35*'Units CF'!I42 -> 663.86154 | I169: =SUM(F169:H169) -> 1301.22 | J169: =F169/$C$157 -> 0.012586648 | K169: =G169/$C$157 -> 0.035657877 | L169: =H169/$C$157 -> 0.050250665 | M169: =SUM(J169:L169) -> 0.098495191 | N169: =M169/$M$171 -> 0.034021879
D170: خط برش سبک 1 | E170: Shearing Line 1 | F170: ='Units CF'!L41*'Units CF'!I42 -> 128.48976 | G170: ='Units CF'!M41*'Units CF'!I42 -> 361.92465 | H170: ='Units CF'!N41*'Units CF'!I42 -> 1615.7316 | I170: =SUM(F170:H170) -> 2106.146 | J170: =F170/$C$157 -> 0.0097259677 | K170: =G170/$C$157 -> 0.027395704 | L170: =H170/$C$157 -> 0.12230199 | M170: =SUM(J170:L170) -> 0.15942366 | N170: =M170/$M$171 -> 0.055067589
E171: Sum | F171: =SUM(F157:F170) -> 16225.575 | G171: =SUM(G157:G170) -> 9742.7463 | H171: =SUM(H157:H170) -> 12278.242 | I171: =SUM(I157:I170) -> 38246.563 | J171: =SUM(J157:J170) -> 1.2281867 | K171: =SUM(K157:K170) -> 0.73747228 | L171: =SUM(L157:L170) -> 0.92939539 | M171: =SUM(M157:M170) -> 2.8950544 | N171: =SUM(N157:N170) -> 1
E172: % | J172: =J171/M171 -> 0.42423615 | K172: =K171/M171 -> 0.25473521 | L172: =L171/M171 -> 0.32102865
B206: Hot Rolled Sheet | D206: ورق گرم
B209: Product | C209: Production | D209: Unit Process | E209: Unit Process | F209: Upstream Emission | G209: Direct Emission | H209: Utility Emission | I209: Total Emission | J209: Upstream CF | K209: Direct CF | L209: Utility CF | M209: Total CFP | N209: Share
C210: (ton) | F210: tCO2e | G210: tCO2e | H210: tCO2e | I210: tCO2e | J210: tCO2e/ton | K210: tCO2e/ton | L210: tCO2e/ton | M210: tCO2e/ton | N210: %
B211: Hot Sheet (Light 1) | C211: ='Units CF'!F41 -> 108972 | D211: انباشت و برداشت | E211: Yard | F211: =F50*'Units CF'!$I$32*'Units CF'!$I$35*'Units CF'!$I$41 -> 5247.713 | G211: =G50*'Units CF'!$I$32*'Units CF'!$I$35*'Units CF'!$I$41 -> 108.20901 | H211: =H50*'Units CF'!$I$32*'Units CF'!$I$35*'Units CF'!$I$41 -> 744.14662 | I211: =SUM(F211:H211) -> 6100.0686 | J211: =F211/$C$211 -> 0.048156527 | K211: =G211/$C$211 -> 0.00099299834 | L211: =H211/$C$211 -> 0.0068287874 | M211: =SUM(J211:L211) -> 0.055978312 | N211: =M211/$M$225 -> 0.019335841
D212: آهک‏سازی | E212: Lime Plant | F212: =F51*'Units CF'!$I$32*'Units CF'!$I$35*'Units CF'!$I$41 -> 4562.506 | G212: =G51*'Units CF'!$I$32*'Units CF'!$I$35*'Units CF'!$I$41 -> 3660.5983 | H212: =H51*'Units CF'!$I$32*'Units CF'!$I$35*'Units CF'!$I$41 -> 205.06308 | I212: =SUM(F212:H212) -> 8428.1674 | J212: =F212/$C$211 -> 0.041868609 | K212: =G212/$C$211 -> 0.0335921 | L212: =H212/$C$211 -> 0.0018817961 | M212: =SUM(J212:L212) -> 0.077342504 | N212: =M212/$M$225 -> 0.026715389
D213: تولید آهک هیدراته | E213: Lime Dehydration | F213: =F52*'Units CF'!$I$32*'Units CF'!$I$35*'Units CF'!$I$41 -> 0.023030373 | G213: =G52*'Units CF'!$I$32*'Units CF'!$I$35*'Units CF'!$I$41 -> 1.5360957 | H213: =H52*'Units CF'!$I$32*'Units CF'!$I$35*'Units CF'!$I$41 -> 14.397135 | I213: =SUM(F213:H213) -> 15.956261 | J213: =F213/$C$211 -> 2.1134211e-07 | K213: =G213/$C$211 -> 1.4096243e-05 | L213: =H213/$C$211 -> 0.00013211774 | M213: =SUM(J213:L213) -> 0.00014642533 | N213: =M213/$M$225 -> 5.0577747e-05
D214: دولومیت‏سازی | E214: Dolomite Plant | F214: =F53*'Units CF'!$I$32*'Units CF'!$I$35*'Units CF'!$I$41 -> 206.79496 | G214: =G53*'Units CF'!$I$32*'Units CF'!$I$35*'Units CF'!$I$41 -> 2000.8616 | H214: =H53*'Units CF'!$I$32*'Units CF'!$I$35*'Units CF'!$I$41 -> 105.96539 | I214: =SUM(F214:H214) -> 2313.6219 | J214: =F214/$C$211 -> 0.0018976889 | K214: =G214/$C$211 -> 0.018361245 | L214: =H214/$C$211 -> 0.0009724093 | M214: =SUM(J214:L214) -> 0.021231343 | N214: =M214/$M$225 -> 0.0073336596
D215: گندله‏سازی | E215: Pelletizing | F215: =F54*'Units CF'!$I$32*'Units CF'!$I$35*'Units CF'!$I$41 -> 6348.8237 | G215: =G54*'Units CF'!$I$32*'Units CF'!$I$35*'Units CF'!$I$41 -> 1544.7911 | H215: =H54*'Units CF'!$I$32*'Units CF'!$I$35*'Units CF'!$I$41 -> 2308.2167 | I215: =SUM(F215:H215) -> 10201.831 | J215: =F215/$C$211 -> 0.058261055 | K215: =G215/$C$211 -> 0.014176037 | L215: =H215/$C$211 -> 0.021181741 | M215: =SUM(J215:L215) -> 0.093618833 | N215: =M215/$M$225 -> 0.032337504
D216: احیای مستقیم | E216: Direct Reduction | F216: =F55*'Units CF'!$I$32*'Units CF'!$I$35*'Units CF'!$I$41 -> 12955.873 | G216: =G55*'Units CF'!$I$32*'Units CF'!$I$35*'Units CF'!$I$41 -> 58143.993 | H216: =H55*'Units CF'!$I$32*'Units CF'!$I$35*'Units CF'!$I$41 -> 11014.818 | I216: =SUM(F216:H216) -> 82114.684 | J216: =F216/$C$211 -> 0.11889176 | K216: =G216/$C$211 -> 0.53356819 | L216: =H216/$C$211 -> 0.10107934 | M216: =SUM(J216:L216) -> 0.75353929 | N216: =M216/$M$225 -> 0.26028502
D217: بریکت‏سازی | E217: Briquetting | F217: =F56*'Units CF'!$I$32*'Units CF'!$I$35*'Units CF'!$I$41 -> 10624.069 | G217: =G56*'Units CF'!$I$32*'Units CF'!$I$35*'Units CF'!$I$41 -> 0.48858374 | H217: =H56*'Units CF'!$I$32*'Units CF'!$I$35*'Units CF'!$I$41 -> 125.00514 | I217: =SUM(F217:H217) -> 10749.563 | J217: =F217/$C$211 -> 0.097493571 | K217: =G217/$C$211 -> 4.4835714e-06 | L217: =H217/$C$211 -> 0.0011471308 | M217: =SUM(J217:L217) -> 0.098645186 | N217: =M217/$M$225 -> 0.03407369
D218: کوره‏های قوس | E218: EAF | F218: =F57*'Units CF'!$I$32*'Units CF'!$I$35*'Units CF'!$I$41 -> 87965.293 | G218: =G57*'Units CF'!$I$32*'Units CF'!$I$35*'Units CF'!$I$41 -> 7444.2996 | H218: =H57*'Units CF'!$I$32*'Units CF'!$I$35*'Units CF'!$I$41 -> 62807.869 | I218: =SUM(F218:H218) -> 158217.46 | J218: =F218/$C$211 -> 0.8072284 | K218: =G218/$C$211 -> 0.068313875 | L218: =H218/$C$211 -> 0.57636704 | M218: =SUM(J218:L218) -> 1.4519093 | N218: =M218/$M$225 -> 0.50151366
D219: گاززدایی | E219: Degassing | F219: =F58*'Units CF'!$I$32*'Units CF'!$I$35*'Units CF'!$I$41 -> 199.55591 | G219: =G58*'Units CF'!$I$32*'Units CF'!$I$35*'Units CF'!$I$41 -> 41.447664 | H219: =H58*'Units CF'!$I$32*'Units CF'!$I$35*'Units CF'!$I$41 -> 413.34414 | I219: =SUM(F219:H219) -> 654.34771 | J219: =F219/$C$211 -> 0.0018312586 | K219: =G219/$C$211 -> 0.0003803515 | L219: =H219/$C$211 -> 0.0037931224 | M219: =SUM(J219:L219) -> 0.0060047325 | N219: =M219/$M$225 -> 0.0020741346
D220: کوره‏های پاتیلی | E220: Ladle Furnaces | F220: =F59*'Units CF'!$I$32*'Units CF'!$I$35*'Units CF'!$I$41 -> 3152.1174 | G220: =G59*'Units CF'!$I$32*'Units CF'!$I$35*'Units CF'!$I$41 -> 221.07935 | H220: =H59*'Units CF'!$I$32*'Units CF'!$I$35*'Units CF'!$I$41 -> 2607.5026 | I220: =SUM(F220:H220) -> 5980.6994 | J220: =F220/$C$211 -> 0.028925939 | K220: =G220/$C$211 -> 0.0020287721 | L220: =H220/$C$211 -> 0.023928189 | M220: =SUM(J220:L220) -> 0.0548829 | N220: =M220/$M$225 -> 0.018957468
D221: ریخته‏گری مداوم | E221: Continuous Casting | F221: =F60*'Units CF'!$I$32*'Units CF'!$I$35*'Units CF'!$I$41 -> 108.96526 | G221: =G60*'Units CF'!$I$32*'Units CF'!$I$35*'Units CF'!$I$41 -> 275.84713 | H221: =H60*'Units CF'!$I$32*'Units CF'!$I$35*'Units CF'!$I$41 -> 1526.3662 | I221: =SUM(F221:H221) -> 1911.1786 | J221: =F221/$C$211 -> 0.00099993817 | K221: =G221/$C$211 -> 0.0025313579 | L221: =H221/$C$211 -> 0.014006958 | M221: =SUM(J221:L221) -> 0.017538254 | N221: =M221/$M$225 -> 0.006058005
D222: آماده‏سازی و خنک‏کننده شمش | E222: Slab Conditioning | F222: =F61*'Units CF'!$I$32*'Units CF'!$I$35*'Units CF'!$I$41 -> 34.776673 | G222: =G61*'Units CF'!$I$32*'Units CF'!$I$35*'Units CF'!$I$41 -> 49.602996 | H222: =H61*'Units CF'!$I$32*'Units CF'!$I$35*'Units CF'!$I$41 -> 601.97178 | I222: =SUM(F222:H222) -> 686.35145 | J222: =F222/$C$211 -> 0.00031913403 | K222: =G222/$C$211 -> 0.00045519029 | L222: =H222/$C$211 -> 0.0055240959 | M222: =SUM(J222:L222) -> 0.0062984202 | N222: =M222/$M$225 -> 0.0021755792
D223: خط نورد گرم | E223: Hot Rolling Mill | F223: ='Units CF'!L35*'Units CF'!I35*'Units CF'!I41 -> 1371.5922 | G223: ='Units CF'!M35*'Units CF'!I35*'Units CF'!I41 -> 3885.7102 | H223: ='Units CF'!N35*'Units CF'!I35*'Units CF'!I41 -> 5475.9155 | I223: =SUM(F223:H223) -> 10733.218 | J223: =F223/$C$211 -> 0.012586648 | K223: =G223/$C$211 -> 0.035657877 | L223: =H223/$C$211 -> 0.050250665 | M223: =SUM(J223:L223) -> 0.098495191 | N223: =M223/$M$225 -> 0.034021879
D224: خط برش سبک شماره 1 | E224: Shearing Line 1 | F224: ='Units CF'!L41*'Units CF'!I41 -> 1059.8581 | G224: ='Units CF'!M41*'Units CF'!I41 -> 2985.3647 | H224: ='Units CF'!N41*'Units CF'!I41 -> 13327.493 | I224: =SUM(F224:H224) -> 17372.716 | J224: =F224/$C$211 -> 0.0097259677 | K224: =G224/$C$211 -> 0.027395704 | L224: =H224/$C$211 -> 0.12230199 | M224: =SUM(J224:L224) -> 0.15942366 | N224: =M224/$M$225 -> 0.055067589
E225: Sum | F225: =SUM(F211:F224) -> 133837.96 | G225: =SUM(G211:G224) -> 80363.829 | H225: =SUM(H211:H224) -> 101278.07 | I225: =SUM(I211:I224) -> 315479.87 | J225: =SUM(J211:J224) -> 1.2281867 | K225: =SUM(K211:K224) -> 0.73747228 | L225: =SUM(L211:L224) -> 0.92939539 | M225: =SUM(M211:M224) -> 2.8950544 | N225: =SUM(N211:N224) -> 1
E226: % | J226: =J225/M225 -> 0.42423615 | K226: =K225/M225 -> 0.25473521 | L226: =L225/M225 -> 0.32102865
B230: Product | C230: Production | D230: Unit Process | E230: Unit Process | F230: Upstream Emission | G230: Direct Emission | H230: Utility Emission | I230: Total Emission | J230: Upstream CF | K230: Direct CF | L230: Utility CF | M230: Total CFP | N230: Share
C231: (ton) | F231: tCO2e | G231: tCO2e | H231: tCO2e | I231: tCO2e | J231: tCO2e/ton | K231: tCO2e/ton | L231: tCO2e/ton | M231: tCO2e/ton | N231: %
B232: Hot Sheet (Light 2) | C232: ='Units CF'!F43 -> 68614 | D232: انباشت و برداشت | E232: Yard | F232: =F50*'Units CF'!$I$32*'Units CF'!$I$36 -> 3077.9726 | G232: =G50*'Units CF'!$I$32*'Units CF'!$I$36 -> 63.468482 | H232: =H50*'Units CF'!$I$32*'Units CF'!$I$36 -> 436.46878 | I232: =SUM(F232:H232) -> 3577.9099 | J232: =F232/$C$232 -> 0.04485925 | K232: =G232/$C$232 -> 0.00092500776 | L232: =H232/$C$232 -> 0.0063612204 | M232: =SUM(J232:L232) -> 0.052145478 | N232: =M232/$M$246 -> 0.019380772
D233: آهک‏سازی | E233: Lime Plant | F233: =F51*'Units CF'!$I$32*'Units CF'!$I$36 -> 2676.074 | G233: =G51*'Units CF'!$I$32*'Units CF'!$I$36 -> 2147.0727 | H233: =H51*'Units CF'!$I$32*'Units CF'!$I$36 -> 120.27688 | I233: =SUM(F233:H233) -> 4943.4236 | J233: =F233/$C$232 -> 0.039001866 | K233: =G233/$C$232 -> 0.031292049 | L233: =H233/$C$232 -> 0.0017529495 | M233: =SUM(J233:L233) -> 0.072046865 | N233: =M233/$M$246 -> 0.026777468
...

Sheet Section 1
B7: Section 1: GHG Emission Inventory of MSC Complex
B8: Sheet Name | C8: Notes
B9: Combustion | C9: Details of Combustion Emission Source Calculations
B10: Vent | C10: Details of Process Emission Source Calculations
B11: Fugitive | C11: Details of Fugitive Emission Calculations
B12: Electricity | C12: Details of Electricity Emission Calculations
B13: On-Site Transportation | C13: Details of On-Site Transportation Emission Calculations
B14: Upstream Transportation | C14: Details of Transportation (Upstream) Emission Calculations
B15: Downstream Transportation | C15: Details of Transportation (Downstream) Emission Calculations
B16: Employee Commuting | C16: Details of Employee Commuting Emission Calculations
B17: Business Travel | C17: Details of Business Travel (Domestic & International) Emission Calculations
B18: Purchased Material | C18: Details of Purchased Material Emission Calculations
B19: Ancillary Input | C19: Details of Ancillary Input Emission Calculations
... B23: Energy Related | C23: Details of Energy-Related Emission Calculations

Sheet Combustion
B7: Combustion
B8: Area | C8: Unit Process | D8: Cost Center Code | E8: Cost Item Code | F8: Annual Consumption | G8: Unit | H8: Fuel Type | I8: LHV | J8: EF | M8: Emission | Q8: Data Source of Annaul Consumption
J9: CO2 | K9: CH4 | L9: N2O | M9: CO2 | N9: CH4 | O9: N2O | P9: Total
I10: (GJ/Unit) | J10: (tCO2/GJ) | K10: (tCH4/GJ) | L10: (tN2O/GJ) | M10: (tCO2/y) | N10: (tCH4/y) | O10: (tN2O/y) | P10: (tCO2e/y)
B11: TAS | C11: All cost centers | E11: 10200 | F11: 0.016 | G11: =VLOOKUP(H11,Settings!$B$30:$F$36,5,0) -> ton | H11: Methane | I11: =VLOOKUP(H11,Settings!$B$30:$C$36,2,FALSE) -> 5 | J11: =VLOOKUP(H11,Settings!$B$46:$E$52,2,FALSE) -> 7 | K11: =VLOOKUP(H11,Settings!$B$46:$E$52,3,FALSE) -> 1e-06 | L11: =VLOOKUP(H11,Settings!$B$46:$E$52,4,FALSE) -> 1e-07 | M11: =F11*I11*J11 -> 0.56 | N11: =F11*I11*K11 -> 8e-08 | O11: =F11*I11*L11 -> 8e-09 | P11: =M11+(N11*Settings!$C$24)+(O11*Settings!$D$24) -> 0.56000434 | Q11: Purchase Order
B12: Iron Making | C12: All cost centers | E12: 10203 | F12: 2.387 | G12: =VLOOKUP(H12,Settings!$B$30:$F$36,5,0) -> ton | H12: Butane | I12: =VLOOKUP(H12,Settings!$B$30:$C$36,2,FALSE) -> 4 | J12: =VLOOKUP(H12,Settings!$B$46:$E$52,2,FALSE) -> 6 | K12: =VLOOKUP(H12,Settings!$B$46:$E$52,3,FALSE) -> 2.8e-06 | L12: =VLOOKUP(H12,Settings!$B$46:$E$52,4,FALSE) -> 5.6e-07 | M12: =F12*I12*J12 -> 57.288 | N12: =F12*I12*K12 -> 2.67344e-05 | O12: =F12*I12*L12 -> 5.34688e-06 | P12: =M12+(N12*Settings!$C$24)+(O12*Settings!$D$24) -> 57.290182 | Q12: Purchase Order
B13: Steel Making | C13: All cost centers | E13: 10203 | F13: 6.023 | G13: =VLOOKUP(H13,Settings!$B$30:$F$36,5,0) -> ton | H13: Butane | I13: =VLOOKUP(H13,Settings!$B$30:$C$36,2,FALSE) -> 4 | J13: =VLOOKUP(H13,Settings!$B$46:$E$52,2,FALSE) -> 6 | K13: =VLOOKUP(H13,Settings!$B$46:$E$52,3,FALSE) -> 2.8e-06 | L13: =VLOOKUP(H13,Settings!$B$46:$E$52,4,FALSE) -> 5.6e-07 | M13: =F13*I13*J13 -> 144.552 | N13: =F13*I13*K13 -> 6.74576e-05 | O13: =F13*I13*L13 -> 1.349152e-05 | P13: =M13+(N13*Settings!$C$24)+(O13*Settings!$D$24) -> 144.5575 | Q13: Purchase Order
B14: Hot Rolling | C14: All cost centers | E14: 10203 | F14: 2.794 | G14: =VLOOKUP(H14,Settings!$B$30:$F$36,5,0) -> ton | H14: Butane | I14: =VLOOKUP(H14,Settings!$B$30:$C$36,2,FALSE) -> 4 | J14: =VLOOKUP(H14,Settings!$B$46:$E$52,2,FALSE) -> 6 | K14: =VLOOKUP(H14,Settings!$B$46:$E$52,3,FALSE) -> 2.8e-06 | L14: =VLOOKUP(H14,Settings!$B$46:$E$52,4,FALSE) -> 5.6e-07 | M14: =F14*I14*J14 -> 67.056 | N14: =F14*I14*K14 -> 3.12928e-05 | O14: =F14*I14*L14 -> 6.25856e-06 | P14: =M14+(N14*Settings!$C$24)+(O14*Settings!$D$24) -> 67.058553 | Q14: Purchase Order
B15: Cold Rolling | C15: All cost centers | E15: 10203 | F15: 14.562 | G15: =VLOOKUP(H15,Settings!$B$30:$F$36,5,0) -> ton | H15: Butane | I15: =VLOOKUP(H15,Settings!$B$30:$C$36,2,FALSE) -> 4 | J15: =VLOOKUP(H15,Settings!$B$46:$E$52,2,FALSE) -> 6 | K15: =VLOOKUP(H15,Settings!$B$46:$E$52,3,FALSE) -> 2.8e-06 | L15: =VLOOKUP(H15,Settings!$B$46:$E$52,4,FALSE) -> 5.6e-07 | M15: =F15*I15*J15 -> 349.488 | N15: =F15*I15*K15 -> 0.0001630944 | O15: =F15*I15*L15 -> 3.261888e-05 | P15: =M15+(N15*Settings!$C$24)+(O15*Settings!$D$24) -> 349.50131 | Q15: Purchase Order
B16: Utility | C16: All cost centers | E16: 10203 | F16: 0.594 | G16: =VLOOKUP(H16,Settings!$B$30:$F$36,5,0) -> ton | H16: Butane | I16: =VLOOKUP(H16,Settings!$B$30:$C$36,2,FALSE) -> 4 | J16: =VLOOKUP(H16,Settings!$B$46:$E$52,2,FALSE) -> 6 | K16: =VLOOKUP(H16,Settings!$B$46:$E$52,3,FALSE) -> 2.8e-06 | L16: =VLOOKUP(H16,Settings!$B$46:$E$52,4,FALSE) -> 5.6e-07 | M16: =F16*I16*J16 -> 14.256 | N16: =F16*I16*K16 -> 6.6528e-06 | O16: =F16*I16*L16 -> 1.33056e-06 | P16: =M16+(N16*Settings!$C$24)+(O16*Settings!$D$24) -> 14.256543 | Q16: Purchase Order
B17: Transportation | C17: All cost centers | E17: 10203 | F17: 0.099 | G17: =VLOOKUP(H17,Settings!$B$30:$F$36,5,0) -> ton | H17: Butane | I17: =VLOOKUP(H17,Settings!$B$30:$C$36,2,FALSE) -> 4 | J17: =VLOOKUP(H17,Settings!$B$46:$E$52,2,FALSE) -> 6 | K17: =VLOOKUP(H17,Settings!$B$46:$E$52,3,FALSE) -> 2.8e-06 | L17: =VLOOKUP(H17,Settings!$B$46:$E$52,4,FALSE) -> 5.6e-07 | M17: =F17*I17*J17 -> 2.376 | N17: =F17*I17*K17 -> 1.1088e-06 | O17: =F17*I17*L17 -> 2.2176e-07 | P17: =M17+(N17*Settings!$C$24)+(O17*Settings!$D$24) -> 2.3760905 | Q17: Purchase Order
B18: Maintenance | C18: All cost centers | E18: 10203 | F18: 0.692 | G18: =VLOOKUP(H18,Settings!$B$30:$F$36,5,0) -> ton | H18: Butane | I18: =VLOOKUP(H18,Settings!$B$30:$C$36,2,FALSE) -> 4 | J18: =VLOOKUP(H18,Settings!$B$46:$E$52,2,FALSE) -> 6 | K18: =VLOOKUP(H18,Settings!$B$46:$E$52,3,FALSE) -> 2.8e-06 | L18: =VLOOKUP(H18,Settings!$B$46:$E$52,4,FALSE) -> 5.6e-07 | M18: =F18*I18*J18 -> 16.608 | N18: =F18*I18*K18 -> 7.7504e-06 | O18: =F18*I18*L18 -> 1.55008e-06 | P18: =M18+(N18*Settings!$C$24)+(O18*Settings!$D$24) -> 16.608632 | Q18: Purchase Order
B19: TAS | C19: All cost centers | E19: 10203 | F19: 4.559 | G19: =VLOOKUP(H19,Settings!$B$30:$F$36,5,0) -> ton | H19: Butane | I19: =VLOOKUP(H19,Settings!$B$30:$C$36,2,FALSE) -> 4 | J19: =VLOOKUP(H19,Settings!$B$46:$E$52,2,FALSE) -> 6 | K19: =VLOOKUP(H19,Settings!$B$46:$E$52,3,FALSE) -> 2.8e-06 | L19: =VLOOKUP(H19,Settings!$B$46:$E$52,4,FALSE) -> 5.6e-07 | M19: =F19*I19*J19 -> 109.416 | N19: =F19*I19*K19 -> 5.10608e-05 | O19: =F19*I19*L19 -> 1.021216e-05 | P19: =M19+(N19*Settings!$C$24)+(O19*Settings!$D$24) -> 109.42017 | Q19: Purchase Order
B20: Iron Making | C20: All cost centers | E20: 10350 | F20: 0 | G20: =VLOOKUP(H20,Settings!$B$30:$F$36,5,0) -> ton | H20: Acetylene | I20: =VLOOKUP(H20,Settings!$B$30:$C$36,2,FALSE) -> 5 | J20: =VLOOKUP(H20,Settings!$B$46:$E$52,2,FALSE) -> 6 | K20: =VLOOKUP(H20,Settings!$B$46:$E$52,3,FALSE) -> 0 | L20: =VLOOKUP(H20,Settings!$B$46:$E$52,4,FALSE) -> 0 | M20: =F20*I20*J20 -> 0 | N20: =F20*I20*K20 -> 0 | O20: =F20*I20*L20 -> 0 | P20: =M20+(N20*Settings!$C$24)+(O20*Settings!$D$24) -> 0 | Q20: Purchase Order
B21: Steel Making | C21: All cost centers | E21: 10350 | F21: 0 | G21: =VLOOKUP(H21,Settings!$B$30:$F$36,5,0) -> ton | H21: Acetylene | I21: =VLOOKUP(H21,Settings!$B$30:$C$36,2,FALSE) -> 5 | J21: =VLOOKUP(H21,Settings!$B$46:$E$52,2,FALSE) -> 6 | K21: =VLOOKUP(H21,Settings!$B$46:$E$52,3,FALSE) -> 0 | L21: =VLOOKUP(H21,Settings!$B$46:$E$52,4,FALSE) -> 0 | M21: =F21*I21*J21 -> 0 | N21: =F21*I21*K21 -> 0 | O21: =F21*I21*L21 -> 0 | P21: =M21+(N21*Settings!$C$24)+(O21*Settings!$D$24) -> 0 | Q21: Purchase Order
B22: Hot Rolling | C22: All cost centers | E22: 10350 | F22: 0 | G22: =VLOOKUP(H22,Settings!$B$30:$F$36,5,0) -> ton | H22: Acetylene | I22: =VLOOKUP(H22,Settings!$B$30:$C$36,2,FALSE) -> 5 | J22: =VLOOKUP(H22,Settings!$B$46:$E$52,2,FALSE) -> 6 | K22: =VLOOKUP(H22,Settings!$B$46:$E$52,3,FALSE) -> 0 | L22: =VLOOKUP(H22,Settings!$B$46:$E$52,4,FALSE) -> 0 | M22: =F22*I22*J22 -> 0 | N22: =F22*I22*K22 -> 0 | O22: =F22*I22*L22 -> 0 | P22: =M22+(N22*Settings!$C$24)+(O22*Settings!$D$24) -> 0 | Q22: Purchase Order
... B27: TAS | C27: All cost centers | E27: 10350 | F27: 0.063 | G27: =VLOOKUP(H27,Settings!$B$30:$F$36,5,0) -> ton | H27: Acetylene | I27: =VLOOKUP(H27,Settings!$B$30:$C$36,2,FALSE) -> 5 | J27: =VLOOKUP(H27,Settings!$B$46:$E$52,2,FALSE) -> 6 | K27: =VLOOKUP(H27,Settings!$B$46:$E$52,3,FALSE) -> 0 | L27: =VLOOKUP(H27,Settings!$B$46:$E$52,4,FALSE) -> 0 | M27: =F27*I27*J27 -> 1.89 | N27: =F27*I27*K27 -> 0 | O27: =F27*I27*L27 -> 0 | P27: =M27+(N27*Settings!$C$24)+(O27*Settings!$D$24) -> 1.89 | Q27: Purchase Order
B28: =VLOOKUP(D28,'Unit List'!$B$9:$E$241,4,0) -> Utility | C28: =VLOOKUP(D28,'Unit List'!$B$9:$D$241,3,0) -> Steam Production | D28: 5120 | E28: 20120 | F28: 12300000 | G28: =VLOOKUP(H28,Settings!$B$30:$F$36,5,0) -> Lit | H28: Gas oil | I28: =VLOOKUP(H28,Settings!$B$30:$C$36,2,FALSE) -> 0.01 | J28: =VLOOKUP(H28,Settings!$B$46:$E$52,2,FALSE) -> 0.0741 | K28: =VLOOKUP(H28,Settings!$B$46:$E$52,3,FALSE) -> 3e-06 | L28: =VLOOKUP(H28,Settings!$B$46:$E$52,4,FALSE) -> 6e-07 | M28: =F28*I28*J28 -> 9114.3 | N28: =F28*I28*K28 -> 0.369 | O28: =F28*I28*L28 -> 0.0738 | P28: =M28+(N28*Settings!$C$24)+(O28*Settings!$D$24) -> 9144.4104
B29: =VLOOKUP(D29,'Unit List'!$B$9:$E$241,4,0) -> Iron Making | C29: =VLOOKUP(D29,'Unit List'!$B$9:$D$241,3,0) -> Lime Making | D29: 1120 | E29: 23180 | F29: 39288.571 | G29: =VLOOKUP(H29,Settings!$B$30:$F$36,5,0) -> kNm3 | H29: Natural Gas | I29: =VLOOKUP(H29,Settings!$B$30:$C$36,2,FALSE) -> 15 | J29: =VLOOKUP(H29,Settings!$B$46:$E$52,2,FALSE) -> 0.0561 | K29: =VLOOKUP(H29,Settings!$B$46:$E$52,3,FALSE) -> 1e-06 | L29: =VLOOKUP(H29,Settings!$B$46:$E$52,4,FALSE) -> 1e-07 | M29: =F29*I29*J29 -> 33061.332 | N29: =F29*I29*K29 -> 0.58932857 | O29: =F29*I29*L29 -> 0.058932857 | P29: =M29+(N29*Settings!$C$24)+(O29*Settings!$D$24) -> 33093.333
B30: =VLOOKUP(D30,'Unit List'!$B$9:$E$241,4,0) -> Iron Making | C30: =VLOOKUP(D30,'Unit List'!$B$9:$D$241,3,0) -> Dolomite Making | D30: 1140 | E30: 23180 | F30: 17136.383 | G30: =VLOOKUP(H30,Settings!$B$30:$F$36,5,0) -> kNm3 | H30: Natural Gas | I30: =VLOOKUP(H30,Settings!$B$30:$C$36,2,FALSE) -> 15 | J30: =VLOOKUP(H30,Settings!$B$46:$E$52,2,FALSE) -> 0.0561 | K30: =VLOOKUP(H30,Settings!$B$46:$E$52,3,FALSE) -> 1e-06 | L30: =VLOOKUP(H30,Settings!$B$46:$E$52,4,FALSE) -> 1e-07 | M30: =F30*I30*J30 -> 14420.266 | N30: =F30*I30*K30 -> 0.25704574 | O30: =F30*I30*L30 -> 0.025704575 | P30: =M30+(N30*Settings!$C$24)+(O30*Settings!$D$24) -> 14434.224
B31: =VLOOKUP(D31,'Unit List'!$B$9:$E$241,4,0) -> Iron Making | C31: =VLOOKUP(D31,'Unit List'!$B$9:$D$241,3,0) -> Pelletizing | D31: 1210 | E31: 23180 | F31: 93739.761 | G31: =VLOOKUP(H31,Settings!$B$30:$F$36,5,0) -> kNm3 | H31: Natural Gas | I31: =VLOOKUP(H31,Settings!$B$30:$C$36,2,FALSE) -> 15 | J31: =VLOOKUP(H31,Settings!$B$46:$E$52,2,FALSE) -> 0.0561 | K31: =VLOOKUP(H31,Settings!$B$46:$E$52,3,FALSE) -> 1e-06 | L31: =VLOOKUP(H31,Settings!$B$46:$E$52,4,FALSE) -> 1e-07 | M31: =F31*I31*J31 -> 78882.009 | N31: =F31*I31*K31 -> 1.4060964 | O31: =F31*I31*L31 -> 0.14060964 | P31: =M31+(N31*Settings!$C$24)+(O31*Settings!$D$24) -> 78958.36
B32: =VLOOKUP(D32,'Unit List'!$B$9:$E$241,4,0) -> Steel Making | C32: =VLOOKUP(D32,'Unit List'!$B$9:$D$241,3,0) -> EAFs | D32: 2210 | E32: 23180 | F32: 961.128 | G32: =VLOOKUP(H32,Settings!$B$30:$F$36,5,0) -> kNm3 | H32: Natural Gas | I32: =VLOOKUP(H32,Settings!$B$30:$C$36,2,FALSE) -> 15 | J32: =VLOOKUP(H32,Settings!$B$46:$E$52,2,FALSE) -> 0.0561 | K32: =VLOOKUP(H32,Settings!$B$46:$E$52,3,FALSE) -> 1e-06 | L32: =VLOOKUP(H32,Settings!$B$46:$E$52,4,FALSE) -> 1e-07 | M32: =F32*I32*J32 -> 808.78921 | N32: =F32*I32*K32 -> 0.01441692 | O32: =F32*I32*L32 -> 0.001441692 | P32: =M32+(N32*Settings!$C$24)+(O32*Settings!$D$24) -> 809.57205
B33: =VLOOKUP(D33,'Unit List'!$B$9:$E$241,4,0) -> Steel Making | C33: =VLOOKUP(D33,'Unit List'!$B$9:$D$241,3,0) -> De-gassing | D33: 2220 | E33: 23180 | F33: 2883.388 | G33: =VLOOKUP(H33,Settings!$B$30:$F$36,5,0) -> kNm3 | H33: Natural Gas | I33: =VLOOKUP(H33,Settings!$B$30:$C$36,2,FALSE) -> 15 | J33: =VLOOKUP(H33,Settings!$B$46:$E$52,2,FALSE) -> 0.0561 | K33: =VLOOKUP(H33,Settings!$B$46:$E$52,3,FALSE) -> 1e-06 | L33: =VLOOKUP(H33,Settings!$B$46:$E$52,4,FALSE) -> 1e-07 | M33: =F33*I33*J33 -> 2426.371 | N33: =F33*I33*K33 -> 0.04325082 | O33: =F33*I33*L33 -> 0.004325082 | P33: =M33+(N33*Settings!$C$24)+(O33*Settings!$D$24) -> 2428.7195
B34: =VLOOKUP(D34,'Unit List'!$B$9:$E$241,4,0) -> Steel Making | C34: =VLOOKUP(D34,'Unit List'!$B$9:$D$241,3,0) -> Laddle Furnaces | D34: 2301 | E34: 23180 | F34: 15378.068 | G34: =VLOOKUP(H34,Settings!$B$30:$F$36,5,0) -> kNm3 | H34: Natural Gas | I34: =VLOOKUP(H34,Settings!$B$30:$C$36,2,FALSE) -> 15 | J34: =VLOOKUP(H34,Settings!$B$46:$E$52,2,FALSE) -> 0.0561 | K34: =VLOOKUP(H34,Settings!$B$46:$E$52,3,FALSE) -> 1e-06 | L34: =VLOOKUP(H34,Settings!$B$46:$E$52,4,FALSE) -> 1e-07 | M34: =F34*I34*J34 -> 12940.644 | N34: =F34*I34*K34 -> 0.23067102 | O34: =F34*I34*L34 -> 0.023067102 | P34: =M34+(N34*Settings!$C$24)+(O34*Settings!$D$24) -> 12953.17
B35: =VLOOKUP(D35,'Unit List'!$B$9:$E$241,4,0) -> Steel Making | C35: =VLOOKUP(D35,'Unit List'!$B$9:$D$241,3,0) -> Casting Machines | D35: 2410 | E35: 23180 | F35: 18718.137 | G35: =VLOOKUP(H35,Settings!$B$30:$F$36,5,0) -> kNm3 | H35: Natural Gas | I35: =VLOOKUP(H35,Settings!$B$30:$C$36,2,FALSE) -> 15 | J35: =VLOOKUP(H35,Settings!$B$46:$E$52,2,FALSE) -> 0.0561 | K35: =VLOOKUP(H35,Settings!$B$46:$E$52,3,FALSE) -> 1e-06 | L35: =VLOOKUP(H35,Settings!$B$46:$E$52,4,FALSE) -> 1e-07 | M35: =F35*I35*J35 -> 15751.312 | N35: =F35*I35*K35 -> 0.28077206 | O35: =F35*I35*L35 -> 0.028077206 | P35: =M35+(N35*Settings!$C$24)+(O35*Settings!$D$24) -> 15766.558
B36: =VLOOKUP(D36,'Unit List'!$B$9:$E$241,4,0) -> Steel Making | C36: =VLOOKUP(D36,'Unit List'!$B$9:$D$241,3,0) -> Slab Cooling | D36: 2510 | E36: 23180 | F36: 3303.085 | G36: =VLOOKUP(H36,Settings!$B$30:$F$36,5,0) -> kNm3 | H36: Natural Gas | I36: =VLOOKUP(H36,Settings!$B$30:$C$36,2,FALSE) -> 15 | J36: =VLOOKUP(H36,Settings!$B$46:$E$52,2,FALSE) -> 0.0561 | K36: =VLOOKUP(H36,Settings!$B$46:$E$52,3,FALSE) -> 1e-06 | L36: =VLOOKUP(H36,Settings!$B$46:$E$52,4,FALSE) -> 1e-07 | M36: =F36*I36*J36 -> 2779.546 | N36: =F36*I36*K36 -> 0.049546275 | O36: =F36*I36*L36 -> 0.0049546275 | P36: =M36+(N36*Settings!$C$24)+(O36*Settings!$D$24) -> 2782.2364
B37: =VLOOKUP(D37,'Unit List'!$B$9:$E$241,4,0) -> Hot Rolling | C37: =VLOOKUP(D37,'Unit List'!$B$9:$D$241,3,0) -> Hot Rolling Mill | D37: 3101 | E37: 23180 | F37: 208.339 | G37: =VLOOKUP(H37,Settings!$B$30:$F$36,5,0) -> kNm3 | H37: Natural Gas | I37: =VLOOKUP(H37,Settings!$B$30:$C$36,2,FALSE) -> 15 | J37: =VLOOKUP(H37,Settings!$B$46:$E$52,2,FALSE) -> 0.0561 | K37: =VLOOKUP(H37,Settings!$B$46:$E$52,3,FALSE) -> 1e-06 | L37: =VLOOKUP(H37,Settings!$B$46:$E$52,4,FALSE) -> 1e-07 | M37: =F37*I37*J37 -> 175.31727 | N37: =F37*I37*K37 -> 0.003125085 | O37: =F37*I37*L37 -> 0.0003125085 | P37: =M37+(N37*Settings!$C$24)+(O37*Settings!$D$24) -> 175.48696
B38: =VLOOKUP(D38,'Unit List'!$B$9:$E$241,4,0) -> Hot Rolling | C38: =VLOOKUP(D38,'Unit List'!$B$9:$D$241,3,0) -> Hot Rolling Mill | D38: 3210 | E38: 23180 | F38: 200005.17 | G38: =VLOOKUP(H38,Settings!$B$30:$F$36,5,0) -> kNm3 | H38: Natural Gas | I38: =VLOOKUP(H38,Settings!$B$30:$C$36,2,FALSE) -> 15 | J38: =VLOOKUP(H38,Settings!$B$46:$E$52,2,FALSE) -> 0.0561 | K38: =VLOOKUP(H38,Settings!$B$46:$E$52,3,FALSE) -> 1e-06 | L38: =VLOOKUP(H38,Settings!$B$46:$E$52,4,FALSE) -> 1e-07 | M38: =F38*I38*J38 -> 168304.35 | N38: =F38*I38*K38 -> 3.0000775 | O38: =F38*I38*L38 -> 0.30000775 | P38: =M38+(N38*Settings!$C$24)+(O38*Settings!$D$24) -> 168467.25
B39: =VLOOKUP(D39,'Unit List'!$B$9:$E$241,4,0) -> Hot Rolling | C39: =VLOOKUP(D39,'Unit List'!$B$9:$D$241,3,0) -> Hot Rolling Mill | D39: 3310 | E39: 23180 | F39: 1041.694 | G39: =VLOOKUP(H39,Settings!$B$30:$F$36,5,0) -> kNm3 | H39: Natural Gas | I39: =VLOOKUP(H39,Settings!$B$30:$C$36,2,FALSE) -> 15 | J39: =VLOOKUP(H39,Settings!$B$46:$E$52,2,FALSE) -> 0.0561 | K39: =VLOOKUP(H39,Settings!$B$46:$E$52,3,FALSE) -> 1e-06 | L39: =VLOOKUP(H39,Settings!$B$46:$E$52,4,FALSE) -> 1e-07 | M39: =F39*I39*J39 -> 876.5855 | N39: =F39*I39*K39 -> 0.01562541 | O39: =F39*I39*L39 -> 0.001562541 | P39: =M39+(N39*Settings!$C$24)+(O39*Settings!$D$24) -> 877.43396
... B69: =VLOOKUP(D69,'Unit List'!$B$9:$E$241,4,0) -> TAS | C69: =VLOOKUP(D69,'Unit List'!$B$9:$D$241,3,0) -> - | D69: 9595 | E69: 23180 | F69: 71188.868 | G69: =VLOOKUP(H69,Settings!$B$30:$F$36,5,0) -> kNm3 | H69: Natural Gas | I69: =VLOOKUP(H69,Settings!$B$30:$C$36,2,FALSE) -> 15 | J69: =VLOOKUP(H69,Settings!$B$46:$E$52,2,FALSE) -> 0.0561 | K69: =VLOOKUP(H69,Settings!$B$46:$E$52,3,FALSE) -> 1e-06 | L69: =VLOOKUP(H69,Settings!$B$46:$E$52,4,FALSE) -> 1e-07 | M69: =F69*I69*J69 -> 59905.432 | N69: =F69*I69*K69 -> 1.067833 | O69: =F69*I69*L69 -> 0.1067833 | P69: =M69+(N69*Settings!$C$24)+(O69*Settings!$D$24) -> 59963.416
B70: =VLOOKUP(D70,'Unit List'!$B$9:$E$241,4,0) -> Utility | C70: =VLOOKUP(D70,'Unit List'!$B$9:$D$241,3,0) -> Steam Production | D70: 5120 | E70: 23190 | F70: 0 | G70: =VLOOKUP(H70,Settings!$B$30:$F$36,5,0) -> kNm3 | H70: Natural Gas | I70: =VLOOKUP(H70,Settings!$B$30:$C$36,2,FALSE) -> 15 | J70: =VLOOKUP(H70,Settings!$B$46:$E$52,2,FALSE) -> 0.0561 | K70: =VLOOKUP(H70,Settings!$B$46:$E$52,3,FALSE) -> 1e-06 | L70: =VLOOKUP(H70,Settings!$B$46:$E$52,4,FALSE) -> 1e-07 | M70: =F70*I70*J70 -> 0 | N70: =F70*I70*K70 -> 0 | O70: =F70*I70*L70 -> 0 | P70: =M70+(N70*Settings!$C$24)+(O70*Settings!$D$24) -> 0
B71: =VLOOKUP(D71,'Unit List'!$B$9:$E$241,4,0) -> Utility | C71: =VLOOKUP(D71,'Unit List'!$B$9:$D$241,3,0) -> PowerPlant 2 | D71: 5140 | E71: 23190 | F71: 143916.48 | G71: =VLOOKUP(H71,Settings!$B$30:$F$36,5,0) -> kNm3 | H71: Natural Gas | I71: =VLOOKUP(H71,Settings!$B$30:$C$36,2,FALSE) -> 15 | J71: =VLOOKUP(H71,Settings!$B$46:$E$52,2,FALSE) -> 0.0561 | K71: =VLOOKUP(H71,Settings!$B$46:$E$52,3,FALSE) -> 1e-06 | L71: =VLOOKUP(H71,Settings!$B$46:$E$52,4,FALSE) -> 1e-07 | M71: =F71*I71*J71 -> 121105.72 | N71: =F71*I71*K71 -> 2.1587472 | O71: =F71*I71*L71 -> 0.21587472 | P71: =M71+(N71*Settings!$C$24)+(O71*Settings!$D$24) -> 121222.94
B72: =VLOOKUP(D72,'Unit List'!$B$9:$E$241,4,0) -> Utility | C72: =VLOOKUP(D72,'Unit List'!$B$9:$D$241,3,0) -> PowerPlant 3 | D72: 5150 | E72: 23190 | F72: 488910.07 | G72: =VLOOKUP(H72,Settings!$B$30:$F$36,5,0) -> kNm3 | H72: Natural Gas | I72: =VLOOKUP(H72,Settings!$B$30:$C$36,2,FALSE) -> 15 | J72: =VLOOKUP(H72,Settings!$B$46:$E$52,2,FALSE) -> 0.0561 | K72: =VLOOKUP(H72,Settings!$B$46:$E$52,3,FALSE) -> 1e-06 | L72: =VLOOKUP(H72,Settings!$B$46:$E$52,4,FALSE) -> 1e-07 | M72: =F72*I72*J72 -> 411417.82 | N72: =F72*I72*K72 -> 7.333651 | O72: =F72*I72*L72 -> 0.7333651 | P72: =M72+(N72*Settings!$C$24)+(O72*Settings!$D$24) -> 411816.04
B73: =VLOOKUP(D73,'Unit List'!$B$9:$E$241,4,0) -> #N/A | C73: =VLOOKUP(D73,'Unit List'!$B$9:$D$241,3,0) -> #N/A | G73: =VLOOKUP(H73,Settings!$B$30:$F$36,5,0) -> #N/A | I73: =VLOOKUP(H73,Settings!$B$30:$C$36,2,FALSE) -> #N/A | J73: =VLOOKUP(H73,Settings!$B$46:$E$52,2,FALSE) -> #N/A | K73: =VLOOKUP(H73,Settings!$B$46:$E$52,3,FALSE) -> #N/A | L73: =VLOOKUP(H73,Settings!$B$46:$E$52,4,FALSE) -> #N/A | M73: =F73*I73*J73 -> #N/A | N73: =F73*I73*K73 -> #N/A | O73: =F73*I73*L73 -> #N/A | P73: =M73+(N73*Settings!$C$24)+(O73*Settings!$D$24) -> #N/A
B74: =VLOOKUP(D74,'Unit List'!$B$9:$E$241,4,0) -> #N/A | C74: =VLOOKUP(D74,'Unit List'!$B$9:$D$241,3,0) -> #N/A | G74: =VLOOKUP(H74,Settings!$B$30:$F$36,5,0) -> #N/A | I74: =VLOOKUP(H74,Settings!$B$30:$C$36,2,FALSE) -> #N/A | J74: =VLOOKUP(H74,Settings!$B$46:$E$52,2,FALSE) -> #N/A | K74: =VLOOKUP(H74,Settings!$B$46:$E$52,3,FALSE) -> #N/A | L74: =VLOOKUP(H74,Settings!$B$46:$E$52,4,FALSE) -> #N/A | M74: =F74*I74*J74 -> #N/A | N74: =F74*I74*K74 -> #N/A | O74: =F74*I74*L74 -> #N/A | P74: =M74+(N74*Settings!$C$24)+(O74*Settings!$D$24) -> #N/A
B75: =VLOOKUP(D75,'Unit List'!$B$9:$E$241,4,0) -> #N/A | C75: =VLOOKUP(D75,'Unit List'!$B$9:$D$241,3,0) -> #N/A | G75: =VLOOKUP(H75,Settings!$B$30:$F$36,5,0) -> #N/A | I75: =VLOOKUP(H75,Settings!$B$30:$C$36,2,FALSE) -> #N/A | J75: =VLOOKUP(H75,Settings!$B$46:$E$52,2,FALSE) -> #N/A | K75: =VLOOKUP(H75,Settings!$B$46:$E$52,3,FALSE) -> #N/A | L75: =VLOOKUP(H75,Settings!$B$46:$E$52,4,FALSE) -> #N/A | M75: =F75*I75*J75 -> #N/A | N75: =F75*I75*K75 -> #N/A | O75: =F75*I75*L75 -> #N/A | P75: =M75+(N75*Settings!$C$24)+(O75*Settings!$D$24) -> #N/A
B76: =VLOOKUP(D76,'Unit List'!$B$9:$E$241,4,0) -> #N/A | C76: =VLOOKUP(D76,'Unit List'!$B$9:$D$241,3,0) -> #N/A | G76: =VLOOKUP(H76,Settings!$B$30:$F$36,5,0) -> #N/A | I76: =VLOOKUP(H76,Settings!$B$30:$C$36,2,FALSE) -> #N/A | J76: =VLOOKUP(H76,Settings!$B$46:$E$52,2,FALSE) -> #N/A | K76: =VLOOKUP(H76,Settings!$B$46:$E$52,3,FALSE) -> #N/A | L76: =VLOOKUP(H76,Settings!$B$46:$E$52,4,FALSE) -> #N/A | M76: =F76*I76*J76 -> #N/A | N76: =F76*I76*K76 -> #N/A | O76: =F76*I76*L76 -> #N/A | P76: =M76+(N76*Settings!$C$24)+(O76*Settings!$D$24) -> #N/A
B77: =VLOOKUP(D77,'Unit List'!$B$9:$E$241,4,0) -> #N/A | C77: =VLOOKUP(D77,'Unit List'!$B$9:$D$241,3,0) -> #N/A | G77: =VLOOKUP(H77,Settings!$B$30:$F$36,5,0) -> #N/A | I77: =VLOOKUP(H77,Settings!$B$30:$C$36,2,FALSE) -> #N/A | J77: =VLOOKUP(H77,Settings!$B$46:$E$52,2,FALSE) -> #N/A | K77: =VLOOKUP(H77,Settings!$B$46:$E$52,3,FALSE) -> #N/A | L77: =VLOOKUP(H77,Settings!$B$46:$E$52,4,FALSE) -> #N/A | M77: =F77*I77*J77 -> #N/A | N77: =F77*I77*K77 -> #N/A | O77: =F77*I77*L77 -> #N/A | P77: =M77+(N77*Settings!$C$24)+(O77*Settings!$D$24) -> #N/A
B78: =VLOOKUP(D78,'Unit List'!$B$9:$E$241,4,0) -> #N/A | C78: =VLOOKUP(D78,'Unit List'!$B$9:$D$241,3,0) -> #N/A | G78: =VLOOKUP(H78,Settings!$B$30:$F$36,5,0) -> #N/A | I78: =VLOOKUP(H78,Settings!$B$30:$C$36,2,FALSE) -> #N/A | J78: =VLOOKUP(H78,Settings!$B$46:$E$52,2,FALSE) -> #N/A | K78: =VLOOKUP(H78,Settings!$B$46:$E$52,3,FALSE) -> #N/A | L78: =VLOOKUP(H78,Settings!$B$46:$E$52,4,FALSE) -> #N/A | M78: =F78*I78*J78 -> #N/A | N78: =F78*I78*K78 -> #N/A | O78: =F78*I78*L78 -> #N/A | P78: =M78+(N78*Settings!$C$24)+(O78*Settings!$D$24) -> #N/A
B79: =VLOOKUP(D79,'Unit List'!$B$9:$E$241,4,0) -> #N/A | C79: =VLOOKUP(D79,'Unit List'!$B$9:$D$241,3,0) -> #N/A | G79: =VLOOKUP(H79,Settings!$B$30:$F$36,5,0) -> #N/A | I79: =VLOOKUP(H79,Settings!$B$30:$C$36,2,FALSE) -> #N/A | J79: =VLOOKUP(H79,Settings!$B$46:$E$52,2,FALSE) -> #N/A | K79: =VLOOKUP(H79,Settings!$B$46:$E$52,3,FALSE) -> #N/A | L79: =VLOOKUP(H79,Settings!$B$46:$E$52,4,FALSE) -> #N/A | M79: =F79*I79*J79 -> #N/A | N79: =F79*I79*K79 -> #N/A | O79: =F79*I79*L79 -> #N/A | P79: =M79+(N79*Settings!$C$24)+(O79*Settings!$D$24) -> #N/A
B80: =VLOOKUP(D80,'Unit List'!$B$9:$E$241,4,0) -> #N/A | C80: =VLOOKUP(D80,'Unit List'!$B$9:$D$241,3,0) -> #N/A | G80: =VLOOKUP(H80,Settings!$B$30:$F$36,5,0) -> #N/A | I80: =VLOOKUP(H80,Settings!$B$30:$C$36,2,FALSE) -> #N/A | J80: =VLOOKUP(H80,Settings!$B$46:$E$52,2,FALSE) -> #N/A | K80: =VLOOKUP(H80,Settings!$B$46:$E$52,3,FALSE) -> #N/A | L80: =VLOOKUP(H80,Settings!$B$46:$E$52,4,FALSE) -> #N/A | M80: =F80*I80*J80 -> #N/A | N80: =F80*I80*K80 -> #N/A | O80: =F80*I80*L80 -> #N/A | P80: =M80+(N80*Settings!$C$24)+(O80*Settings!$D$24) -> #N/A
B81: =VLOOKUP(D81,'Unit List'!$B$9:$E$241,4,0) -> #N/A | C81: =VLOOKUP(D81,'Unit List'!$B$9:$D$241,3,0) -> #N/A | G81: =VLOOKUP(H81,Settings!$B$30:$F$36,5,0) -> #N/A | I81: =VLOOKUP(H81,Settings!$B$30:$C$36,2,FALSE) -> #N/A | J81: =VLOOKUP(H81,Settings!$B$46:$E$52,2,FALSE) -> #N/A | K81: =VLOOKUP(H81,Settings!$B$46:$E$52,3,FALSE) -> #N/A | L81: =VLOOKUP(H81,Settings!$B$46:$E$52,4,FALSE) -> #N/A | M81: =F81*I81*J81 -> #N/A | N81: =F81*I81*K81 -> #N/A | O81: =F81*I81*L81 -> #N/A | P81: =M81+(N81*Settings!$C$24)+(O81*Settings!$D$24) -> #N/A
B82: =VLOOKUP(D82,'Unit List'!$B$9:$E$241,4,0) -> #N/A | C82: =VLOOKUP(D82,'Unit List'!$B$9:$D$241,3,0) -> #N/A | G82: =VLOOKUP(H82,Settings!$B$30:$F$36,5,0) -> #N/A | I82: =VLOOKUP(H82,Settings!$B$30:$C$36,2,FALSE) -> #N/A | J82: =VLOOKUP(H82,Settings!$B$46:$E$52,2,FALSE) -> #N/A | K82: =VLOOKUP(H82,Settings!$B$46:$E$52,3,FALSE) -> #N/A | L82: =VLOOKUP(H82,Settings!$B$46:$E$52,4,FALSE) -> #N/A | M82: =F82*I82*J82 -> #N/A | N82: =F82*I82*K82 -> #N/A | O82: =F82*I82*L82 -> #N/A | P82: =M82+(N82*Settings!$C$24)+(O82*Settings!$D$24) -> #N/A
B83: =VLOOKUP(D83,'Unit List'!$B$9:$E$241,4,0) -> #N/A | C83: =VLOOKUP(D83,'Unit List'!$B$9:$D$241,3,0) -> #N/A | G83: =VLOOKUP(H83,Settings!$B$30:$F$36,5,0) -> #N/A | I83: =VLOOKUP(H83,Settings!$B$30:$C$36,2,FALSE) -> #N/A | J83: =VLOOKUP(H83,Settings!$B$46:$E$52,2,FALSE) -> #N/A | K83: =VLOOKUP(H83,Settings!$B$46:$E$52,3,FALSE) -> #N/A | L83: =VLOOKUP(H83,Settings!$B$46:$E$52,4,FALSE) -> #N/A | M83: =F83*I83*J83 -> #N/A | N83: =F83*I83*K83 -> #N/A | O83: =F83*I83*L83 -> #N/A | P83: =M83+(N83*Settings!$C$24)+(O83*Settings!$D$24) -> #N/A
B84: =VLOOKUP(D84,'Unit List'!$B$9:$E$241,4,0) -> #N/A | C84: =VLOOKUP(D84,'Unit List'!$B$9:$D$241,3,0) -> #N/A | G84: =VLOOKUP(H84,Settings!$B$30:$F$36,5,0) -> #N/A | I84: =VLOOKUP(H84,Settings!$B$30:$C$36,2,FALSE) -> #N/A | J84: =VLOOKUP(H84,Settings!$B$46:$E$52,2,FALSE) -> #N/A | K84: =VLOOKUP(H84,Settings!$B$46:$E$52,3,FALSE) -> #N/A | L84: =VLOOKUP(H84,Settings!$B$46:$E$52,4,FALSE) -> #N/A | M84: =F84*I84*J84 -> #N/A | N84: =F84*I84*K84 -> #N/A | O84: =F84*I84*L84 -> #N/A | P84: =M84+(N84*Settings!$C$24)+(O84*Settings!$D$24) -> #N/A
... B95: =VLOOKUP(D95,'Unit List'!$B$9:$E$241,4,0) -> #N/A | C95: =VLOOKUP(D95,'Unit List'!$B$9:$D$241,3,0) -> #N/A | G95: =VLOOKUP(H95,Settings!$B$30:$F$36,5,0) -> #N/A | I95: =VLOOKUP(H95,Settings!$B$30:$C$36,2,FALSE) -> #N/A | J95: =VLOOKUP(H95,Settings!$B$46:$E$52,2,FALSE) -> #N/A | K95: =VLOOKUP(H95,Settings!$B$46:$E$52,3,FALSE) -> #N/A | L95: =VLOOKUP(H95,Settings!$B$46:$E$52,4,FALSE) -> #N/A | M95: =F95*I95*J95 -> #N/A | N95: =F95*I95*K95 -> #N/A | O95: =F95*I95*L95 -> #N/A | P95: =M95+(N95*Settings!$C$24)+(O95*Settings!$D$24) -> #N/A
B96: Sum | M96: =_xlfn.AGGREGATE(9,6,M11:M95) -> 1295472.5 | N96: =_xlfn.AGGREGATE(9,6,N11:N95) -> 23.285476 | O96: =_xlfn.AGGREGATE(9,6,O11:O95) -> 2.3654831 | P96: =_xlfn.AGGREGATE(9,6,P11:P95) -> 1296747
J100: Combustion Emissions
J101: Emission Code | K101: Area | M101: Emission
M102: (tCO2/y) | N102: (tCH4/y) | O102: (tN2O/y) | P102: (tCO2e/y)
J103: 1-C-1 | K103: Iron Making | M103: =SUMIF($B$11:$B$95,K103,$M$11:$M$95) -> 126420.9 | N103: =SUMIF($B$11:$B$95,K103,$N$11:$N$95) -> 2.2524975 | O103: =SUMIF(B11:B95,K103,O11:O95) -> 0.22525242 | P103: =SUMIF($B$11:$B$95,K103,$P$11:$P$95) -> 126543.21
J104: 2-C-2 | K104: Steel Making | M104: =SUMIF($B$11:$B$95,K104,$M$11:$M$95) -> 34851.215 | N104: =SUMIF($B$11:$B$95,K104,$N$11:$N$95) -> 0.61872455 | O104: =SUMIF(B12:B96,K104,O12:O96) -> 0.061879201 | P104: =SUMIF($B$11:$B$95,K104,$P$11:$P$95) -> 34884.813
J105: 3-C-3 | K105: Hot Rolling | M105: =SUMIF($B$11:$B$95,K105,$M$11:$M$95) -> 175384.09 | N105: =SUMIF($B$11:$B$95,K105,$N$11:$N$95) -> 3.125112 | O105: =SUMIF(B13:B97,K105,O13:O97) -> 0.31251433 | P105: =SUMIF($B$11:$B$95,K105,$P$11:$P$95) -> 175553.78
J106: 4-C-4 | K106: Cold Rolling | M106: =SUMIF($B$11:$B$95,K106,$M$11:$M$95) -> 27783.999 | N106: =SUMIF($B$11:$B$95,K106,$N$11:$N$95) -> 0.4891918 | O106: =SUMIF(B14:B98,K106,O14:O98) -> 0.04893549 | P106: =SUMIF($B$11:$B$95,K106,$P$11:$P$95) -> 27810.566
J107: 5-C-5 | K107: Utility | M107: =SUMIF($B$11:$B$95,K107,$M$11:$M$95) -> 827049.63 | N107: =SUMIF($B$11:$B$95,K107,$N$11:$N$95) -> 14.948705 | O107: =SUMIF(B15:B99,K107,O15:O99) -> 1.5317712 | P107: =SUMIF($B$11:$B$95,K107,$P$11:$P$95) -> 827871.42
J108: 6-C-6 | K108: Transportation | M108: =SUMIF($B$11:$B$95,K108,$M$11:$M$95) -> 2.376 | N108: =SUMIF($B$11:$B$95,K108,$N$11:$N$95) -> 1.1088e-06 | O108: =SUMIF(B16:B100,K108,O16:O100) -> 2.2176e-07 | P108: =SUMIF($B$11:$B$95,K108,$P$11:$P$95) -> 2.3760905
J109: 7-C-7 | K109: Maintenance | M109: =SUMIF($B$11:$B$95,K109,$M$11:$M$95) -> 13894.644 | N109: =SUMIF($B$11:$B$95,K109,$N$11:$N$95) -> 0.24738219 | O109: =SUMIF(B17:B101,K109,O17:O101) -> 0.024738994 | P109: =SUMIF($B$11:$B$95,K109,$P$11:$P$95) -> 13908.077
J110: 9-C-8 | K110: TAS | M110: =SUMIF($B$11:$B$95,K110,$M$11:$M$95) -> 90085.662 | N110: =SUMIF($B$11:$B$95,K110,$N$11:$N$95) -> 1.6038621 | O110: =SUMIF(B18:B102,K110,O18:O102) -> 0.16039131 | P110: =SUMIF($B$11:$B$95,K110,$P$11:$P$95) -> 90172.753
J111: Sum | M111: =_xlfn.AGGREGATE(9,6,M103:M110) -> 1295472.5 | N111: =_xlfn.AGGREGATE(9,6,N103:N110) -> 23.285476 | O111: =_xlfn.AGGREGATE(9,6,O103:O110) -> 2.3654831 | P111: =_xlfn.AGGREGATE(9,6,P103:P110) -> 1296747

Sheet Vent
B7: Vent
B8: Area | C8: Unit Process | D8: Cost Center Code | E8: Emission Source | F8: Gas | G8: GWP | H8: Production | I8: EF | J8: Gas Feed | K8: EF | L8: Emission | N8: Data Source of Activity Data
H9: (ton/y) | I9: (ton/ton of product) | J9: (kNm3) | K9: (ton per kNm3) | L9: (ton/y) | M9: (tCO2e/y)
B10: =VLOOKUP(D10,'Unit List'!$B$9:$E$241,4,0) -> Iron Making | C10: =VLOOKUP(D10,'Unit List'!$B$8:$E$241,3,0) -> Lime Making | D10: 1120 | E10: CO2 process vent in Lime production | F10: CO2 | G10: =HLOOKUP(F10,Settings!$B$23:$G$24,2,0) -> 1 | H10: 263251 | I10: 0.757 | L10: =H10*I10 -> 199281.01 | M10: =L10*G10 -> 199281.01 | N10: Measurement
B11: =VLOOKUP(D11,'Unit List'!$B$9:$E$241,4,0) -> Steel Making | C11: =VLOOKUP(D11,'Unit List'!$B$8:$E$241,3,0) -> EAFs | D11: 2210 | E11: CO2 process vent in EAF (1-8) | F11: CO2 | G11: =HLOOKUP(F11,Settings!$B$23:$G$24,2,0) -> 1 | H11: 7742718 | I11: 0.055227879 | L11: =H11*I11 -> 427613.9 | M11: =L11*G11 -> 427613.9 | N11: Measurement
B12: =VLOOKUP(D12,'Unit List'!$B$9:$E$241,4,0) -> Iron Making | C12: =VLOOKUP(D12,'Unit List'!$B$8:$E$241,3,0) -> Dolomite Making | D12: 1140 | E12: CO2 process vent in Dolomite production | F12: CO2 | G12: =HLOOKUP(F12,Settings!$B$23:$G$24,2,0) -> 1 | H12: 229204 | I12: 0.47732 | L12: =H12*I12 -> 109403.65 | M12: =L12*G12 -> 109403.65 | N12: Measurement
B13: =VLOOKUP(D13,'Unit List'!$B$9:$E$241,4,0) -> Iron Making | C13: =VLOOKUP(D13,'Unit List'!$B$8:$E$241,3,0) -> Direct Reduction | D13: 1310 | E13: CO2 process vent in DRI 1 | F13: CO2 | G13: =HLOOKUP(F13,Settings!$B$23:$G$24,2,0) -> 1 | J13: 1203870 | K13: 2.01 | L13: =J13*K13 -> 2419778.7 | M13: =L13*G13 -> 2419778.7 | N13: PRS4.GASNAG29
B14: =VLOOKUP(D14,'Unit List'!$B$9:$E$241,4,0) -> Iron Making | C14: =VLOOKUP(D14,'Unit List'!$B$8:$E$241,3,0) -> Direct Reduction | D14: 1315 | E14: CO2 process vent in DRI 2 | F14: CO2 | G14: =HLOOKUP(F14,Settings!$B$23:$G$24,2,0) -> 1 | J14: 565966.17 | K14: 2.01 | L14: =J14*K14 -> 1137592 | M14: =L14*G14 -> 1137592 | N14: GASNAG32
B15: =VLOOKUP(D15,'Unit List'!$B$9:$E$241,4,0) -> #N/A | C15: =VLOOKUP(D15,'Unit List'!$B$8:$E$241,3,0) -> #N/A | G15: =HLOOKUP(F15,Settings!$B$23:$G$24,2,0) -> #N/A | M15: =L15*G15 -> #N/A
B16: =VLOOKUP(D16,'Unit List'!$B$9:$E$241,4,0) -> #N/A | C16: =VLOOKUP(D16,'Unit List'!$B$8:$E$241,3,0) -> #N/A | G16: =HLOOKUP(F16,Settings!$B$23:$G$24,2,0) -> #N/A | M16: =L16*G16 -> #N/A
B17: Sum | M17: =_xlfn.AGGREGATE(9,6,M10:M16) -> 4293669.3
I21: References for EFs: | K21: Vent Emissions
H22: The Intergovernmental Panel on Climate Change (IPCC) Guidelines for National Greenhouse Gas Inventories, 2006. | I22: Lime Making: | K22: Emission Code | L22: Area | M22: Emission
H23: GHG Protocol, Calculating Greenhouse Gas Emissions from Iron and Steel Production, 2008 (Equation13). | I23: EAFs: | M23: (tCO2e/y)
H24: GHG Protocol, Calculating Greenhouse Gas Emissions from Iron and Steel Production, 2008 (Equation14). | I24: Direct Reduction: | K24: 1-V-9 | L24: Iron Making | M24: =SUMIF($B$10:$B$16,L24,$M$10:$M$16) -> 3866055.4
H25: The Intergovernmental Panel on Climate Change (IPCC) Guidelines for National Greenhouse Gas Inventories, 2006. | I25: Dolomite Making: | K25: 2-V-10 | L25: Steel Making | M25: =SUMIF($B$10:$B$16,L25,$M$10:$M$16) -> 427613.9
K26: 3-V-11 | L26: Hot Rolling | M26: =SUMIF($B$10:$B$16,L26,$M$10:$M$16) -> 0
K27: 4-V-12 | L27: Cold Rolling | M27: =SUMIF($B$10:$B$16,L27,$M$10:$M$16) -> 0
K28: 5-V-13 | L28: Utility | M28: =SUMIF($B$10:$B$16,L28,$M$10:$M$16) -> 0
K29: 6-V-14 | L29: Transportation | M29: =SUMIF($B$10:$B$16,L29,$M$10:$M$16) -> 0
K30: 7-V-15 | L30: Maintenance | M30: =SUMIF($B$10:$B$16,L30,$M$10:$M$16) -> 0
K31: 9-V-16 | L31: TAS | M31: =SUMIF($B$10:$B$16,L31,$M$10:$M$16) -> 0
K32: Sum | M32: =_xlfn.AGGREGATE(9,6,M24:M31) -> 4293669.3

Sheet Fugitive
B7: Fugitive (Methane)
B8: Emission Code | C8: Area | D8: Facility - Unit Process | E8: Facility | F8: Valves | G8: Flanges | H8: PSVs | I8: Fugitive Emission (No Control) | J8: Control Efficiency | K8: Emission | M8: Data Source of Equipment Count
F9: EFs (gr/hr) | K9: CH4 | L9: Total CO2e
F10: =Settings!C138 -> 4.0369688 | G10: =Settings!C139 -> 1.3154168 | H10: =Settings!C140 -> 104.00865
F11: Equipment Count | I11: (gr/hr) | J11: (%) | K11: (tCH4/y) | L11: (tCO2e/y)
B12: None | C12: Iron Making | D12: PRS1,2 - Pelletizing | E12: CH4 | F12: 49 | G12: 25 | H12: 4 | I12: =F12*$F$10+G12*$G$10+H12*$H$10 -> 646.73147 | J12: 0 | K12: =I12*(1-J12)*Settings!$D$16*Settings!$D$13/1000000 -> 5.114694 | L12: =K12*Settings!$G$24 -> 152.41788 | M12: P&IDs
B13: None | C13: Iron Making | D13: PRS3 - Lime Making | E13: CH4 | F13: 27 | G13: 17 | H13: 2 | I13: =F13*$F$10+G13*$G$10+H13*$H$10 -> 339.37753 | J13: 0 | K13: =I13*(1-J13)*Settings!$D$16*Settings!$D$13/1000000 -> 2.6839767 | L13: =K13*Settings!$G$24 -> 79.982507 | M13: P&IDs
B14: None | C14: Iron Making | D14: PRS4 - Direct Reduction | E14: CH4 | F14: 15 | G14: 22 | H14: 0 | I14: =F14*$F$10+G14*$G$10+H14*$H$10 -> 89.493702 | J14: 0 | K14: =I14*(1-J14)*Settings!$D$16*Settings!$D$13/1000000 -> 0.70776344 | L14: =K14*Settings!$G$24 -> 21.091351 | M14: P&IDs
B15: None | C15: Steel Making | D15: PRS5 - EAFs | E15: CH4 | F15: 31 | G15: 16 | H15: 2 | I15: =F15*$F$10+G15*$G$10+H15*$H$10 -> 354.20999 | J15: 0 | K15: =I15*(1-J15)*Settings!$D$16*Settings!$D$13/1000000 -> 2.8012796 | L15: =K15*Settings!$G$24 -> 83.478133 | M15: P&IDs
B16: None | C16: Steel Making | D16: PRS6,7 - Casting Machines | E16: CH4 | F16: 44 | G16: 31 | H16: 4 | I16: =F16*$F$10+G16*$G$10+H16*$H$10 -> 634.43913 | J16: 0 | K16: =I16*(1-J16)*Settings!$D$16*Settings!$D$13/1000000 -> 5.0174796 | L16: =K16*Settings!$G$24 -> 149.52089 | M16: P&IDs
B17: None | C17: Hot Rolling | D17: PRS8 - Hot Rolling | E17: CH4 | F17: 27 | G17: 21 | H17: 3 | I17: =F17*$F$10+G17*$G$10+H17*$H$10 -> 448.64785 | J17: 0 | K17: =I17*(1-J17)*Settings!$D$16*Settings!$D$13/1000000 -> 3.5481441 | L17: =K17*Settings!$G$24 -> 105.73469 | M17: P&IDs
B18: None | C18: Cold Rolling | D18: PRS9,10 - Cold Rolling | E18: CH4 | F18: 25 | G18: 18 | H18: 2 | I18: =F18*$F$10+G18*$G$10+H18*$H$10 -> 332.61901 | J18: 0 | K18: =I18*(1-J18)*Settings!$D$16*Settings!$D$13/1000000 -> 2.6305268 | L18: =K18*Settings!$G$24 -> 78.389698 | M18: P&IDs
B19: None | C19: Utility | D19: PRS11 - PowerPlant 1 | E19: CH4 | F19: 40 | G19: 17 | H19: 3 | I19: =F19*$F$10+G19*$G$10+H19*$H$10 -> 495.86677 | J19: 0 | K19: =I19*(1-J19)*Settings!$D$16*Settings!$D$13/1000000 -> 3.9215763 | L19: =K19*Settings!$G$24 -> 116.86297 | M19: P&IDs
B20: None | C20: Utility | D20: PRS12 - Industrial Water Production | E20: CH4 | F20: 26 | G20: 15 | H20: 2 | I20: =F20*$F$10+G20*$G$10+H20*$H$10 -> 332.70973 | J20: 0 | K20: =I20*(1-J20)*Settings!$D$16*Settings!$D$13/1000000 -> 2.6312442 | L20: =K20*Settings!$G$24 -> 78.411078 | M20: P&IDs
B21: None | C21: Utility | D21: PRS13 - PowerPlant 2 | E21: CH4 | F21: 5 | G21: 8 | H21: 0 | I21: =F21*$F$10+G21*$G$10+H21*$H$10 -> 30.708178 | J21: 0 | K21: =I21*(1-J21)*Settings!$D$16*Settings!$D$13/1000000 -> 0.24285649 | L21: =K21*Settings!$G$24 -> 7.2371234 | M21: P&IDs
B22: None | C22: TAS | D22: PRS14 - Fire Fighting | E22: CH4 | F22: 18 | G22: 12 | H22: 2 | I22: =F22*$F$10+G22*$G$10+H22*$H$10 -> 296.46773 | J22: 0 | K22: =I22*(1-J22)*Settings!$D$16*Settings!$D$13/1000000 -> 2.3446234 | L22: =K22*Settings!$G$24 -> 69.869776 | M22: P&IDs
B23: None | C23: Cold Rolling | D23: PRS15 - Galvanizing Line | E23: CH4 | F23: 27 | G23: 24 | H23: 2 | I23: =F23*$F$10+G23*$G$10+H23*$H$10 -> 348.58545 | J23: 0 | K23: =I23*(1-J23)*Settings!$D$16*Settings!$D$13/1000000 -> 2.7567978 | L23: =K23*Settings!$G$24 -> 82.152575 | M23: P&IDs
... B30: None | C30: Utility | D30: PRS22 - Waste 21 Unit | E30: CH4 | F30: 17 | G30: 18 | H30: 2 | I30: =F30*$F$10+G30*$G$10+H30*$H$10 -> 300.32326 | J30: 0 | K30: =I30*(1-J30)*Settings!$D$16*Settings!$D$13/1000000 -> 2.3751149 | L30: =K30*Settings!$G$24 -> 70.778425 | M30: P&IDs
B31: None | C31: Utility | D31: Turbines/Boilers - Boilers & Turbines | E31: CH4 | I31: =F31*$F$10+G31*$G$10+H31*$H$10 -> 0 | J31: 0 | K31: =I31*(1-J31)*Settings!$D$16*Settings!$D$13/1000000 -> 0 | L31: =K31*Settings!$G$24 -> 0 | M31: P&IDs
B32: None | C32: Iron Making | D32: Reformers - Direct Reduction | E32: CH4 | I32: =F32*$F$10+G32*$G$10+H32*$H$10 -> 0 | J32: 0 | K32: =I32*(1-J32)*Settings!$D$16*Settings!$D$13/1000000 -> 0 | L32: =K32*Settings!$G$24 -> 0 | M32: P&IDs
B33: None | C33: Utility | D33: HoseinAbad Station - Methane Distribution | E33: CH4 | F33: 7 | G33: 6 | H33: 0 | I33: =F33*$F$10+G33*$G$10+H33*$H$10 -> 36.151282 | J33: 0 | K33: =I33*(1-J33)*Settings!$D$16*Settings!$D$13/1000000 -> 0.28590343 | L33: =K33*Settings!$G$24 -> 8.5199222 | M33: P&IDs
B34: None | C34: Utility | D34: Batching Point - Methane Distribution | E34: CH4 | F34: 9 | G34: 6 | H34: 0 | I34: =F34*$F$10+G34*$G$10+H34*$H$10 -> 44.22522 | J34: 0 | K34: =I34*(1-J34)*Settings!$D$16*Settings!$D$13/1000000 -> 0.34975639 | L34: =K34*Settings!$G$24 -> 10.42274 | M34: P&IDs
B35: None | C35: Utility | D35: 70000 Station - Methane Distribution | E35: CH4 | F35: 72 | G35: 52 | H35: 2 | I35: =F35*$F$10+G35*$G$10+H35*$H$10 -> 567.08072 | J35: 0 | K35: =I35*(1-J35)*Settings!$D$16*Settings!$D$13/1000000 -> 4.4847737 | L35: =K35*Settings!$G$24 -> 133.64626 | M35: P&IDs
B36: None | C36: Utility | D36: 200000 Station - Methane Distribution | E36: CH4 | F36: 135 | G36: 129 | H36: 3 | I36: =F36*$F$10+G36*$G$10+H36*$H$10 -> 1026.7055 | J36: 0 | K36: =I36*(1-J36)*Settings!$D$16*Settings!$D$13/1000000 -> 8.1197291 | L36: =K36*Settings!$G$24 -> 241.96793 | M36: P&IDs
B37: None | C37: Utility | D37: Valve Station - Methane Distribution | E37: CH4 | F37: 2 | G37: 1 | H37: 0 | I37: =F37*$F$10+G37*$G$10+H37*$H$10 -> 9.3893544 | J37: 0 | K37: =I37*(1-J37)*Settings!$D$16*Settings!$D$13/1000000 -> 0.074255972 | L37: =K37*Settings!$G$24 -> 2.212828 | M37: P&IDs
B38: None | E38: CH4 | I38: =F38*$F$10+G38*$G$10+H38*$H$10 -> 0 | J38: 0 | K38: =I38*(1-J38)*Settings!$D$16*Settings!$D$13/1000000 -> 0 | L38: =K38*Settings!$G$24 -> 0
B39: None | E39: CH4 | I39: =F39*$F$10+G39*$G$10+H39*$H$10 -> 0 | J39: 0 | K39: =I39*(1-J39)*Settings!$D$16*Settings!$D$13/1000000 -> 0 | L39: =K39*Settings!$G$24 -> 0
B40: None | E40: CH4 | I40: =F40*$F$10+G40*$G$10+H40*$H$10 -> 0 | J40: 0 | K40: =I40*(1-J40)*Settings!$D$16*Settings!$D$13/1000000 -> 0 | L40: =K40*Settings!$G$24 -> 0
B41: None | E41: CH4 | I41: =F41*$F$10+G41*$G$10+H41*$H$10 -> 0 | J41: 0 | K41: =I41*(1-J41)*Settings!$D$16*Settings!$D$13/1000000 -> 0 | L41: =K41*Settings!$G$24 -> 0
B42: Sum | K42: =_xlfn.AGGREGATE(9,6,K12:K41) -> 61.836212 | L42: =_xlfn.AGGREGATE(9,6,L12:L41) -> 1842.7191
B45: Fugitive (Other GHGs)
B46: Emission Code | C46: Area | D46: Unit Process | E46: GHG | F46: Annual Consumption | H46: GWP | I46: Notes | K46: Emission | M46: Data Source of Annaul Consumption
K47: GHG | L47: Total CO2e
F48: (kg) | K48: (t/y) | L48: (tCO2e/y)
B49: 5-F-25 | C49: Utility | D49: Electricity Distribution | E49: SF6 | F49: 400 | H49: =HLOOKUP(E49,Settings!$B$23:$G$24,2,FALSE) -> 24300 | I49: - | K49: =F49/1000 -> 0.4 | L49: =K49*H49 -> 9720 | M49: Purchase Order
B50: 7-F-26 | C50: Maintenance | D50: CO2 fire extinguishers | E50: CO2 | F50: 46864 | H50: =HLOOKUP(E50,Settings!$B$23:$G$24,2,FALSE) -> 1 | I50: - | K50: =F50/1000 -> 46.864 | L50: =K50*H50 -> 46.864 | M50: Purchase Order
B51: Sum | L51: =_xlfn.AGGREGATE(9,6,L49:L50) -> 9766.864
B54: Fugitive (Non-Kyoto GHG)
B55: Emission Code | C55: Area | D55: Unit Process | E55: GHG | F55: Annual Consumption | H55: GWP | I55: Notes | K55: Emission | M55: Data Source of Annaul Consumption
K56: GHG | L56: Total CO2e
F57: (kg) | K57: (t/y) | L57: (tCO2e/y)
B58: None | C58: Iron Making | D58: All cost centers | E58: CFC-12 | F58: 0 | H58: =HLOOKUP(E58,Settings!$B$23:$G$24,2,FALSE) -> 12500 | I58: Non-Kyoto GHG | K58: =F58/1000 -> 0 | L58: =K58*H58 -> 0 | M58: Purchase Order
B59: None | C59: Steel Making | D59: All cost centers | E59: CFC-12 | F59: 0 | H59: =HLOOKUP(E59,Settings!$B$23:$G$24,2,FALSE) -> 12500 | I59: Non-Kyoto GHG | K59: =F59/1000 -> 0 | L59: =K59*H59 -> 0 | M59: Purchase Order
B60: None | C60: Hot Rolling | D60: All cost centers | E60: CFC-12 | F60: 0 | H60: =HLOOKUP(E60,Settings!$B$23:$G$24,2,FALSE) -> 12500 | I60: Non-Kyoto GHG | K60: =F60/1000 -> 0 | L60: =K60*H60 -> 0 | M60: Purchase Order
B61: None | C61: Cold Rolling | D61: All cost centers | E61: CFC-12 | F61: 68 | H61: =HLOOKUP(E61,Settings!$B$23:$G$24,2,FALSE) -> 12500 | I61: Non-Kyoto GHG | K61: =F61/1000 -> 0.068 | L61: =K61*H61 -> 850 | M61: Purchase Order
B62: None | C62: Utility | D62: All cost centers | E62: CFC-12 | F62: 5149 | H62: =HLOOKUP(E62,Settings!$B$23:$G$24,2,FALSE) -> 12500 | I62: Non-Kyoto GHG | K62: =F62/1000 -> 5.149 | L62: =K62*H62 -> 64362.5 | M62: Purchase Order
B63: None | C63: Transportation | D63: All cost centers | E63: CFC-12 | F63: 57 | H63: =HLOOKUP(E63,Settings!$B$23:$G$24,2,FALSE) -> 12500 | I63: Non-Kyoto GHG | K63: =F63/1000 -> 0.057 | L63: =K63*H63 -> 712.5 | M63: Purchase Order
B64: None | C64: Maintenance | D64: All cost centers | E64: CFC-12 | F64: 14 | H64: =HLOOKUP(E64,Settings!$B$23:$G$24,2,FALSE) -> 12500 | I64: Non-Kyoto GHG | K64: =F64/1000 -> 0.014 | L64: =K64*H64 -> 175 | M64: Purchase Order
B65: None | C65: TAS | D65: All cost centers | E65: CFC-12 | F65: 0 | H65: =HLOOKUP(E65,Settings!$B$23:$G$24,2,FALSE) -> 12500 | I65: Non-Kyoto GHG | K65: =F65/1000 -> 0 | L65: =K65*H65 -> 0 | M65: Purchase Order
B66: None | H66: =HLOOKUP(E66,Settings!$B$23:$G$24,2,FALSE) -> #N/A | K66: =F66/1000 -> 0 | L66: =K66*H66 -> #N/A
B67: None | H67: =HLOOKUP(E67,Settings!$B$23:$G$24,2,FALSE) -> #N/A | K67: =F67/1000 -> 0 | L67: =K67*H67 -> #N/A
B68: Sum | L68: =_xlfn.AGGREGATE(9,6,L49:L67) -> 85633.728
B71: Fugitive (Non-energy product use)
B72: Emission Code | C72: Area | D72: Emission Source | E72: GHG | F72: Annual Consumption | H72: LHV | I72: Carbon Content | J72: ODU Factor | K72: Emission | M72: Data Source of Annaul Consumption
K73: GHG | L73: Total CO2e
F74: (kg) | H74: (TJ/ton) | I74: (ton C/TJ) | J74: - | K74: (kgCO2/y) | L74: (tCO2e/y)
B75: 1-F-27 | C75: Iron Making | D75: Non-energy product use (oil) | E75: CO2 | F75: 152840 | H75: 0.0402 | I75: 20 | J75: 0.2 | K75: =F75*H75*I75*J75*44/12 -> 90114.464 | L75: =K75/1000 -> 90.114464 | M75: Purchase Order
B76: 2-F-28 | C76: Steel Making | D76: Non-energy product use (oil) | E76: CO2 | F76: 428177 | H76: 0.0402 | I76: 20 | J76: 0.2 | K76: =F76*H76*I76*J76*44/12 -> 252453.16 | L76: =K76/1000 -> 252.45316 | M76: Purchase Order
B77: 3-F-29 | C77: Hot Rolling | D77: Non-energy product use (oil) | E77: CO2 | F77: 739855 | H77: 0.0402 | I77: 20 | J77: 0.2 | K77: =F77*H77*I77*J77*44/12 -> 436218.51 | L77: =K77/1000 -> 436.21851 | M77: Purchase Order
B78: 4-F-30 | C78: Cold Rolling | D78: Non-energy product use (oil) | E78: CO2 | F78: 1853460 | H78: 0.0402 | I78: 20 | J78: 0.2 | K78: =F78*H78*I78*J78*44/12 -> 1092800 | L78: =K78/1000 -> 1092.8 | M78: Purchase Order
B79: 5-F-31 | C79: Utility | D79: Non-energy product use (oil) | E79: CO2 | F79: 13202 | H79: 0.0402 | I79: 20 | J79: 0.2 | K79: =F79*H79*I79*J79*44/12 -> 7783.8992 | L79: =K79/1000 -> 7.7838992 | M79: Purchase Order
B80: 6-F-32 | C80: Transportation | D80: Non-energy product use (oil) | E80: CO2 | F80: 51256 | H80: 0.0402 | I80: 20 | J80: 0.2 | K80: =F80*H80*I80*J80*44/12 -> 30220.538 | L80: =K80/1000 -> 30.220538 | M80: Purchase Order
B81: 7-F-33 | C81: Maintenance | D81: Non-energy product use (oil) | E81: CO2 | F81: 19975 | H81: 0.0402 | I81: 20 | J81: 0.2 | K81: =F81*H81*I81*J81*44/12 -> 11777.26 | L81: =K81/1000 -> 11.77726 | M81: Purchase Order
B82: 9-F-34 | C82: TAS | D82: Non-energy product use (oil) | E82: CO2 | F82: 4370 | H82: 0.0402 | I82: 20 | J82: 0.2 | K82: =F82*H82*I82*J82*44/12 -> 2576.552 | L82: =K82/1000 -> 2.576552 | M82: Purchase Order
B83: 1-F-35 | C83: Iron Making | D83: Non-energy product use (grease) | E83: CO2 | F83: 107445 | H83: 0.0402 | I83: 20 | J83: 0.05 | K83: =F83*H83*I83*J83*44/12 -> 15837.393 | L83: =K83/1000 -> 15.837393 | M83: Purchase Order
B84: 2-F-36 | C84: Steel Making | D84: Non-energy product use (grease) | E84: CO2 | F84: 190484 | H84: 0.0402 | I84: 20 | J84: 0.05 | K84: =F84*H84*I84*J84*44/12 -> 28077.342 | L84: =K84/1000 -> 28.077342 | M84: Purchase Order
B85: 3-F-37 | C85: Hot Rolling | D85: Non-energy product use (grease) | E85: CO2 | F85: 247958 | H85: 0.0402 | I85: 20 | J85: 0.05 | K85: =F85*H85*I85*J85*44/12 -> 36549.009 | L85: =K85/1000 -> 36.549009 | M85: Purchase Order
B86: 4-F-38 | C86: Cold Rolling | D86: Non-energy product use (grease) | E86: CO2 | F86: 23034 | H86: 0.0402 | I86: 20 | J86: 0.05 | K86: =F86*H86*I86*J86*44/12 -> 3395.2116 | L86: =K86/1000 -> 3.3952116 | M86: Purchase Order
... B90: 9-F-42 | C90: TAS | D90: Non-energy product use (grease) | E90: CO2 | F90: 20 | H90: 0.0402 | I90: 20 | J90: 0.05 | K90: =F90*H90*I90*J90*44/12 -> 2.948 | L90: =K90/1000 -> 0.002948 | M90: Purchase Order
B91: Sum | L91: =_xlfn.AGGREGATE(9,6,L75:L90) -> 2009.1497
K95: Total Fugitive Emissions
K96: Area | L96: Emission
L97: (tCO2e/y)
K98: Iron Making | L98: =SUMIF($C$12:$C$41,K98,$L$12:$L$41)+SUMIF($C$49:$C$50,K98,$L$49:$L$50)+SUMIF($C$75:$C$90,K98,$L$75:$L$90) -> 437.19189
K99: Steel Making | L99: =SUMIF($C$12:$C$41,K99,$L$12:$L$41)+SUMIF($C$49:$C$50,K99,$L$49:$L$50)+SUMIF($C$75:$C$90,K99,$L$75:$L$90) -> 513.52953
K100: Hot Rolling | L100: =SUMIF($C$12:$C$41,K100,$L$12:$L$41)+SUMIF($C$49:$C$50,K100,$L$49:$L$50)+SUMIF($C$75:$C$90,K100,$L$75:$L$90) -> 649.28064
K101: Cold Rolling | L101: =SUMIF($C$12:$C$41,K101,$L$12:$L$41)+SUMIF($C$49:$C$50,K101,$L$49:$L$50)+SUMIF($C$75:$C$90,K101,$L$75:$L$90) -> 1338.8901
K102: Utility | L102: =SUMIF($C$12:$C$41,K102,$L$12:$L$41)+SUMIF($C$49:$C$50,K102,$L$49:$L$50)+SUMIF($C$75:$C$90,K102,$L$75:$L$90) -> 10470.41
K103: Transportation | L103: =SUMIF($C$12:$C$41,K103,$L$12:$L$41)+SUMIF($C$49:$C$50,K103,$L$49:$L$50)+SUMIF($C$75:$C$90,K103,$L$75:$L$90) -> 31.340778
K104: Maintenance | L104: =SUMIF($C$12:$C$41,K104,$L$12:$L$41)+SUMIF($C$49:$C$50,K104,$L$49:$L$50)+SUMIF($C$75:$C$90,K104,$L$75:$L$90) -> 105.64034
K105: TAS | L105: =SUMIF($C$12:$C$41,K105,$L$12:$L$41)+SUMIF($C$49:$C$50,K105,$L$49:$L$50)+SUMIF($C$75:$C$90,K105,$L$75:$L$90) -> 72.449276
K106: Sum | L106: =_xlfn.AGGREGATE(9,6,L98:L105) -> 13618.733
K108: Non-Kyoto GHGs | L108: =L68 -> 85633.728
I112: Methane Fugitive Emissions
I113: Emission Code | J113: Area | K113: CH4 | L113: Total CO2e
K114: (tCH4/y) | L114: (tCO2e/y)
I115: 1-F-17 | J115: Iron Making | K115: =SUMIF($C$12:$C$41,J115,$K$12:$K$41) -> 11.115437 | L115: =SUMIF($C$12:$C$41,J115,$L$12:$L$41) -> 331.24004
I116: 2-F-18 | J116: Steel Making | K116: =SUMIF($C$12:$C$41,J116,$K$12:$K$41) -> 7.8187593 | L116: =SUMIF($C$12:$C$41,J116,$L$12:$L$41) -> 232.99903
I117: 3-F-19 | J117: Hot Rolling | K117: =SUMIF($C$12:$C$41,J117,$K$12:$K$41) -> 5.923259 | L117: =SUMIF($C$12:$C$41,J117,$L$12:$L$41) -> 176.51312
I118: 4-F-20 | J118: Cold Rolling | K118: =SUMIF($C$12:$C$41,J118,$K$12:$K$41) -> 8.1441224 | L118: =SUMIF($C$12:$C$41,J118,$L$12:$L$41) -> 242.69485
I119: 5-F-21 | J119: Utility | K119: =SUMIF($C$12:$C$41,J119,$K$12:$K$41) -> 24.914493 | L119: =SUMIF($C$12:$C$41,J119,$L$12:$L$41) -> 742.45189
I120: 6-F-22 | J120: Transportation | K120: =SUMIF($C$12:$C$41,J120,$K$12:$K$41) -> 0 | L120: =SUMIF($C$12:$C$41,J120,$L$12:$L$41) -> 0
I121: 7-F-23 | J121: Maintenance | K121: =SUMIF($C$12:$C$41,J121,$K$12:$K$41) -> 1.575518 | L121: =SUMIF($C$12:$C$41,J121,$L$12:$L$41) -> 46.950437
I122: 9-F-24 | J122: TAS | K122: =SUMIF($C$12:$C$41,J122,$K$12:$K$41) -> 2.3446234 | L122: =SUMIF($C$12:$C$41,J122,$L$12:$L$41) -> 69.869776
I123: Sum | K123: =_xlfn.AGGREGATE(9,6,K115:K122) -> 61.836212 | L123: =_xlfn.AGGREGATE(9,6,L115:L122) -> 1842.7191

Sheet Electricity
B7: EF Calculation for Electricity
B8: Cost Item Code | C8: Cost Item | D8: Input Electricity | F8: Power Plant Type | H8: EF | K8: Emission of Input Electricity | N8: Data Source of Annaul Consumption
H9: CO2 | I9: CH4 | J9: N2O | K9: CO2 | L9: CH4 | M9: N2O
D10: (kWh/y) | H10: (g/kWh) | I10: (g/kWh) | J10: (g/kWh) | K10: (tCO2/y) | L10: (tCH4/y) | M10: (tN2O/y)
C11: Electricity from grid (Net) | D11: 3359544285 | F11: Total Average | H11: =VLOOKUP(F11,Settings!$B$110:$E$116,2,FALSE) -> 687.342 | I11: =VLOOKUP(F11,Settings!$B$110:$E$116,3,FALSE) -> 14 | J11: =VLOOKUP(F11,Settings!$B$110:$E$116,4,FALSE) -> 0.002 | K11: =D11*H11/1000000 -> 2309155.9 | L11: =D11*I11/1000000 -> 47033.62 | M11: =D11*J11/1000000 -> 6.7190886 | N11: Calculation
C12: Electricity from contract | D12: 1015200000 | F12: Direct Contract | H12: =VLOOKUP(F12,Settings!$B$110:$E$116,2,FALSE) -> 619.741 | I12: =VLOOKUP(F12,Settings!$B$110:$E$116,3,FALSE) -> 12 | J12: =VLOOKUP(F12,Settings!$B$110:$E$116,4,FALSE) -> 0.002 | K12: =D12*H12/1000000 -> 629161.06 | L12: =D12*I12/1000000 -> 12182.4 | M12: =D12*J12/1000000 -> 2.0304 | N12: Bill
C13: Electricity from Solar Plant | D13: 21819320 | F13: Solar | H13: =VLOOKUP(F13,Settings!$B$110:$E$116,2,FALSE) -> 0.0803154 | I13: =VLOOKUP(F13,Settings!$B$110:$E$116,3,FALSE) -> 0 | J13: =VLOOKUP(F13,Settings!$B$110:$E$116,4,FALSE) -> 0 | K13: =D13*H13/1000000 -> 1.7524274 | L13: =D13*I13/1000000 -> 0 | M13: =D13*J13/1000000 -> 0 | N13: Bill
B14: 51110 | C14: Electricity generated on-site 1 | D14: 1070502976 | F14: MSC Production | H14: =VLOOKUP(F14,Settings!$B$110:$E$116,2,FALSE) -> 0 | I14: =VLOOKUP(F14,Settings!$B$110:$E$116,3,FALSE) -> 0 | J14: =VLOOKUP(F14,Settings!$B$110:$E$116,4,FALSE) -> 0 | K14: =D14*H14/1000000 -> 0 | L14: =D14*I14/1000000 -> 0 | M14: =D14*J14/1000000 -> 0 | N14: SUM(ELEACT1&2&3)
B15: 51120 | C15: Electricity generated on-site 2 | D15: 549536612 | F15: MSC Production | H15: =VLOOKUP(F15,Settings!$B$110:$E$116,2,FALSE) -> 0 | I15: =VLOOKUP(F15,Settings!$B$110:$E$116,3,FALSE) -> 0 | J15: =VLOOKUP(F15,Settings!$B$110:$E$116,4,FALSE) -> 0 | K15: =D15*H15/1000000 -> 0 | L15: =D15*I15/1000000 -> 0 | M15: =D15*J15/1000000 -> 0 | N15: ELEACT4
B16: 51130 | C16: Electricity generated on-site 3 | D16: 1780192400 | F16: MSC Production | H16: =VLOOKUP(F16,Settings!$B$110:$E$116,2,FALSE) -> 0 | I16: =VLOOKUP(F16,Settings!$B$110:$E$116,3,FALSE) -> 0 | J16: =VLOOKUP(F16,Settings!$B$110:$E$116,4,FALSE) -> 0 | K16: =D16*H16/1000000 -> 0 | L16: =D16*I16/1000000 -> 0 | M16: =D16*J16/1000000 -> 0 | N16: ELEACT326
H17: =VLOOKUP(F17,Settings!$B$110:$E$116,2,FALSE) -> #N/A | I17: =VLOOKUP(F17,Settings!$B$110:$E$116,3,FALSE) -> #N/A | J17: =VLOOKUP(F17,Settings!$B$110:$E$116,4,FALSE) -> #N/A | K17: =D17*H17/1000000 -> #N/A | L17: =D17*I17/1000000 -> #N/A | M17: =D17*J17/1000000 -> #N/A
H18: =VLOOKUP(F18,Settings!$B$110:$E$116,2,FALSE) -> #N/A | I18: =VLOOKUP(F18,Settings!$B$110:$E$116,3,FALSE) -> #N/A | J18: =VLOOKUP(F18,Settings!$B$110:$E$116,4,FALSE) -> #N/A | K18: =D18*H18/1000000 -> #N/A | L18: =D18*I18/1000000 -> #N/A | M18: =D18*J18/1000000 -> #N/A
B19: Sum | D19: =SUM(D11:D18) -> 7796795593 | K19: =_xlfn.AGGREGATE(9,6,K11:K18) -> 2938318.7 | L19: =_xlfn.AGGREGATE(9,6,L11:L18) -> 59216.02 | M19: =_xlfn.AGGREGATE(9,6,M11:M18) -> 8.7494886
C20: Apportionment Factor | D20: =D19/F126 -> 1.0197104 | K20: EF
K21: CO2 | L21: CH4 | M21: N2O
K22: (tCO2/kWh) | L22: (tCH4/kWh) | M22: (tN2O/kWh)
K23: =K19/D19 -> 0.00037686235 | L23: =L19/D19 -> 7.5949176e-06 | M23: =M19/D19 -> 1.1221903e-09
B28: Electricity
B29: Area | C29: Unit Process | D29: Cost Center Code | E29: Cost Item Code | F29: Consumed Electricity | G29: EF | J29: Emisison | N29: Data Source of Annaul Consumption
G30: CO2 | H30: CH4 | I30: N2O | J30: CO2 | K30: CH4 | L30: N2O | M30: Total
F31: (kWh/y) | G31: (tCO2/kWh) | H31: (tCH4/kWh) | I31: (tN2O/kWh) | J31: (tCO2/y) | K31: (tCH4/y) | L31: (tN2O/y) | M31: (tCO2e/y)
B32: =VLOOKUP(D32,'Unit List'!$B$9:$E$241,4,0) -> Iron Making | C32: =VLOOKUP(D32,'Unit List'!$B$9:$D$241,3,0) -> Yard | D32: 1110 | E32: 54110 | F32: 56714353 | G32: =$K$23 -> 0.00037686235 | H32: =$L$23 -> 7.5949176e-06 | I32: =$M$23 -> 1.1221903e-09 | J32: =F32*G32*$D$20 -> 21794.785 | K32: =F32*H32*$D$20 -> 439.23093 | L32: =F32*I32*$D$20 -> 0.064898755 | M32: =L32*Settings!$D$24+Electricity!K32*Settings!$C$24+Electricity!J32 -> 33671.738 | N32: Estimation
B33: =VLOOKUP(D33,'Unit List'!$B$9:$E$241,4,0) -> Iron Making | C33: =VLOOKUP(D33,'Unit List'!$B$9:$D$241,3,0) -> Lime Making | D33: 1120 | E33: 54110 | F33: 7336275.3 | G33: =$K$23 -> 0.00037686235 | H33: =$L$23 -> 7.5949176e-06 | I33: =$M$23 -> 1.1221903e-09 | J33: =F33*G33*$D$20 -> 2819.2607 | K33: =F33*H33*$D$20 -> 56.816641 | L33: =F33*I33*$D$20 -> 0.0083949673 | M33: =L33*Settings!$D$24+Electricity!K33*Settings!$C$24+Electricity!J33 -> 4355.6018 | N33: Estimation
B34: =VLOOKUP(D34,'Unit List'!$B$9:$E$241,4,0) -> Iron Making | C34: =VLOOKUP(D34,'Unit List'!$B$9:$D$241,3,0) -> Lime Hydration | D34: 1130 | E34: 54110 | F34: 1915017.7 | G34: =$K$23 -> 0.00037686235 | H34: =$L$23 -> 7.5949176e-06 | I34: =$M$23 -> 1.1221903e-09 | J34: =F34*G34*$D$20 -> 735.92304 | K34: =F34*H34*$D$20 -> 14.831078 | L34: =F34*I34*$D$20 -> 0.0021913723 | M34: =L34*Settings!$D$24+Electricity!K34*Settings!$C$24+Electricity!J34 -> 1136.9604 | N34: Estimation
B35: =VLOOKUP(D35,'Unit List'!$B$9:$E$241,4,0) -> Iron Making | C35: =VLOOKUP(D35,'Unit List'!$B$9:$D$241,3,0) -> Dolomite Making | D35: 1140 | E35: 54110 | F35: 8703054 | G35: =$K$23 -> 0.00037686235 | H35: =$L$23 -> 7.5949176e-06 | I35: =$M$23 -> 1.1221903e-09 | J35: =F35*G35*$D$20 -> 3344.5007 | K35: =F35*H35*$D$20 -> 67.401818 | L35: =F35*I35*$D$20 -> 0.0099589847 | M35: =L35*Settings!$D$24+Electricity!K35*Settings!$C$24+Electricity!J35 -> 5167.0686 | N35: Estimation
B36: =VLOOKUP(D36,'Unit List'!$B$9:$E$241,4,0) -> Iron Making | C36: =VLOOKUP(D36,'Unit List'!$B$9:$D$241,3,0) -> Pelletizing | D36: 1210 | E36: 54110 | F36: 176322821 | G36: =$K$23 -> 0.00037686235 | H36: =$L$23 -> 7.5949176e-06 | I36: =$M$23 -> 1.1221903e-09 | J36: =F36*G36*$D$20 -> 67759.18 | K36: =F36*H36*$D$20 -> 1365.5527 | L36: =F36*I36*$D$20 -> 0.20176782 | M36: =L36*Settings!$D$24+Electricity!K36*Settings!$C$24+Electricity!J36 -> 104684.18 | N36: Estimation
B37: =VLOOKUP(D37,'Unit List'!$B$9:$E$241,4,0) -> Iron Making | C37: =VLOOKUP(D37,'Unit List'!$B$9:$D$241,3,0) -> Direct Reduction | D37: 1310 | E37: 54110 | F37: 4.3753899e+08 | G37: =$K$23 -> 0.00037686235 | H37: =$L$23 -> 7.5949176e-06 | I37: =$M$23 -> 1.1221903e-09 | J37: =F37*G37*$D$20 -> 168142.07 | K37: =F37*H37*$D$20 -> 3388.5718 | L37: =F37*I37*$D$20 -> 0.50067989 | M37: =L37*Settings!$D$24+Electricity!K37*Settings!$C$24+Electricity!J37 -> 259770.19 | N37: Estimation
B38: =VLOOKUP(D38,'Unit List'!$B$9:$E$241,4,0) -> Iron Making | C38: =VLOOKUP(D38,'Unit List'!$B$9:$D$241,3,0) -> Direct Reduction | D38: 1315 | E38: 54110 | F38: 2.4738028e+08 | G38: =$K$23 -> 0.00037686235 | H38: =$L$23 -> 7.5949176e-06 | I38: =$M$23 -> 1.1221903e-09 | J38: =F38*G38*$D$20 -> 95065.883 | K38: =F38*H38*$D$20 -> 1915.8654 | L38: =F38*I38*$D$20 -> 0.28307952 | M38: =L38*Settings!$D$24+Electricity!K38*Settings!$C$24+Electricity!J38 -> 146871.53 | N38: Estimation
B39: =VLOOKUP(D39,'Unit List'!$B$9:$E$241,4,0) -> Iron Making | C39: =VLOOKUP(D39,'Unit List'!$B$9:$D$241,3,0) -> Direct Reduction | D39: 1320 | E39: 54110 | F39: 54444897 | G39: =$K$23 -> 0.00037686235 | H39: =$L$23 -> 7.5949176e-06 | I39: =$M$23 -> 1.1221903e-09 | J39: =F39*G39*$D$20 -> 20922.655 | K39: =F39*H39*$D$20 -> 421.65486 | L39: =F39*I39*$D$20 -> 0.062301796 | M39: =L39*Settings!$D$24+Electricity!K39*Settings!$C$24+Electricity!J39 -> 32324.345 | N39: Estimation
B40: =VLOOKUP(D40,'Unit List'!$B$9:$E$241,4,0) -> Iron Making | C40: =VLOOKUP(D40,'Unit List'!$B$9:$D$241,3,0) -> Direct Reduction | D40: 1325 | E40: 54110 | F40: 21795619 | G40: =$K$23 -> 0.00037686235 | H40: =$L$23 -> 7.5949176e-06 | I40: =$M$23 -> 1.1221903e-09 | J40: =F40*G40*$D$20 -> 8375.8487 | K40: =F40*H40*$D$20 -> 168.79872 | L40: =F40*I40*$D$20 -> 0.024940927 | M40: =L40*Settings!$D$24+Electricity!K40*Settings!$C$24+Electricity!J40 -> 12940.223 | N40: Estimation
B41: =VLOOKUP(D41,'Unit List'!$B$9:$E$241,4,0) -> Iron Making | C41: =VLOOKUP(D41,'Unit List'!$B$9:$D$241,3,0) -> Briquetting | D41: 1330 | E41: 54110 | F41: 2969721.7 | G41: =$K$23 -> 0.00037686235 | H41: =$L$23 -> 7.5949176e-06 | I41: =$M$23 -> 1.1221903e-09 | J41: =F41*G41*$D$20 -> 1141.2357 | K41: =F41*H41*$D$20 -> 22.999356 | L41: =F41*I41*$D$20 -> 0.0033982798 | M41: =L41*Settings!$D$24+Electricity!K41*Settings!$C$24+Electricity!J41 -> 1763.1461 | N41: Estimation
B42: =VLOOKUP(D42,'Unit List'!$B$9:$E$241,4,0) -> Iron Making | C42: =VLOOKUP(D42,'Unit List'!$B$9:$D$241,3,0) -> Briquetting | D42: 1335 | E42: 54110 | F42: 3269342.8 | G42: =$K$23 -> 0.00037686235 | H42: =$L$23 -> 7.5949176e-06 | I42: =$M$23 -> 1.1221903e-09 | J42: =F42*G42*$D$20 -> 1256.3773 | K42: =F42*H42*$D$20 -> 25.319807 | L42: =F42*I42*$D$20 -> 0.0037411391 | M42: =L42*Settings!$D$24+Electricity!K42*Settings!$C$24+Electricity!J42 -> 1941.0334 | N42: Estimation
B43: =VLOOKUP(D43,'Unit List'!$B$9:$E$241,4,0) -> Steel Making | C43: =VLOOKUP(D43,'Unit List'!$B$9:$D$241,3,0) -> EAFs | D43: 2110 | E43: 54110 | F43: 5734270.2 | G43: =$K$23 -> 0.00037686235 | H43: =$L$23 -> 7.5949176e-06 | I43: =$M$23 -> 1.1221903e-09 | J43: =F43*G43*$D$20 -> 2203.6254 | K43: =F43*H43*$D$20 -> 44.409725 | L43: =F43*I43*$D$20 -> 0.0065617781 | M43: =L43*Settings!$D$24+Electricity!K43*Settings!$C$24+Electricity!J43 -> 3404.4794 | N43: Estimation
B44: =VLOOKUP(D44,'Unit List'!$B$9:$E$241,4,0) -> Steel Making | C44: =VLOOKUP(D44,'Unit List'!$B$9:$D$241,3,0) -> EAFs | D44: 2120 | E44: 54110 | F44: 7167837.8 | G44: =$K$23 -> 0.00037686235 | H44: =$L$23 -> 7.5949176e-06 | I44: =$M$23 -> 1.1221903e-09 | J44: =F44*G44*$D$20 -> 2754.5318 | K44: =F44*H44*$D$20 -> 55.512157 | L44: =F44*I44*$D$20 -> 0.0082022226 | M44: =L44*Settings!$D$24+Electricity!K44*Settings!$C$24+Electricity!J44 -> 4255.5992 | N44: Estimation
B45: =VLOOKUP(D45,'Unit List'!$B$9:$E$241,4,0) -> Steel Making | C45: =VLOOKUP(D45,'Unit List'!$B$9:$D$241,3,0) -> EAFs | D45: 2130 | E45: 54110 | F45: 86014054 | G45: =$K$23 -> 0.00037686235 | H45: =$L$23 -> 7.5949176e-06 | I45: =$M$23 -> 1.1221903e-09 | J45: =F45*G45*$D$20 -> 33054.381 | K45: =F45*H45*$D$20 -> 666.14588 | L45: =F45*I45*$D$20 -> 0.098426672 | M45: =L45*Settings!$D$24+Electricity!K45*Settings!$C$24+Electricity!J45 -> 51067.19 | N45: Estimation
B46: =VLOOKUP(D46,'Unit List'!$B$9:$E$241,4,0) -> Steel Making | C46: =VLOOKUP(D46,'Unit List'!$B$9:$D$241,3,0) -> EAFs | D46: 2210 | E46: 23140 | F46: 1.8779735e+08 | G46: =$K$23 -> 0.00037686235 | H46: =$L$23 -> 7.5949176e-06 | I46: =$M$23 -> 1.1221903e-09 | J46: =F46*G46*$D$20 -> 72168.732 | K46: =F46*H46*$D$20 -> 1454.4185 | L46: =F46*I46*$D$20 -> 0.21489823 | M46: =L46*Settings!$D$24+Electricity!K46*Settings!$C$24+Electricity!J46 -> 111496.7 | N46: Estimation
B47: =VLOOKUP(D47,'Unit List'!$B$9:$E$241,4,0) -> Steel Making | C47: =VLOOKUP(D47,'Unit List'!$B$9:$D$241,3,0) -> De-gassing | D47: 2220 | E47: 54110 | F47: 9697254.2 | G47: =$K$23 -> 0.00037686235 | H47: =$L$23 -> 7.5949176e-06 | I47: =$M$23 -> 1.1221903e-09 | J47: =F47*G47*$D$20 -> 3726.5624 | K47: =F47*H47*$D$20 -> 75.101518 | L47: =F47*I47*$D$20 -> 0.011096657 | M47: =L47*Settings!$D$24+Electricity!K47*Settings!$C$24+Electricity!J47 -> 5757.3328 | N47: Estimation
B48: =VLOOKUP(D48,'Unit List'!$B$9:$E$241,4,0) -> Steel Making | C48: =VLOOKUP(D48,'Unit List'!$B$9:$D$241,3,0) -> Laddle Furnaces | D48: 2240 | E48: 54110 | F48: 42782004 | G48: =$K$23 -> 0.00037686235 | H48: =$L$23 -> 7.5949176e-06 | I48: =$M$23 -> 1.1221903e-09 | J48: =F48*G48*$D$20 -> 16440.716 | K48: =F48*H48*$D$20 -> 331.33022 | L48: =F48*I48*$D$20 -> 0.04895584 | M48: =L48*Settings!$D$24+Electricity!K48*Settings!$C$24+Electricity!J48 -> 25399.998 | N48: Estimation
B49: =VLOOKUP(D49,'Unit List'!$B$9:$E$241,4,0) -> Steel Making | C49: =VLOOKUP(D49,'Unit List'!$B$9:$D$241,3,0) -> Laddle Furnaces | D49: 2301 | E49: 54110 | F49: 4563413.8 | G49: =$K$23 -> 0.00037686235 | H49: =$L$23 -> 7.5949176e-06 | I49: =$M$23 -> 1.1221903e-09 | J49: =F49*G49*$D$20 -> 1753.6764 | K49: =F49*H49*$D$20 -> 35.341891 | L49: =F49*I49*$D$20 -> 0.0052219563 | M49: =L49*Settings!$D$24+Electricity!K49*Settings!$C$24+Electricity!J49 -> 2709.3331 | N49: Estimation
B50: =VLOOKUP(D50,'Unit List'!$B$9:$E$241,4,0) -> Steel Making | C50: =VLOOKUP(D50,'Unit List'!$B$9:$D$241,3,0) -> Casting Machines | D50: 2410 | E50: 54110 | F50: 95888702 | G50: =$K$23 -> 0.00037686235 | H50: =$L$23 -> 7.5949176e-06 | I50: =$M$23 -> 1.1221903e-09 | J50: =F50*G50*$D$20 -> 36849.115 | K50: =F50*H50*$D$20 -> 742.62125 | L50: =F50*I50*$D$20 -> 0.10972632 | M50: =L50*Settings!$D$24+Electricity!K50*Settings!$C$24+Electricity!J50 -> 56929.843 | N50: Estimation
B51: =VLOOKUP(D51,'Unit List'!$B$9:$E$241,4,0) -> Steel Making | C51: =VLOOKUP(D51,'Unit List'!$B$9:$D$241,3,0) -> Slab Cooling | D51: 2510 | E51: 54110 | F51: 35976826 | G51: =$K$23 -> 0.00037686235 | H51: =$L$23 -> 7.5949176e-06 | I51: =$M$23 -> 1.1221903e-09 | J51: =F51*G51*$D$20 -> 13825.551 | K51: =F51*H51*$D$20 -> 278.62673 | L51: =F51*I51*$D$20 -> 0.041168613 | M51: =L51*Settings!$D$24+Electricity!K51*Settings!$C$24+Electricity!J51 -> 21359.712 | N51: Estimation
... B115: =VLOOKUP(D115,'Unit List'!$B$9:$E$241,4,0) -> Maintenance | C115: =VLOOKUP(D115,'Unit List'!$B$9:$D$241,3,0) -> - | D115: 7340 | E115: 54110 | F115: 1499730.1 | G115: =$K$23 -> 0.00037686235 | H115: =$L$23 -> 7.5949176e-06 | I115: =$M$23 -> 1.1221903e-09 | J115: =F115*G115*$D$20 -> 576.33197 | K115: =F115*H115*$D$20 -> 11.614834 | L115: =F115*I115*$D$20 -> 0.0017161549 | M115: =L115*Settings!$D$24+Electricity!K115*Settings!$C$24+Electricity!J115 -> 890.40101 | N115: Estimation
B116: =VLOOKUP(D116,'Unit List'!$B$9:$E$241,4,0) -> Maintenance | C116: =VLOOKUP(D116,'Unit List'!$B$9:$D$241,3,0) -> - | D116: 7360 | E116: 54110 | F116: 1285482.9 | G116: =$K$23 -> 0.00037686235 | H116: =$L$23 -> 7.5949176e-06 | I116: =$M$23 -> 1.1221903e-09 | J116: =F116*G116*$D$20 -> 493.99883 | K116: =F116*H116*$D$20 -> 9.9555724 | L116: =F116*I116*$D$20 -> 0.0014709899 | M116: =L116*Settings!$D$24+Electricity!K116*Settings!$C$24+Electricity!J116 -> 763.20086 | N116: Estimation
B117: =VLOOKUP(D117,'Unit List'!$B$9:$E$241,4,0) -> TAS | C117: =VLOOKUP(D117,'Unit List'!$B$9:$D$241,3,0) -> - | D117: 9595 | E117: 54110 | F117: 2668971 | G117: =$K$23 -> 0.00037686235 | H117: =$L$23 -> 7.5949176e-06 | I117: =$M$23 -> 1.1221903e-09 | J117: =F117*G117*$D$20 -> 1025.6601 | K117: =F117*H117*$D$20 -> 20.670158 | L117: =F117*I117*$D$20 -> 0.003054128 | M117: =L117*Settings!$D$24+Electricity!K117*Settings!$C$24+Electricity!J117 -> 1584.5882 | N117: Estimation
B118: =VLOOKUP(D118,'Unit List'!$B$9:$E$241,4,0) -> Steel Making | C118: =VLOOKUP(D118,'Unit List'!$B$9:$D$241,3,0) -> EAFs | D118: 2210 | E118: 23140 | F118: 4667188901 | G118: =$K$23 -> 0.00037686235 | H118: =$L$23 -> 7.5949176e-06 | I118: =$M$23 -> 1.1221903e-09 | J118: =F118*G118*$D$20 -> 1793556.2 | K118: =F118*H118*$D$20 -> 36145.589 | L118: =F118*I118*$D$20 -> 5.3407071 | M118: =L118*Settings!$D$24+Electricity!K118*Settings!$C$24+Electricity!J118 -> 2770945.1
B119: =VLOOKUP(D119,'Unit List'!$B$9:$E$241,4,0) -> Steel Making | C119: =VLOOKUP(D119,'Unit List'!$B$9:$D$241,3,0) -> Laddle Furnaces | D119: 2240 | E119: 23140 | F119: 149846198 | G119: =$K$23 -> 0.00037686235 | H119: =$L$23 -> 7.5949176e-06 | I119: =$M$23 -> 1.1221903e-09 | J119: =F119*G119*$D$20 -> 57584.466 | K119: =F119*H119*$D$20 -> 1160.5014 | L119: =F119*I119*$D$20 -> 0.17147038 | M119: =L119*Settings!$D$24+Electricity!K119*Settings!$C$24+Electricity!J119 -> 88964.815
B120: =VLOOKUP(D120,'Unit List'!$B$9:$E$241,4,0) -> #N/A | C120: =VLOOKUP(D120,'Unit List'!$B$9:$D$241,3,0) -> #N/A | G120: =$K$23 -> 0.00037686235 | H120: =$L$23 -> 7.5949176e-06 | I120: =$M$23 -> 1.1221903e-09 | J120: =F120*G120*$D$20 -> 0 | K120: =F120*H120*$D$20 -> 0 | L120: =F120*I120*$D$20 -> 0 | M120: =L120*Settings!$D$24+Electricity!K120*Settings!$C$24+Electricity!J120 -> 0
B121: =VLOOKUP(D121,'Unit List'!$B$9:$E$241,4,0) -> #N/A | C121: =VLOOKUP(D121,'Unit List'!$B$9:$D$241,3,0) -> #N/A | G121: =$K$23 -> 0.00037686235 | H121: =$L$23 -> 7.5949176e-06 | I121: =$M$23 -> 1.1221903e-09 | J121: =F121*G121*$D$20 -> 0 | K121: =F121*H121*$D$20 -> 0 | L121: =F121*I121*$D$20 -> 0 | M121: =L121*Settings!$D$24+Electricity!K121*Settings!$C$24+Electricity!J121 -> 0
B122: =VLOOKUP(D122,'Unit List'!$B$9:$E$241,4,0) -> #N/A | C122: =VLOOKUP(D122,'Unit List'!$B$9:$D$241,3,0) -> #N/A | G122: =$K$23 -> 0.00037686235 | H122: =$L$23 -> 7.5949176e-06 | I122: =$M$23 -> 1.1221903e-09 | J122: =F122*G122*$D$20 -> 0 | K122: =F122*H122*$D$20 -> 0 | L122: =F122*I122*$D$20 -> 0 | M122: =L122*Settings!$D$24+Electricity!K122*Settings!$C$24+Electricity!J122 -> 0
B123: =VLOOKUP(D123,'Unit List'!$B$9:$E$241,4,0) -> #N/A | C123: =VLOOKUP(D123,'Unit List'!$B$9:$D$241,3,0) -> #N/A | G123: =$K$23 -> 0.00037686235 | H123: =$L$23 -> 7.5949176e-06 | I123: =$M$23 -> 1.1221903e-09 | J123: =F123*G123*$D$20 -> 0 | K123: =F123*H123*$D$20 -> 0 | L123: =F123*I123*$D$20 -> 0 | M123: =L123*Settings!$D$24+Electricity!K123*Settings!$C$24+Electricity!J123 -> 0
B124: =VLOOKUP(D124,'Unit List'!$B$9:$E$241,4,0) -> #N/A | C124: =VLOOKUP(D124,'Unit List'!$B$9:$D$241,3,0) -> #N/A | G124: =$K$23 -> 0.00037686235 | H124: =$L$23 -> 7.5949176e-06 | I124: =$M$23 -> 1.1221903e-09 | J124: =F124*G124*$D$20 -> 0 | K124: =F124*H124*$D$20 -> 0 | L124: =F124*I124*$D$20 -> 0 | M124: =L124*Settings!$D$24+Electricity!K124*Settings!$C$24+Electricity!J124 -> 0
